Workbook
Name _100X2.5MM_UV_Cable_Tie_Black: 'Master Data'!$Y$4:$Y$74
Name _38x50_OD_DWC_Pipe__500MTR__UV___Anti_Rodent: 'Master Data'!$AM$4:$AM$74
Name _3CX240Sqmm_A2XFY_19_33KV_HT_Cable: 'Master Data'!$L$4:$L$74
Name _3CX240Sqmm_A2XFY_UNSCR_ATR_UV_AF_3.3_KV: 'Master Data'!$K$4:$K$74
Name AC_Cables: 'Master Data'!$K$3:$K$74
Name Assets: 'Master Data'!$G$3:$AR$74
Name Aux_Control_Cable: 'Master Data'!$N$3:$N$74
Name Aux_UPS_Panel: 'Master Data'!$AD$3:$AD$74
Name bala: 'Master Data'!$AO$20:$AO$60
Name Battery: 'Master Data'!$G$3:$G$74
Name Bus_Duct: 'Master Data'!$H$3:$H$74
Name Cable_Glands: 'Master Data'!$T$3:$T$74
Name Cable_Lugs: 'Master Data'!$V$3:$V$74
Name Cable_Route_Marker: 'Master Data'!$X$3:$X$74
Name Cable_Sleeve: 'Master Data'!$W$3:$W$74
Name Cable_Termination_Kit: 'Master Data'!$U$3:$U$74
Name Cable_Tie: 'Master Data'!$Y$3:$Y$74
Name Cable_Tray: 'Master Data'!$I$3:$I$74
Name Cables: 'Master Data'!$N$3:$N$74
Name Catagory: 'Master Data'!$B$3:$B$10
Name CCTV: 'Master Data'!$P$3:$P$74
Name Civil: 'Master Data'!$Q$3:$Q$74
Name Column_C_120x50x15x1493x2mm_Thick: 'Master Data'!$AJ$4:$AJ$60
Name Column_Post___140x50x20x2.0_MM: 'Master Data'!$AJ$4:$AJ$74
Name Communication_Cable: 'Master Data'!$O$3:$O$74
Name Conductors: 'Master Data'!$R$3:$R$74
Name Connectors: 'Master Data'!$S$3:$S$74
Name Control_Cable: 'Master Data'!$V$3:$V$74
Name CT___PT: 'Master Data'!#REF!
Name CT_PT: 'Master Data'!#REF!
Name DC_Cable: 'Master Data'!$J$4:$J$74
Name DC_Cables: 'Master Data'!$J$3:$J$74
Name Earthing: 'Master Data'!$AE$3:$AE$74
Name Earthing_cables: 'Master Data'!$M$3:$M$74
Name Earthing_Strip: 'Master Data'!$AE$4:$AE$74
Name ESE_Train: 'Master Data'!$AH$4:$AH$74
Name Fencing: 'Master Data'!$AF$3:$AF$74
Name Gland: 'Master Data'!#REF!
Name HEX_BOLT_NUT_2PLN_WSR_1SP_WSR_M_16x40: 'Master Data'!$AK$4:$AK$74
Name HT_Cables: 'Master Data'!$L$3:$L$74
Name HT_Panel: 'Master Data'!$AB$3:$AB$74
Name Inverter: 'Master Data'!$Z$3:$Z$74
Name Inverter_Column_Post__ISMC___100x50x5mm___3000mmL: 'Master Data'!$AG$4:$AG$74
Name Inverters: 'Master Data'!$AG$3:$AG$74
Name Inverters_Structure: 'Master Data'!$AG$3:$AG$74
Name Lighting_arrestor: 'Master Data'!$AH$3:$AH$74
Name Location: 'Master Data'!$B$32:$B$38
Name LT_Panel: 'Master Data'!$AC$3:$AC$74
Name M16x40mm_B_N_2PW_1SW_HDG_8.8: 'Master Data'!$AK$4:$AK$60
Name MCS: 'Master Data'!$R$3:$R$74
Name MMS_Fasteners: 'Master Data'!$AK$3:$AK$74
Name Module_Mounting_Structure: 'Master Data'!$AJ$3:$AJ$74
Name NIFPS: 'Master Data'!$AL$3:$AL$74
Name Others: 'Master Data'!$AP$3:$AP$74
Name Pipes: 'Master Data'!$AM$3:$AM$74
Name Price: 'Master Data'!$D$15:$D$16
Name Safety_Equipments: 'Master Data'!$AO$3:$AO$74
Name Sand_Bucket_With_Stend__canopy: 'Master Data'!$AO$4:$AO$74
Name Scada: 'Master Data'!$AR$3:$AR$74
Name Solar_Modules: 'Master Data'!$AN$3:$AN$74

Sheet Recon-Statement
A2: DATE | B2: =TODAY() -> 45634 | E2: BOQ VS RECEIVED | J2: RECEIVED VS STOCK
A3: S.No | B3: Item Description | C3: Make / Vendor | D3: Unit | E3: BOQ | F3: Received | G3: Yet to Receive | H3: Excess Received | I3: Column3 | J3: Received. | K3: Issued | L3: Theoretical Stock | M3: Column32 | N3: Remarks
A4: =BOQ[[#This Row],[S.No]] -> A | B4: =BOQ[[#This Row],[Item Description]] -> Module_Mounting_Structure | C4: =BOQ[[#This Row],[Make / Vendor]] -> 0 | D4: =BOQ[[#This Row],[Unit]] -> 0 | F4: =SUMIF('Goods Receipt'!$J:$J,Over_all[[#This Row],[Item Description]],'Goods Receipt'!$M:$M) -> 0 | H4: =IF(Over_all[[#This Row],[BOQ]]-Over_all[[#This Row],[Received]]<0,Over_all[[#This Row],[BOQ]]-Over_all[[#This Row],[Received]],"") | K4: =SUMIF(ISSUE!$F:$F,Over_all[[#This Row],[Item Description]],ISSUE!$I:$I) -> 0 | L4: =Over_all[[#This Row],[Received.]]-Over_all[[#This Row],[Issued]] -> 0
A5: =BOQ[[#This Row],[S.No]] -> 1 | B5: =BOQ[[#This Row],[Item Description]] -> Column Post - 120x50x20x2.0 MM | C5: =BOQ[[#This Row],[Make / Vendor]] -> 0 | D5: =BOQ[[#This Row],[Unit]] -> Nos | E5: =BOQ[[#This Row],[BOQ]] -> 4434 | F5: =SUMIF('Goods Receipt'!$J:$J,Over_all[[#This Row],[Item Description]],'Goods Receipt'!$M:$M) -> 4493 | G5: =IF(Over_all[[#This Row],[BOQ]]-Over_all[[#This Row],[Received]]>=0,Over_all[[#This Row],[BOQ]]-Over_all[[#This Row],[Received]],"") | H5: =IF(Over_all[[#This Row],[BOQ]]-Over_all[[#This Row],[Received]]<0,Over_all[[#This Row],[BOQ]]-Over_all[[#This Row],[Received]],"") -> -59 | J5: =Over_all[[#This Row],[Received]] -> 4493 | K5: =SUMIF(ISSUE!$F:$F,Over_all[[#This Row],[Item Description]],ISSUE!$I:$I) -> 2549 | L5: =Over_all[[#This Row],[Received.]]-Over_all[[#This Row],[Issued]] -> 1944
A6: =BOQ[[#This Row],[S.No]] -> 2 | B6: =BOQ[[#This Row],[Item Description]] -> Column Ext - 50x50x2.0 MM | C6: =BOQ[[#This Row],[Make / Vendor]] -> 0 | D6: =BOQ[[#This Row],[Unit]] -> Nos | E6: =BOQ[[#This Row],[BOQ]] -> 4434 | F6: =SUMIF('Goods Receipt'!$J:$J,Over_all[[#This Row],[Item Description]],'Goods Receipt'!$M:$M) -> 4409 | G6: =IF(Over_all[[#This Row],[BOQ]]-Over_all[[#This Row],[Received]]>=0,Over_all[[#This Row],[BOQ]]-Over_all[[#This Row],[Received]],"") -> 25 | H6: =IF(Over_all[[#This Row],[BOQ]]-Over_all[[#This Row],[Received]]<0,Over_all[[#This Row],[BOQ]]-Over_all[[#This Row],[Received]],"") | J6: =Over_all[[#This Row],[Received]] -> 4409 | K6: =SUMIF(ISSUE!$F:$F,Over_all[[#This Row],[Item Description]],ISSUE!$I:$I) -> 2528 | L6: =Over_all[[#This Row],[Received.]]-Over_all[[#This Row],[Issued]] -> 1881
A7: =BOQ[[#This Row],[S.No]] -> 3 | B7: =BOQ[[#This Row],[Item Description]] -> Module Mounting Strucyure - Purlin (P1) | C7: =BOQ[[#This Row],[Make / Vendor]] -> 0 | D7: =BOQ[[#This Row],[Unit]] -> Nos | E7: =BOQ[[#This Row],[BOQ]] -> 5912 | F7: =SUMIF('Goods Receipt'!$J:$J,Over_all[[#This Row],[Item Description]],'Goods Receipt'!$M:$M) -> 5990 | G7: =IF(Over_all[[#This Row],[BOQ]]-Over_all[[#This Row],[Received]]>=0,Over_all[[#This Row],[BOQ]]-Over_all[[#This Row],[Received]],"") | H7: =IF(Over_all[[#This Row],[BOQ]]-Over_all[[#This Row],[Received]]<0,Over_all[[#This Row],[BOQ]]-Over_all[[#This Row],[Received]],"") -> -78 | J7: =Over_all[[#This Row],[Received]] -> 5990 | K7: =SUMIF(ISSUE!$F:$F,Over_all[[#This Row],[Item Description]],ISSUE!$I:$I) -> 0 | L7: =Over_all[[#This Row],[Received.]]-Over_all[[#This Row],[Issued]] -> 5990
A8: =BOQ[[#This Row],[S.No]] -> 4 | B8: =BOQ[[#This Row],[Item Description]] -> Module Mounting Strucyure - Rafter | C8: =BOQ[[#This Row],[Make / Vendor]] -> 0 | D8: =BOQ[[#This Row],[Unit]] -> Nos | E8: =BOQ[[#This Row],[BOQ]] -> 4434 | F8: =SUMIF('Goods Receipt'!$J:$J,Over_all[[#This Row],[Item Description]],'Goods Receipt'!$M:$M) -> 4488 | G8: =IF(Over_all[[#This Row],[BOQ]]-Over_all[[#This Row],[Received]]>=0,Over_all[[#This Row],[BOQ]]-Over_all[[#This Row],[Received]],"") | H8: =IF(Over_all[[#This Row],[BOQ]]-Over_all[[#This Row],[Received]]<0,Over_all[[#This Row],[BOQ]]-Over_all[[#This Row],[Received]],"") -> -54 | J8: =Over_all[[#This Row],[Received]] -> 4488 | K8: =SUMIF(ISSUE!$F:$F,Over_all[[#This Row],[Item Description]],ISSUE!$I:$I) -> 1090 | L8: =Over_all[[#This Row],[Received.]]-Over_all[[#This Row],[Issued]] -> 3398
A9: =BOQ[[#This Row],[S.No]] -> 5 | B9: =BOQ[[#This Row],[Item Description]] -> Module Mounting Strucyure - Rafter Bracing Back | C9: =BOQ[[#This Row],[Make / Vendor]] -> 0 | D9: =BOQ[[#This Row],[Unit]] -> Nos | E9: =BOQ[[#This Row],[BOQ]] -> 4434 | F9: =SUMIF('Goods Receipt'!$J:$J,Over_all[[#This Row],[Item Description]],'Goods Receipt'!$M:$M) -> 4494 | G9: =IF(Over_all[[#This Row],[BOQ]]-Over_all[[#This Row],[Received]]>=0,Over_all[[#This Row],[BOQ]]-Over_all[[#This Row],[Received]],"") | H9: =IF(Over_all[[#This Row],[BOQ]]-Over_all[[#This Row],[Received]]<0,Over_all[[#This Row],[BOQ]]-Over_all[[#This Row],[Received]],"") -> -60 | J9: =Over_all[[#This Row],[Received]] -> 4494 | K9: =SUMIF(ISSUE!$F:$F,Over_all[[#This Row],[Item Description]],ISSUE!$I:$I) -> 1090 | L9: =Over_all[[#This Row],[Received.]]-Over_all[[#This Row],[Issued]] -> 3404
A10: =BOQ[[#This Row],[S.No]] -> 6 | B10: =BOQ[[#This Row],[Item Description]] -> Module Mounting Strucyure - Bracing Connector | C10: =BOQ[[#This Row],[Make / Vendor]] -> 0 | D10: =BOQ[[#This Row],[Unit]] -> Nos | E10: =BOQ[[#This Row],[BOQ]] -> 4434 | F10: =SUMIF('Goods Receipt'!$J:$J,Over_all[[#This Row],[Item Description]],'Goods Receipt'!$M:$M) -> 4536 | G10: =IF(Over_all[[#This Row],[BOQ]]-Over_all[[#This Row],[Received]]>=0,Over_all[[#This Row],[BOQ]]-Over_all[[#This Row],[Received]],"") | H10: =IF(Over_all[[#This Row],[BOQ]]-Over_all[[#This Row],[Received]]<0,Over_all[[#This Row],[BOQ]]-Over_all[[#This Row],[Received]],"") -> -102 | J10: =Over_all[[#This Row],[Received]] -> 4536 | K10: =SUMIF(ISSUE!$F:$F,Over_all[[#This Row],[Item Description]],ISSUE!$I:$I) -> 0 | L10: =Over_all[[#This Row],[Received.]]-Over_all[[#This Row],[Issued]] -> 4536
A11: =BOQ[[#This Row],[S.No]] -> 7 | B11: =BOQ[[#This Row],[Item Description]] -> Module Mounting Strucyure - Purlin (P2) | C11: =BOQ[[#This Row],[Make / Vendor]] -> 0 | D11: =BOQ[[#This Row],[Unit]] -> Nos | E11: =BOQ[[#This Row],[BOQ]] -> 2956 | F11: =SUMIF('Goods Receipt'!$J:$J,Over_all[[#This Row],[Item Description]],'Goods Receipt'!$M:$M) -> 2995 | G11: =IF(Over_all[[#This Row],[BOQ]]-Over_all[[#This Row],[Received]]>=0,Over_all[[#This Row],[BOQ]]-Over_all[[#This Row],[Received]],"") | H11: =IF(Over_all[[#This Row],[BOQ]]-Over_all[[#This Row],[Received]]<0,Over_all[[#This Row],[BOQ]]-Over_all[[#This Row],[Received]],"") -> -39 | J11: =Over_all[[#This Row],[Received]] -> 2995 | K11: =SUMIF(ISSUE!$F:$F,Over_all[[#This Row],[Item Description]],ISSUE!$I:$I) -> 0 | L11: =Over_all[[#This Row],[Received.]]-Over_all[[#This Row],[Issued]] -> 2995
A12: =BOQ[[#This Row],[S.No]] -> 8 | B12: =BOQ[[#This Row],[Item Description]] -> Module Mounting Strucyure - Col, to Rafter Bracing front | C12: =BOQ[[#This Row],[Make / Vendor]] -> 0 | D12: =BOQ[[#This Row],[Unit]] -> Nos | E12: =BOQ[[#This Row],[BOQ]] -> 4434 | F12: =SUMIF('Goods Receipt'!$J:$J,Over_all[[#This Row],[Item Description]],'Goods Receipt'!$M:$M) -> 4200 | G12: =IF(Over_all[[#This Row],[BOQ]]-Over_all[[#This Row],[Received]]>=0,Over_all[[#This Row],[BOQ]]-Over_all[[#This Row],[Received]],"") -> 234 | H12: =IF(Over_all[[#This Row],[BOQ]]-Over_all[[#This Row],[Received]]<0,Over_all[[#This Row],[BOQ]]-Over_all[[#This Row],[Received]],"") | J12: =Over_all[[#This Row],[Received]] -> 4200 | K12: =SUMIF(ISSUE!$F:$F,Over_all[[#This Row],[Item Description]],ISSUE!$I:$I) -> 1090 | L12: =Over_all[[#This Row],[Received.]]-Over_all[[#This Row],[Issued]] -> 3110
A13: =BOQ[[#This Row],[S.No]] -> 9 | B13: =BOQ[[#This Row],[Item Description]] -> Module Mounting Strucyure - Stay Bracing | C13: =BOQ[[#This Row],[Make / Vendor]] -> 0 | D13: =BOQ[[#This Row],[Unit]] -> Nos | E13: =BOQ[[#This Row],[BOQ]] -> 1478 | F13: =SUMIF('Goods Receipt'!$J:$J,Over_all[[#This Row],[Item Description]],'Goods Receipt'!$M:$M) -> 1498 | G13: =IF(Over_all[[#This Row],[BOQ]]-Over_all[[#This Row],[Received]]>=0,Over_all[[#This Row],[BOQ]]-Over_all[[#This Row],[Received]],"") | H13: =IF(Over_all[[#This Row],[BOQ]]-Over_all[[#This Row],[Received]]<0,Over_all[[#This Row],[BOQ]]-Over_all[[#This Row],[Received]],"") -> -20 | J13: =Over_all[[#This Row],[Received]] -> 1498 | K13: =SUMIF(ISSUE!$F:$F,Over_all[[#This Row],[Item Description]],ISSUE!$I:$I) -> 0 | L13: =Over_all[[#This Row],[Received.]]-Over_all[[#This Row],[Issued]] -> 1498
A14: =BOQ[[#This Row],[S.No]] -> 0 | B14: =BOQ[[#This Row],[Item Description]] -> 0 | C14: =BOQ[[#This Row],[Make / Vendor]] -> 0 | D14: =BOQ[[#This Row],[Unit]] -> 0 | E14: =BOQ[[#This Row],[BOQ]] -> 0 | F14: =SUMIF('Goods Receipt'!$J:$J,Over_all[[#This Row],[Item Description]],'Goods Receipt'!$M:$M) -> 0 | G14: =IF(Over_all[[#This Row],[BOQ]]-Over_all[[#This Row],[Received]]>=0,Over_all[[#This Row],[BOQ]]-Over_all[[#This Row],[Received]],"") -> 0 | H14: =IF(Over_all[[#This Row],[BOQ]]-Over_all[[#This Row],[Received]]<0,Over_all[[#This Row],[BOQ]]-Over_all[[#This Row],[Received]],"") | J14: =Over_all[[#This Row],[Received]] -> 0 | K14: =SUMIF(ISSUE!$F:$F,Over_all[[#This Row],[Item Description]],ISSUE!$I:$I) -> 0 | L14: =Over_all[[#This Row],[Received.]]-Over_all[[#This Row],[Issued]] -> 0
A15: =BOQ[[#This Row],[S.No]] -> B | B15: =BOQ[[#This Row],[Item Description]] -> MMS_Fasteners | C15: =BOQ[[#This Row],[Make / Vendor]] -> 0 | D15: =BOQ[[#This Row],[Unit]] -> 0 | E15: =BOQ[[#This Row],[BOQ]] -> 0 | F15: =SUMIF('Goods Receipt'!$J:$J,Over_all[[#This Row],[Item Description]],'Goods Receipt'!$M:$M) -> 0 | G15: =IF(Over_all[[#This Row],[BOQ]]-Over_all[[#This Row],[Received]]>=0,Over_all[[#This Row],[BOQ]]-Over_all[[#This Row],[Received]],"") -> 0 | H15: =IF(Over_all[[#This Row],[BOQ]]-Over_all[[#This Row],[Received]]<0,Over_all[[#This Row],[BOQ]]-Over_all[[#This Row],[Received]],"") | J15: =Over_all[[#This Row],[Received]] -> 0 | K15: =SUMIF(ISSUE!$F:$F,Over_all[[#This Row],[Item Description]],ISSUE!$I:$I) -> 0 | L15: =Over_all[[#This Row],[Received.]]-Over_all[[#This Row],[Issued]] -> 0
A16: =BOQ[[#This Row],[S.No]] -> 1 | B16: =BOQ[[#This Row],[Item Description]] -> HEX BOLT+NUT+2PLN WSR+1SP WSR M-16x40 | C16: =BOQ[[#This Row],[Make / Vendor]] -> 0 | D16: =BOQ[[#This Row],[Unit]] -> Set | E16: =BOQ[[#This Row],[BOQ]] -> 4434 | F16: =SUMIF('Goods Receipt'!$J:$J,Over_all[[#This Row],[Item Description]],'Goods Receipt'!$M:$M) -> 4290 | G16: =IF(Over_all[[#This Row],[BOQ]]-Over_all[[#This Row],[Received]]>=0,Over_all[[#This Row],[BOQ]]-Over_all[[#This Row],[Received]],"") -> 144 | H16: =IF(Over_all[[#This Row],[BOQ]]-Over_all[[#This Row],[Received]]<0,Over_all[[#This Row],[BOQ]]-Over_all[[#This Row],[Received]],"") | J16: =Over_all[[#This Row],[Received]] -> 4290 | K16: =SUMIF(ISSUE!$F:$F,Over_all[[#This Row],[Item Description]],ISSUE!$I:$I) -> 2000 | L16: =Over_all[[#This Row],[Received.]]-Over_all[[#This Row],[Issued]] -> 2290
... A26: =BOQ[[#This Row],[S.No]] -> 0 | B26: =BOQ[[#This Row],[Item Description]] -> 0 | C26: =BOQ[[#This Row],[Make / Vendor]] -> 0 | D26: =BOQ[[#This Row],[Unit]] -> 0 | E26: =BOQ[[#This Row],[BOQ]] -> 0 | F26: =SUMIF('Goods Receipt'!$J:$J,Over_all[[#This Row],[Item Description]],'Goods Receipt'!$M:$M) -> 0 | G26: =IF(Over_all[[#This Row],[BOQ]]-Over_all[[#This Row],[Received]]>=0,Over_all[[#This Row],[BOQ]]-Over_all[[#This Row],[Received]],"") -> 0 | H26: =IF(Over_all[[#This Row],[BOQ]]-Over_all[[#This Row],[Received]]<0,Over_all[[#This Row],[BOQ]]-Over_all[[#This Row],[Received]],"") | J26: =Over_all[[#This Row],[Received]] -> 0 | K26: =SUMIF(ISSUE!$F:$F,Over_all[[#This Row],[Item Description]],ISSUE!$I:$I) -> 0 | L26: =Over_all[[#This Row],[Received.]]-Over_all[[#This Row],[Issued]] -> 0
A27: =BOQ[[#This Row],[S.No]] -> C | B27: =BOQ[[#This Row],[Item Description]] -> Solar_Modules | C27: =BOQ[[#This Row],[Make / Vendor]] -> 0 | D27: Nos | E27: 20692 | F27: =SUMIF('Goods Receipt'!$J:$J,Over_all[[#This Row],[Item Description]],'Goods Receipt'!$M:$M) -> 0 | G27: =IF(Over_all[[#This Row],[BOQ]]-Over_all[[#This Row],[Received]]>=0,Over_all[[#This Row],[BOQ]]-Over_all[[#This Row],[Received]],"") -> 20692 | H27: =IF(Over_all[[#This Row],[BOQ]]-Over_all[[#This Row],[Received]]<0,Over_all[[#This Row],[BOQ]]-Over_all[[#This Row],[Received]],"") | J27: =Over_all[[#This Row],[Received]] -> 0 | K27: =SUMIF(ISSUE!$F:$F,Over_all[[#This Row],[Item Description]],ISSUE!$I:$I) -> 0 | L27: =Over_all[[#This Row],[Received.]]-Over_all[[#This Row],[Issued]] -> 0
A28: =BOQ[[#This Row],[S.No]] -> 0 | B28: =BOQ[[#This Row],[Item Description]] -> 0 | C28: =BOQ[[#This Row],[Make / Vendor]] -> 0 | F28: =SUMIF('Goods Receipt'!$J:$J,Over_all[[#This Row],[Item Description]],'Goods Receipt'!$M:$M) -> 0 | G28: =IF(Over_all[[#This Row],[BOQ]]-Over_all[[#This Row],[Received]]>=0,Over_all[[#This Row],[BOQ]]-Over_all[[#This Row],[Received]],"") -> 0 | H28: =IF(Over_all[[#This Row],[BOQ]]-Over_all[[#This Row],[Received]]<0,Over_all[[#This Row],[BOQ]]-Over_all[[#This Row],[Received]],"") | J28: =Over_all[[#This Row],[Received]] -> 0 | K28: =SUMIF(ISSUE!$F:$F,Over_all[[#This Row],[Item Description]],ISSUE!$I:$I) -> 0 | L28: =Over_all[[#This Row],[Received.]]-Over_all[[#This Row],[Issued]] -> 0
A29: =BOQ[[#This Row],[S.No]] -> D | B29: =BOQ[[#This Row],[Item Description]] -> Cables | C29: =BOQ[[#This Row],[Make / Vendor]] -> 0 | D29: =BOQ[[#This Row],[Unit]] -> 0 | E29: =BOQ[[#This Row],[BOQ]] -> 0 | F29: =SUMIF('Goods Receipt'!$J:$J,Over_all[[#This Row],[Item Description]],'Goods Receipt'!$M:$M) -> 0 | G29: =IF(Over_all[[#This Row],[BOQ]]-Over_all[[#This Row],[Received]]>=0,Over_all[[#This Row],[BOQ]]-Over_all[[#This Row],[Received]],"") -> 0 | H29: =IF(Over_all[[#This Row],[BOQ]]-Over_all[[#This Row],[Received]]<0,Over_all[[#This Row],[BOQ]]-Over_all[[#This Row],[Received]],"") | J29: =Over_all[[#This Row],[Received]] -> 0 | K29: =SUMIF(ISSUE!$F:$F,Over_all[[#This Row],[Item Description]],ISSUE!$I:$I) -> 0 | L29: =Over_all[[#This Row],[Received.]]-Over_all[[#This Row],[Issued]] -> 0
A30: =BOQ[[#This Row],[S.No]] -> D.1 | B30: =BOQ[[#This Row],[Item Description]] -> DC_Cables | C30: =BOQ[[#This Row],[Make / Vendor]] -> 0 | D30: =BOQ[[#This Row],[Unit]] -> 0 | E30: =BOQ[[#This Row],[BOQ]] -> 0 | F30: =SUMIF('Goods Receipt'!$J:$J,Over_all[[#This Row],[Item Description]],'Goods Receipt'!$M:$M) -> 0 | G30: =IF(Over_all[[#This Row],[BOQ]]-Over_all[[#This Row],[Received]]>=0,Over_all[[#This Row],[BOQ]]-Over_all[[#This Row],[Received]],"") -> 0 | H30: =IF(Over_all[[#This Row],[BOQ]]-Over_all[[#This Row],[Received]]<0,Over_all[[#This Row],[BOQ]]-Over_all[[#This Row],[Received]],"") | J30: =Over_all[[#This Row],[Received]] -> 0 | K30: =SUMIF(ISSUE!$F:$F,Over_all[[#This Row],[Item Description]],ISSUE!$I:$I) -> 0 | L30: =Over_all[[#This Row],[Received.]]-Over_all[[#This Row],[Issued]] -> 0
A31: =BOQ[[#This Row],[S.No]] -> 1 | B31: =BOQ[[#This Row],[Item Description]] -> 1CX6Sqmm DC Cable Black | C31: =BOQ[[#This Row],[Make / Vendor]] -> 0 | D31: =BOQ[[#This Row],[Unit]] -> Mtr | E31: =BOQ[[#This Row],[BOQ]] -> 17000 | F31: =SUMIF('Goods Receipt'!$J:$J,Over_all[[#This Row],[Item Description]],'Goods Receipt'!$M:$M) -> 18582 | G31: =IF(Over_all[[#This Row],[BOQ]]-Over_all[[#This Row],[Received]]>=0,Over_all[[#This Row],[BOQ]]-Over_all[[#This Row],[Received]],"") | H31: =IF(Over_all[[#This Row],[BOQ]]-Over_all[[#This Row],[Received]]<0,Over_all[[#This Row],[BOQ]]-Over_all[[#This Row],[Received]],"") -> -1582 | J31: =Over_all[[#This Row],[Received]] -> 18582 | K31: =SUMIF(ISSUE!$F:$F,Over_all[[#This Row],[Item Description]],ISSUE!$I:$I) -> 16082 | L31: =Over_all[[#This Row],[Received.]]-Over_all[[#This Row],[Issued]] -> 2500
A32: =BOQ[[#This Row],[S.No]] -> 2 | B32: =BOQ[[#This Row],[Item Description]] -> 1CX6Sqmm DC Cable Red | C32: =BOQ[[#This Row],[Make / Vendor]] -> 0 | D32: =BOQ[[#This Row],[Unit]] -> Mtr | E32: =BOQ[[#This Row],[BOQ]] -> 17000 | F32: =SUMIF('Goods Receipt'!$J:$J,Over_all[[#This Row],[Item Description]],'Goods Receipt'!$M:$M) -> 21199 | G32: =IF(Over_all[[#This Row],[BOQ]]-Over_all[[#This Row],[Received]]>=0,Over_all[[#This Row],[BOQ]]-Over_all[[#This Row],[Received]],"") | H32: =IF(Over_all[[#This Row],[BOQ]]-Over_all[[#This Row],[Received]]<0,Over_all[[#This Row],[BOQ]]-Over_all[[#This Row],[Received]],"") -> -4199 | J32: =Over_all[[#This Row],[Received]] -> 21199 | K32: =SUMIF(ISSUE!$F:$F,Over_all[[#This Row],[Item Description]],ISSUE!$I:$I) -> 16107 | L32: =Over_all[[#This Row],[Received.]]-Over_all[[#This Row],[Issued]] -> 5092
A33: =BOQ[[#This Row],[S.No]] -> 0 | B33: =BOQ[[#This Row],[Item Description]] -> 0 | C33: =BOQ[[#This Row],[Make / Vendor]] -> 0 | D33: =BOQ[[#This Row],[Unit]] -> 0 | E33: =BOQ[[#This Row],[BOQ]] -> 0 | F33: =SUMIF('Goods Receipt'!$J:$J,Over_all[[#This Row],[Item Description]],'Goods Receipt'!$M:$M) -> 0 | G33: =IF(Over_all[[#This Row],[BOQ]]-Over_all[[#This Row],[Received]]>=0,Over_all[[#This Row],[BOQ]]-Over_all[[#This Row],[Received]],"") -> 0 | H33: =IF(Over_all[[#This Row],[BOQ]]-Over_all[[#This Row],[Received]]<0,Over_all[[#This Row],[BOQ]]-Over_all[[#This Row],[Received]],"") | J33: =Over_all[[#This Row],[Received]] -> 0 | K33: =SUMIF(ISSUE!$F:$F,Over_all[[#This Row],[Item Description]],ISSUE!$I:$I) -> 0 | L33: =Over_all[[#This Row],[Received.]]-Over_all[[#This Row],[Issued]] -> 0
A34: =BOQ[[#This Row],[S.No]] -> D.2 | B34: =BOQ[[#This Row],[Item Description]] -> AC_Cables | C34: =BOQ[[#This Row],[Make / Vendor]] -> 0 | D34: =BOQ[[#This Row],[Unit]] -> 0 | E34: =BOQ[[#This Row],[BOQ]] -> 0 | F34: =SUMIF('Goods Receipt'!$J:$J,Over_all[[#This Row],[Item Description]],'Goods Receipt'!$M:$M) -> 0 | G34: =IF(Over_all[[#This Row],[BOQ]]-Over_all[[#This Row],[Received]]>=0,Over_all[[#This Row],[BOQ]]-Over_all[[#This Row],[Received]],"") -> 0 | H34: =IF(Over_all[[#This Row],[BOQ]]-Over_all[[#This Row],[Received]]<0,Over_all[[#This Row],[BOQ]]-Over_all[[#This Row],[Received]],"") | J34: =Over_all[[#This Row],[Received]] -> 0 | K34: =SUMIF(ISSUE!$F:$F,Over_all[[#This Row],[Item Description]],ISSUE!$I:$I) -> 0 | L34: =Over_all[[#This Row],[Received.]]-Over_all[[#This Row],[Issued]] -> 0
A35: =BOQ[[#This Row],[S.No]] -> 1 | B35: =BOQ[[#This Row],[Item Description]] -> 3CX240Sqmm A2XFY UNSCR ATR UV AF 3.3 KV | C35: =BOQ[[#This Row],[Make / Vendor]] -> 0 | D35: =BOQ[[#This Row],[Unit]] -> Mtr | E35: =BOQ[[#This Row],[BOQ]] -> 9500 | F35: =SUMIF('Goods Receipt'!$J:$J,Over_all[[#This Row],[Item Description]],'Goods Receipt'!$M:$M) -> 12066 | G35: =IF(Over_all[[#This Row],[BOQ]]-Over_all[[#This Row],[Received]]>=0,Over_all[[#This Row],[BOQ]]-Over_all[[#This Row],[Received]],"") | H35: =IF(Over_all[[#This Row],[BOQ]]-Over_all[[#This Row],[Received]]<0,Over_all[[#This Row],[BOQ]]-Over_all[[#This Row],[Received]],"") -> -2566 | J35: =Over_all[[#This Row],[Received]] -> 12066 | K35: =SUMIF(ISSUE!$F:$F,Over_all[[#This Row],[Item Description]],ISSUE!$I:$I) -> 8045 | L35: =Over_all[[#This Row],[Received.]]-Over_all[[#This Row],[Issued]] -> 4021
A36: =BOQ[[#This Row],[S.No]] -> 0 | B36: =BOQ[[#This Row],[Item Description]] -> 0 | C36: =BOQ[[#This Row],[Make / Vendor]] -> 0 | D36: =BOQ[[#This Row],[Unit]] -> 0 | E36: =BOQ[[#This Row],[BOQ]] -> 0 | F36: =SUMIF('Goods Receipt'!$J:$J,Over_all[[#This Row],[Item Description]],'Goods Receipt'!$M:$M) -> 0 | G36: =IF(Over_all[[#This Row],[BOQ]]-Over_all[[#This Row],[Received]]>=0,Over_all[[#This Row],[BOQ]]-Over_all[[#This Row],[Received]],"") -> 0 | H36: =IF(Over_all[[#This Row],[BOQ]]-Over_all[[#This Row],[Received]]<0,Over_all[[#This Row],[BOQ]]-Over_all[[#This Row],[Received]],"") | J36: =Over_all[[#This Row],[Received]] -> 0 | K36: =SUMIF(ISSUE!$F:$F,Over_all[[#This Row],[Item Description]],ISSUE!$I:$I) -> 0 | L36: =Over_all[[#This Row],[Received.]]-Over_all[[#This Row],[Issued]] -> 0
A37: =BOQ[[#This Row],[S.No]] -> D.3 | B37: =BOQ[[#This Row],[Item Description]] -> HT_Cables | C37: =BOQ[[#This Row],[Make / Vendor]] -> 0 | D37: =BOQ[[#This Row],[Unit]] -> 0 | E37: =BOQ[[#This Row],[BOQ]] -> 0 | F37: =SUMIF('Goods Receipt'!$J:$J,Over_all[[#This Row],[Item Description]],'Goods Receipt'!$M:$M) -> 0 | G37: =IF(Over_all[[#This Row],[BOQ]]-Over_all[[#This Row],[Received]]>=0,Over_all[[#This Row],[BOQ]]-Over_all[[#This Row],[Received]],"") -> 0 | H37: =IF(Over_all[[#This Row],[BOQ]]-Over_all[[#This Row],[Received]]<0,Over_all[[#This Row],[BOQ]]-Over_all[[#This Row],[Received]],"") | J37: =Over_all[[#This Row],[Received]] -> 0 | K37: =SUMIF(ISSUE!$F:$F,Over_all[[#This Row],[Item Description]],ISSUE!$I:$I) -> 0 | L37: =Over_all[[#This Row],[Received.]]-Over_all[[#This Row],[Issued]] -> 0
A38: =BOQ[[#This Row],[S.No]] -> 1 | B38: =BOQ[[#This Row],[Item Description]] -> 3CX240Sqmm A2XFY 19/33KV HT Cable | C38: =BOQ[[#This Row],[Make / Vendor]] -> 0 | D38: =BOQ[[#This Row],[Unit]] -> Mtr | E38: =BOQ[[#This Row],[BOQ]] -> 1400 | F38: =SUMIF('Goods Receipt'!$J:$J,Over_all[[#This Row],[Item Description]],'Goods Receipt'!$M:$M) -> 1512 | G38: =IF(Over_all[[#This Row],[BOQ]]-Over_all[[#This Row],[Received]]>=0,Over_all[[#This Row],[BOQ]]-Over_all[[#This Row],[Received]],"") | H38: =IF(Over_all[[#This Row],[BOQ]]-Over_all[[#This Row],[Received]]<0,Over_all[[#This Row],[BOQ]]-Over_all[[#This Row],[Received]],"") -> -112 | J38: =Over_all[[#This Row],[Received]] -> 1512 | K38: =SUMIF(ISSUE!$F:$F,Over_all[[#This Row],[Item Description]],ISSUE!$I:$I) -> 0 | L38: =Over_all[[#This Row],[Received.]]-Over_all[[#This Row],[Issued]] -> 1512
A39: =BOQ[[#This Row],[S.No]] -> 0 | B39: =BOQ[[#This Row],[Item Description]] -> 0 | C39: =BOQ[[#This Row],[Make / Vendor]] -> 0 | D39: =BOQ[[#This Row],[Unit]] -> 0 | E39: =BOQ[[#This Row],[BOQ]] -> 0 | F39: =SUMIF('Goods Receipt'!$J:$J,Over_all[[#This Row],[Item Description]],'Goods Receipt'!$M:$M) -> 0 | G39: =IF(Over_all[[#This Row],[BOQ]]-Over_all[[#This Row],[Received]]>=0,Over_all[[#This Row],[BOQ]]-Over_all[[#This Row],[Received]],"") -> 0 | H39: =IF(Over_all[[#This Row],[BOQ]]-Over_all[[#This Row],[Received]]<0,Over_all[[#This Row],[BOQ]]-Over_all[[#This Row],[Received]],"") | J39: =Over_all[[#This Row],[Received]] -> 0 | K39: =SUMIF(ISSUE!$F:$F,Over_all[[#This Row],[Item Description]],ISSUE!$I:$I) -> 0 | L39: =Over_all[[#This Row],[Received.]]-Over_all[[#This Row],[Issued]] -> 0
A40: =BOQ[[#This Row],[S.No]] -> D.4 | B40: =BOQ[[#This Row],[Item Description]] -> Earthing_cables | C40: =BOQ[[#This Row],[Make / Vendor]] -> 0 | D40: =BOQ[[#This Row],[Unit]] -> 0 | E40: =BOQ[[#This Row],[BOQ]] -> 0 | F40: =SUMIF('Goods Receipt'!$J:$J,Over_all[[#This Row],[Item Description]],'Goods Receipt'!$M:$M) -> 0 | G40: =IF(Over_all[[#This Row],[BOQ]]-Over_all[[#This Row],[Received]]>=0,Over_all[[#This Row],[BOQ]]-Over_all[[#This Row],[Received]],"") -> 0 | H40: =IF(Over_all[[#This Row],[BOQ]]-Over_all[[#This Row],[Received]]<0,Over_all[[#This Row],[BOQ]]-Over_all[[#This Row],[Received]],"") | J40: =Over_all[[#This Row],[Received]] -> 0 | K40: =SUMIF(ISSUE!$F:$F,Over_all[[#This Row],[Item Description]],ISSUE!$I:$I) -> 0 | L40: =Over_all[[#This Row],[Received.]]-Over_all[[#This Row],[Issued]] -> 0
... A145: =BOQ[[#This Row],[S.No]] -> 9 | B145: =BOQ[[#This Row],[Item Description]] -> SS-304 (M12x80(SS-304-80mm L | C145: =BOQ[[#This Row],[Make / Vendor]] -> 0 | D145: =BOQ[[#This Row],[Unit]] -> Set | E145: =BOQ[[#This Row],[BOQ]] -> 440 | F145: =SUMIF('Goods Receipt'!$J:$J,Over_all[[#This Row],[Item Description]],'Goods Receipt'!$M:$M) -> 440 | G145: =IF(Over_all[[#This Row],[BOQ]]-Over_all[[#This Row],[Received]]>=0,Over_all[[#This Row],[BOQ]]-Over_all[[#This Row],[Received]],"") -> 0 | H145: =IF(Over_all[[#This Row],[BOQ]]-Over_all[[#This Row],[Received]]<0,Over_all[[#This Row],[BOQ]]-Over_all[[#This Row],[Received]],"") | J145: =Over_all[[#This Row],[Received]] -> 440 | K145: =SUMIF(ISSUE!$F:$F,Over_all[[#This Row],[Item Description]],ISSUE!$I:$I) -> 308 | L145: =Over_all[[#This Row],[Received.]]-Over_all[[#This Row],[Issued]] -> 132
A146: 10 | B146: =BOQ[[#This Row],[Item Description]] -> SS-304 (M10x80(SS-304-80mm L | C146: =BOQ[[#This Row],[Make / Vendor]] -> 0 | D146: =BOQ[[#This Row],[Unit]] -> Set | E146: =BOQ[[#This Row],[BOQ]] -> 352 | F146: =SUMIF('Goods Receipt'!$J:$J,Over_all[[#This Row],[Item Description]],'Goods Receipt'!$M:$M) -> 352 | G146: =IF(Over_all[[#This Row],[BOQ]]-Over_all[[#This Row],[Received]]>=0,Over_all[[#This Row],[BOQ]]-Over_all[[#This Row],[Received]],"") -> 0 | H146: =IF(Over_all[[#This Row],[BOQ]]-Over_all[[#This Row],[Received]]<0,Over_all[[#This Row],[BOQ]]-Over_all[[#This Row],[Received]],"") | J146: =Over_all[[#This Row],[Received]] -> 352 | K146: =SUMIF(ISSUE!$F:$F,Over_all[[#This Row],[Item Description]],ISSUE!$I:$I) -> 176 | L146: =Over_all[[#This Row],[Received.]]-Over_all[[#This Row],[Issued]] -> 176
A147: 11 | B147: =BOQ[[#This Row],[Item Description]] -> SDS with EPDM washer | C147: =BOQ[[#This Row],[Make / Vendor]] -> 0 | D147: =BOQ[[#This Row],[Unit]] -> Nos | E147: =BOQ[[#This Row],[BOQ]] -> 440 | F147: =SUMIF('Goods Receipt'!$J:$J,Over_all[[#This Row],[Item Description]],'Goods Receipt'!$M:$M) -> 440 | G147: =IF(Over_all[[#This Row],[BOQ]]-Over_all[[#This Row],[Received]]>=0,Over_all[[#This Row],[BOQ]]-Over_all[[#This Row],[Received]],"") -> 0 | H147: =IF(Over_all[[#This Row],[BOQ]]-Over_all[[#This Row],[Received]]<0,Over_all[[#This Row],[BOQ]]-Over_all[[#This Row],[Received]],"") | J147: =Over_all[[#This Row],[Received]] -> 440 | K147: =SUMIF(ISSUE!$F:$F,Over_all[[#This Row],[Item Description]],ISSUE!$I:$I) -> 220 | L147: =Over_all[[#This Row],[Received.]]-Over_all[[#This Row],[Issued]] -> 220
A148: =BOQ[[#This Row],[S.No]] -> 0 | B148: =BOQ[[#This Row],[Item Description]] -> 0 | C148: =BOQ[[#This Row],[Make / Vendor]] -> 0 | D148: =BOQ[[#This Row],[Unit]] -> 0 | E148: =BOQ[[#This Row],[BOQ]] -> 0 | F148: =SUMIF('Goods Receipt'!$J:$J,Over_all[[#This Row],[Item Description]],'Goods Receipt'!$M:$M) -> 0 | G148: =IF(Over_all[[#This Row],[BOQ]]-Over_all[[#This Row],[Received]]>=0,Over_all[[#This Row],[BOQ]]-Over_all[[#This Row],[Received]],"") -> 0 | H148: =IF(Over_all[[#This Row],[BOQ]]-Over_all[[#This Row],[Received]]<0,Over_all[[#This Row],[BOQ]]-Over_all[[#This Row],[Received]],"") | J148: =Over_all[[#This Row],[Received]] -> 0 | K148: =SUMIF(ISSUE!$F:$F,Over_all[[#This Row],[Item Description]],ISSUE!$I:$I) -> 0 | L148: =Over_all[[#This Row],[Received.]]-Over_all[[#This Row],[Issued]] -> 0
A149: =BOQ[[#This Row],[S.No]] -> J | B149: =BOQ[[#This Row],[Item Description]] -> Connectors | C149: =BOQ[[#This Row],[Make / Vendor]] -> 0 | D149: =BOQ[[#This Row],[Unit]] -> 0 | E149: =BOQ[[#This Row],[BOQ]] -> 0 | F149: =SUMIF('Goods Receipt'!$J:$J,Over_all[[#This Row],[Item Description]],'Goods Receipt'!$M:$M) -> 0 | G149: =IF(Over_all[[#This Row],[BOQ]]-Over_all[[#This Row],[Received]]>=0,Over_all[[#This Row],[BOQ]]-Over_all[[#This Row],[Received]],"") -> 0 | H149: =IF(Over_all[[#This Row],[BOQ]]-Over_all[[#This Row],[Received]]<0,Over_all[[#This Row],[BOQ]]-Over_all[[#This Row],[Received]],"") | J149: =Over_all[[#This Row],[Received]] -> 0 | K149: =SUMIF(ISSUE!$F:$F,Over_all[[#This Row],[Item Description]],ISSUE!$I:$I) -> 0 | L149: =Over_all[[#This Row],[Received.]]-Over_all[[#This Row],[Issued]] -> 0
A150: =BOQ[[#This Row],[S.No]] -> 0 | B150: =BOQ[[#This Row],[Item Description]] -> 0 | C150: =BOQ[[#This Row],[Make / Vendor]] -> 0 | D150: =BOQ[[#This Row],[Unit]] -> 0 | E150: =BOQ[[#This Row],[BOQ]] -> 0 | F150: =SUMIF('Goods Receipt'!$J:$J,Over_all[[#This Row],[Item Description]],'Goods Receipt'!$M:$M) -> 0 | G150: =IF(Over_all[[#This Row],[BOQ]]-Over_all[[#This Row],[Received]]>=0,Over_all[[#This Row],[BOQ]]-Over_all[[#This Row],[Received]],"") -> 0 | H150: =IF(Over_all[[#This Row],[BOQ]]-Over_all[[#This Row],[Received]]<0,Over_all[[#This Row],[BOQ]]-Over_all[[#This Row],[Received]],"") | J150: =Over_all[[#This Row],[Received]] -> 0 | K150: =SUMIF(ISSUE!$F:$F,Over_all[[#This Row],[Item Description]],ISSUE!$I:$I) -> 0 | L150: =Over_all[[#This Row],[Received.]]-Over_all[[#This Row],[Issued]] -> 0
A151: =BOQ[[#This Row],[S.No]] -> K | B151: =BOQ[[#This Row],[Item Description]] -> Cable_Glands | C151: =BOQ[[#This Row],[Make / Vendor]] -> 0 | D151: =BOQ[[#This Row],[Unit]] -> 0 | E151: =BOQ[[#This Row],[BOQ]] -> 0 | F151: =SUMIF('Goods Receipt'!$J:$J,Over_all[[#This Row],[Item Description]],'Goods Receipt'!$M:$M) -> 0 | G151: =IF(Over_all[[#This Row],[BOQ]]-Over_all[[#This Row],[Received]]>=0,Over_all[[#This Row],[BOQ]]-Over_all[[#This Row],[Received]],"") -> 0 | H151: =IF(Over_all[[#This Row],[BOQ]]-Over_all[[#This Row],[Received]]<0,Over_all[[#This Row],[BOQ]]-Over_all[[#This Row],[Received]],"") | J151: =Over_all[[#This Row],[Received]] -> 0 | K151: =SUMIF(ISSUE!$F:$F,Over_all[[#This Row],[Item Description]],ISSUE!$I:$I) -> 0 | L151: =Over_all[[#This Row],[Received.]]-Over_all[[#This Row],[Issued]] -> 0
A152: =BOQ[[#This Row],[S.No]] -> 1 | B152: =BOQ[[#This Row],[Item Description]] -> 3C X 240 Sq.mm Double Compression Metal Gland | C152: =BOQ[[#This Row],[Make / Vendor]] -> 0 | D152: =BOQ[[#This Row],[Unit]] -> Nos | E152: =BOQ[[#This Row],[BOQ]] -> 47 | F152: =SUMIF('Goods Receipt'!$J:$J,Over_all[[#This Row],[Item Description]],'Goods Receipt'!$M:$M) -> 47 | G152: =IF(Over_all[[#This Row],[BOQ]]-Over_all[[#This Row],[Received]]>=0,Over_all[[#This Row],[BOQ]]-Over_all[[#This Row],[Received]],"") -> 0 | H152: =IF(Over_all[[#This Row],[BOQ]]-Over_all[[#This Row],[Received]]<0,Over_all[[#This Row],[BOQ]]-Over_all[[#This Row],[Received]],"") | J152: =Over_all[[#This Row],[Received]] -> 47 | K152: =SUMIF(ISSUE!$F:$F,Over_all[[#This Row],[Item Description]],ISSUE!$I:$I) -> 0 | L152: =Over_all[[#This Row],[Received.]]-Over_all[[#This Row],[Issued]] -> 47
A153: =BOQ[[#This Row],[S.No]] -> 2 | B153: =BOQ[[#This Row],[Item Description]] -> 3C X 240 Sq.mm Double Bracing Metal Gland | C153: =BOQ[[#This Row],[Make / Vendor]] -> 0 | D153: =BOQ[[#This Row],[Unit]] -> Nos | E153: =BOQ[[#This Row],[BOQ]] -> 16 | F153: =SUMIF('Goods Receipt'!$J:$J,Over_all[[#This Row],[Item Description]],'Goods Receipt'!$M:$M) -> 16 | G153: =IF(Over_all[[#This Row],[BOQ]]-Over_all[[#This Row],[Received]]>=0,Over_all[[#This Row],[BOQ]]-Over_all[[#This Row],[Received]],"") -> 0 | H153: =IF(Over_all[[#This Row],[BOQ]]-Over_all[[#This Row],[Received]]<0,Over_all[[#This Row],[BOQ]]-Over_all[[#This Row],[Received]],"") | J153: =Over_all[[#This Row],[Received]] -> 16 | K153: =SUMIF(ISSUE!$F:$F,Over_all[[#This Row],[Item Description]],ISSUE!$I:$I) -> 0 | L153: =Over_all[[#This Row],[Received.]]-Over_all[[#This Row],[Issued]] -> 16
A154: =BOQ[[#This Row],[S.No]] -> 3 | B154: =BOQ[[#This Row],[Item Description]] -> 3C X 35 Sq.mm Double Bracing Metal Gland | C154: =BOQ[[#This Row],[Make / Vendor]] -> 0 | D154: =BOQ[[#This Row],[Unit]] -> Nos | E154: =BOQ[[#This Row],[BOQ]] -> 6 | F154: =SUMIF('Goods Receipt'!$J:$J,Over_all[[#This Row],[Item Description]],'Goods Receipt'!$M:$M) -> 6 | G154: =IF(Over_all[[#This Row],[BOQ]]-Over_all[[#This Row],[Received]]>=0,Over_all[[#This Row],[BOQ]]-Over_all[[#This Row],[Received]],"") -> 0 | H154: =IF(Over_all[[#This Row],[BOQ]]-Over_all[[#This Row],[Received]]<0,Over_all[[#This Row],[BOQ]]-Over_all[[#This Row],[Received]],"") | J154: =Over_all[[#This Row],[Received]] -> 6 | K154: =SUMIF(ISSUE!$F:$F,Over_all[[#This Row],[Item Description]],ISSUE!$I:$I) -> 0 | L154: =Over_all[[#This Row],[Received.]]-Over_all[[#This Row],[Issued]] -> 6
A155: =BOQ[[#This Row],[S.No]] -> 4 | B155: =BOQ[[#This Row],[Item Description]] -> 2C X 6 Sq.mm Double Bracing Metal Gland | C155: =BOQ[[#This Row],[Make / Vendor]] -> 0 | D155: =BOQ[[#This Row],[Unit]] -> Nos | E155: =BOQ[[#This Row],[BOQ]] -> 10 | F155: =SUMIF('Goods Receipt'!$J:$J,Over_all[[#This Row],[Item Description]],'Goods Receipt'!$M:$M) -> 10 | G155: =IF(Over_all[[#This Row],[BOQ]]-Over_all[[#This Row],[Received]]>=0,Over_all[[#This Row],[BOQ]]-Over_all[[#This Row],[Received]],"") -> 0 | H155: =IF(Over_all[[#This Row],[BOQ]]-Over_all[[#This Row],[Received]]<0,Over_all[[#This Row],[BOQ]]-Over_all[[#This Row],[Received]],"") | J155: =Over_all[[#This Row],[Received]] -> 10 | K155: =SUMIF(ISSUE!$F:$F,Over_all[[#This Row],[Item Description]],ISSUE!$I:$I) -> 0 | L155: =Over_all[[#This Row],[Received.]]-Over_all[[#This Row],[Issued]] -> 10
A156: =BOQ[[#This Row],[S.No]] -> 5 | B156: =BOQ[[#This Row],[Item Description]] -> 4C X 6 Sq.mm Double Bracing Metal Gland | C156: =BOQ[[#This Row],[Make / Vendor]] -> 0 | D156: =BOQ[[#This Row],[Unit]] -> Nos | E156: =BOQ[[#This Row],[BOQ]] -> 290 | F156: =SUMIF('Goods Receipt'!$J:$J,Over_all[[#This Row],[Item Description]],'Goods Receipt'!$M:$M) -> 290 | G156: =IF(Over_all[[#This Row],[BOQ]]-Over_all[[#This Row],[Received]]>=0,Over_all[[#This Row],[BOQ]]-Over_all[[#This Row],[Received]],"") -> 0 | H156: =IF(Over_all[[#This Row],[BOQ]]-Over_all[[#This Row],[Received]]<0,Over_all[[#This Row],[BOQ]]-Over_all[[#This Row],[Received]],"") | J156: =Over_all[[#This Row],[Received]] -> 290 | K156: =SUMIF(ISSUE!$F:$F,Over_all[[#This Row],[Item Description]],ISSUE!$I:$I) -> 0 | L156: =Over_all[[#This Row],[Received.]]-Over_all[[#This Row],[Issued]] -> 290
A157: =BOQ[[#This Row],[S.No]] -> 6 | B157: =BOQ[[#This Row],[Item Description]] -> 2C X 4.0 Sq.mm PVC Gland | C157: =BOQ[[#This Row],[Make / Vendor]] -> 0 | D157: =BOQ[[#This Row],[Unit]] -> Nos | E157: =BOQ[[#This Row],[BOQ]] -> 20 | F157: =SUMIF('Goods Receipt'!$J:$J,Over_all[[#This Row],[Item Description]],'Goods Receipt'!$M:$M) -> 20 | G157: =IF(Over_all[[#This Row],[BOQ]]-Over_all[[#This Row],[Received]]>=0,Over_all[[#This Row],[BOQ]]-Over_all[[#This Row],[Received]],"") -> 0 | H157: =IF(Over_all[[#This Row],[BOQ]]-Over_all[[#This Row],[Received]]<0,Over_all[[#This Row],[BOQ]]-Over_all[[#This Row],[Received]],"") | J157: =Over_all[[#This Row],[Received]] -> 20 | K157: =SUMIF(ISSUE!$F:$F,Over_all[[#This Row],[Item Description]],ISSUE!$I:$I) -> 0 | L157: =Over_all[[#This Row],[Received.]]-Over_all[[#This Row],[Issued]] -> 20
A158: =BOQ[[#This Row],[S.No]] -> 7 | B158: =BOQ[[#This Row],[Item Description]] -> 2C X 2.5 Sq.mm PVC Gland | C158: =BOQ[[#This Row],[Make / Vendor]] -> 0 | D158: =BOQ[[#This Row],[Unit]] -> Nos | E158: =BOQ[[#This Row],[BOQ]] -> 30 | F158: =SUMIF('Goods Receipt'!$J:$J,Over_all[[#This Row],[Item Description]],'Goods Receipt'!$M:$M) -> 30 | G158: =IF(Over_all[[#This Row],[BOQ]]-Over_all[[#This Row],[Received]]>=0,Over_all[[#This Row],[BOQ]]-Over_all[[#This Row],[Received]],"") -> 0 | H158: =IF(Over_all[[#This Row],[BOQ]]-Over_all[[#This Row],[Received]]<0,Over_all[[#This Row],[BOQ]]-Over_all[[#This Row],[Received]],"") | J158: =Over_all[[#This Row],[Received]] -> 30 | K158: =SUMIF(ISSUE!$F:$F,Over_all[[#This Row],[Item Description]],ISSUE!$I:$I) -> 0 | L158: =Over_all[[#This Row],[Received.]]-Over_all[[#This Row],[Issued]] -> 30
A159: =BOQ[[#This Row],[S.No]] -> 8 | B159: =BOQ[[#This Row],[Item Description]] -> 12C X 2.5 Sq.mm PVC Gland | C159: =BOQ[[#This Row],[Make / Vendor]] -> 0 | D159: =BOQ[[#This Row],[Unit]] -> Nos | E159: =BOQ[[#This Row],[BOQ]] -> 30 | F159: =SUMIF('Goods Receipt'!$J:$J,Over_all[[#This Row],[Item Description]],'Goods Receipt'!$M:$M) -> 30 | G159: =IF(Over_all[[#This Row],[BOQ]]-Over_all[[#This Row],[Received]]>=0,Over_all[[#This Row],[BOQ]]-Over_all[[#This Row],[Received]],"") -> 0 | H159: =IF(Over_all[[#This Row],[BOQ]]-Over_all[[#This Row],[Received]]<0,Over_all[[#This Row],[BOQ]]-Over_all[[#This Row],[Received]],"") | J159: =Over_all[[#This Row],[Received]] -> 30 | K159: =SUMIF(ISSUE!$F:$F,Over_all[[#This Row],[Item Description]],ISSUE!$I:$I) -> 0 | L159: =Over_all[[#This Row],[Received.]]-Over_all[[#This Row],[Issued]] -> 30
... A170: =BOQ[[#This Row],[S.No]] -> 6 | B170: =BOQ[[#This Row],[Item Description]] -> 35 Sq.mm Al Ring Type Lug | C170: =BOQ[[#This Row],[Make / Vendor]] -> 0 | D170: =BOQ[[#This Row],[Unit]] -> Nos | E170: =BOQ[[#This Row],[BOQ]] -> 15 | F170: =SUMIF('Goods Receipt'!$J:$J,Over_all[[#This Row],[Item Description]],'Goods Receipt'!$M:$M) -> 15 | G170: =IF(Over_all[[#This Row],[BOQ]]-Over_all[[#This Row],[Received]]>=0,Over_all[[#This Row],[BOQ]]-Over_all[[#This Row],[Received]],"") -> 0 | H170: =IF(Over_all[[#This Row],[BOQ]]-Over_all[[#This Row],[Received]]<0,Over_all[[#This Row],[BOQ]]-Over_all[[#This Row],[Received]],"") | J170: =Over_all[[#This Row],[Received]] -> 15 | K170: =SUMIF(ISSUE!$F:$F,Over_all[[#This Row],[Item Description]],ISSUE!$I:$I) -> 0 | L170: =Over_all[[#This Row],[Received.]]-Over_all[[#This Row],[Issued]] -> 15
A171: =BOQ[[#This Row],[S.No]] -> 7 | B171: =BOQ[[#This Row],[Item Description]] -> 2.5 Sq.mm Cu Ring Typr Lug | C171: =BOQ[[#This Row],[Make / Vendor]] -> 0 | D171: =BOQ[[#This Row],[Unit]] -> Nos | E171: =BOQ[[#This Row],[BOQ]] -> 40 | F171: 40 | G171: =IF(Over_all[[#This Row],[BOQ]]-Over_all[[#This Row],[Received]]>=0,Over_all[[#This Row],[BOQ]]-Over_all[[#This Row],[Received]],"") -> 0 | H171: =IF(Over_all[[#This Row],[BOQ]]-Over_all[[#This Row],[Received]]<0,Over_all[[#This Row],[BOQ]]-Over_all[[#This Row],[Received]],"") | J171: =Over_all[[#This Row],[Received]] -> 40 | K171: =SUMIF(ISSUE!$F:$F,Over_all[[#This Row],[Item Description]],ISSUE!$I:$I) -> 0 | L171: =Over_all[[#This Row],[Received.]]-Over_all[[#This Row],[Issued]] -> 40
A172: =BOQ[[#This Row],[S.No]] -> 8 | B172: =BOQ[[#This Row],[Item Description]] -> 2.5 Sq.mm Cu Pin Type Lug | C172: =BOQ[[#This Row],[Make / Vendor]] -> 0 | D172: =BOQ[[#This Row],[Unit]] -> Nos | E172: =BOQ[[#This Row],[BOQ]] -> 30 | F172: =SUMIF('Goods Receipt'!$J:$J,Over_all[[#This Row],[Item Description]],'Goods Receipt'!$M:$M) -> 60 | G172: =IF(Over_all[[#This Row],[BOQ]]-Over_all[[#This Row],[Received]]>=0,Over_all[[#This Row],[BOQ]]-Over_all[[#This Row],[Received]],"") | H172: =IF(Over_all[[#This Row],[BOQ]]-Over_all[[#This Row],[Received]]<0,Over_all[[#This Row],[BOQ]]-Over_all[[#This Row],[Received]],"") -> -30 | J172: =Over_all[[#This Row],[Received]] -> 60 | K172: =SUMIF(ISSUE!$F:$F,Over_all[[#This Row],[Item Description]],ISSUE!$I:$I) -> 0 | L172: =Over_all[[#This Row],[Received.]]-Over_all[[#This Row],[Issued]] -> 60
A173: =BOQ[[#This Row],[S.No]] -> 9 | B173: =BOQ[[#This Row],[Item Description]] -> 2.5 Sq.mm Cu Fork Type Lug | C173: =BOQ[[#This Row],[Make / Vendor]] -> 0 | D173: =BOQ[[#This Row],[Unit]] -> Nos | E173: =BOQ[[#This Row],[BOQ]] -> 0 | F173: =SUMIF('Goods Receipt'!$J:$J,Over_all[[#This Row],[Item Description]],'Goods Receipt'!$M:$M) -> 30 | G173: =IF(Over_all[[#This Row],[BOQ]]-Over_all[[#This Row],[Received]]>=0,Over_all[[#This Row],[BOQ]]-Over_all[[#This Row],[Received]],"") | H173: =IF(Over_all[[#This Row],[BOQ]]-Over_all[[#This Row],[Received]]<0,Over_all[[#This Row],[BOQ]]-Over_all[[#This Row],[Received]],"") -> -30 | J173: =Over_all[[#This Row],[Received]] -> 30 | K173: =SUMIF(ISSUE!$F:$F,Over_all[[#This Row],[Item Description]],ISSUE!$I:$I) -> 0 | L173: =Over_all[[#This Row],[Received.]]-Over_all[[#This Row],[Issued]] -> 30
A174: =BOQ[[#This Row],[S.No]] -> 10 | B174: =BOQ[[#This Row],[Item Description]] -> 6 Sq.mm Fork Type Copper Lug | C174: =BOQ[[#This Row],[Make / Vendor]] -> 0 | D174: =BOQ[[#This Row],[Unit]] -> Nos | E174: =BOQ[[#This Row],[BOQ]] -> 20 | F174: =SUMIF('Goods Receipt'!$J:$J,Over_all[[#This Row],[Item Description]],'Goods Receipt'!$M:$M) -> 20 | G174: =IF(Over_all[[#This Row],[BOQ]]-Over_all[[#This Row],[Received]]>=0,Over_all[[#This Row],[BOQ]]-Over_all[[#This Row],[Received]],"") -> 0 | H174: =IF(Over_all[[#This Row],[BOQ]]-Over_all[[#This Row],[Received]]<0,Over_all[[#This Row],[BOQ]]-Over_all[[#This Row],[Received]],"") | J174: =Over_all[[#This Row],[Received]] -> 20 | K174: =SUMIF(ISSUE!$F:$F,Over_all[[#This Row],[Item Description]],ISSUE!$I:$I) -> 0 | L174: =Over_all[[#This Row],[Received.]]-Over_all[[#This Row],[Issued]] -> 20
A175: =BOQ[[#This Row],[S.No]] -> 11 | B175: =BOQ[[#This Row],[Item Description]] -> 6 Sq.mm AL Ring Type Lug | C175: =BOQ[[#This Row],[Make / Vendor]] -> 0 | D175: =BOQ[[#This Row],[Unit]] -> Nos | E175: =BOQ[[#This Row],[BOQ]] -> 0 | F175: =SUMIF('Goods Receipt'!$J:$J,Over_all[[#This Row],[Item Description]],'Goods Receipt'!$M:$M) -> 910 | G175: =IF(Over_all[[#This Row],[BOQ]]-Over_all[[#This Row],[Received]]>=0,Over_all[[#This Row],[BOQ]]-Over_all[[#This Row],[Received]],"") | H175: =IF(Over_all[[#This Row],[BOQ]]-Over_all[[#This Row],[Received]]<0,Over_all[[#This Row],[BOQ]]-Over_all[[#This Row],[Received]],"") -> -910 | J175: =Over_all[[#This Row],[Received]] -> 910 | K175: =SUMIF(ISSUE!$F:$F,Over_all[[#This Row],[Item Description]],ISSUE!$I:$I) -> 0 | L175: =Over_all[[#This Row],[Received.]]-Over_all[[#This Row],[Issued]] -> 910
A176: =BOQ[[#This Row],[S.No]] -> 12 | B176: =BOQ[[#This Row],[Item Description]] -> 6 Sq.mm Cu Pin Type Lug | C176: =BOQ[[#This Row],[Make / Vendor]] -> 0 | D176: =BOQ[[#This Row],[Unit]] -> Nos | E176: =BOQ[[#This Row],[BOQ]] -> 0 | F176: =SUMIF('Goods Receipt'!$J:$J,Over_all[[#This Row],[Item Description]],'Goods Receipt'!$M:$M) -> 15 | G176: =IF(Over_all[[#This Row],[BOQ]]-Over_all[[#This Row],[Received]]>=0,Over_all[[#This Row],[BOQ]]-Over_all[[#This Row],[Received]],"") | H176: =IF(Over_all[[#This Row],[BOQ]]-Over_all[[#This Row],[Received]]<0,Over_all[[#This Row],[BOQ]]-Over_all[[#This Row],[Received]],"") -> -15 | J176: =Over_all[[#This Row],[Received]] -> 15 | K176: =SUMIF(ISSUE!$F:$F,Over_all[[#This Row],[Item Description]],ISSUE!$I:$I) -> 0 | L176: =Over_all[[#This Row],[Received.]]-Over_all[[#This Row],[Issued]] -> 15
A177: =BOQ[[#This Row],[S.No]] -> 13 | B177: =BOQ[[#This Row],[Item Description]] -> 16 Sq.mm Ring Type Lug | C177: =BOQ[[#This Row],[Make / Vendor]] -> 0 | D177: =BOQ[[#This Row],[Unit]] -> Nos | E177: =BOQ[[#This Row],[BOQ]] -> 0 | F177: =SUMIF('Goods Receipt'!$J:$J,Over_all[[#This Row],[Item Description]],'Goods Receipt'!$M:$M) -> 15 | G177: =IF(Over_all[[#This Row],[BOQ]]-Over_all[[#This Row],[Received]]>=0,Over_all[[#This Row],[BOQ]]-Over_all[[#This Row],[Received]],"") | H177: =IF(Over_all[[#This Row],[BOQ]]-Over_all[[#This Row],[Received]]<0,Over_all[[#This Row],[BOQ]]-Over_all[[#This Row],[Received]],"") -> -15 | J177: =Over_all[[#This Row],[Received]] -> 15 | K177: =SUMIF(ISSUE!$F:$F,Over_all[[#This Row],[Item Description]],ISSUE!$I:$I) -> 0 | L177: =Over_all[[#This Row],[Received.]]-Over_all[[#This Row],[Issued]] -> 15
A178: =BOQ[[#This Row],[S.No]] -> 0 | B178: =BOQ[[#This Row],[Item Description]] -> 0 | C178: =BOQ[[#This Row],[Make / Vendor]] -> 0 | D178: =BOQ[[#This Row],[Unit]] -> 0 | E178: =BOQ[[#This Row],[BOQ]] -> 0 | F178: =SUMIF('Goods Receipt'!$J:$J,Over_all[[#This Row],[Item Description]],'Goods Receipt'!$M:$M) -> 0 | G178: =IF(Over_all[[#This Row],[BOQ]]-Over_all[[#This Row],[Received]]>=0,Over_all[[#This Row],[BOQ]]-Over_all[[#This Row],[Received]],"") -> 0 | H178: =IF(Over_all[[#This Row],[BOQ]]-Over_all[[#This Row],[Received]]<0,Over_all[[#This Row],[BOQ]]-Over_all[[#This Row],[Received]],"") | J178: =Over_all[[#This Row],[Received]] -> 0 | K178: =SUMIF(ISSUE!$F:$F,Over_all[[#This Row],[Item Description]],ISSUE!$I:$I) -> 0 | L178: =Over_all[[#This Row],[Received.]]-Over_all[[#This Row],[Issued]] -> 0
A179: =BOQ[[#This Row],[S.No]] -> N | B179: =BOQ[[#This Row],[Item Description]] -> Cable_Tie | C179: =BOQ[[#This Row],[Make / Vendor]] -> 0 | D179: =BOQ[[#This Row],[Unit]] -> 0 | E179: =BOQ[[#This Row],[BOQ]] -> 0 | F179: =SUMIF('Goods Receipt'!$J:$J,Over_all[[#This Row],[Item Description]],'Goods Receipt'!$M:$M) -> 0 | G179: =IF(Over_all[[#This Row],[BOQ]]-Over_all[[#This Row],[Received]]>=0,Over_all[[#This Row],[BOQ]]-Over_all[[#This Row],[Received]],"") -> 0 | H179: =IF(Over_all[[#This Row],[BOQ]]-Over_all[[#This Row],[Received]]<0,Over_all[[#This Row],[BOQ]]-Over_all[[#This Row],[Received]],"") | J179: =Over_all[[#This Row],[Received]] -> 0 | K179: =SUMIF(ISSUE!$F:$F,Over_all[[#This Row],[Item Description]],ISSUE!$I:$I) -> 0 | L179: =Over_all[[#This Row],[Received.]]-Over_all[[#This Row],[Issued]] -> 0
A180: =BOQ[[#This Row],[S.No]] -> 1 | B180: =BOQ[[#This Row],[Item Description]] -> 100X2.5MM UV Cable Tie Black | C180: =BOQ[[#This Row],[Make / Vendor]] -> 0 | D180: =BOQ[[#This Row],[Unit]] -> Pkt | E180: =BOQ[[#This Row],[BOQ]] -> 25000 | F180: =SUMIF('Goods Receipt'!$J:$J,Over_all[[#This Row],[Item Description]],'Goods Receipt'!$M:$M) -> 25000 | G180: =IF(Over_all[[#This Row],[BOQ]]-Over_all[[#This Row],[Received]]>=0,Over_all[[#This Row],[BOQ]]-Over_all[[#This Row],[Received]],"") -> 0 | H180: =IF(Over_all[[#This Row],[BOQ]]-Over_all[[#This Row],[Received]]<0,Over_all[[#This Row],[BOQ]]-Over_all[[#This Row],[Received]],"") | J180: =Over_all[[#This Row],[Received]] -> 25000 | K180: =SUMIF(ISSUE!$F:$F,Over_all[[#This Row],[Item Description]],ISSUE!$I:$I) -> 0 | L180: =Over_all[[#This Row],[Received.]]-Over_all[[#This Row],[Issued]] -> 25000
A181: =BOQ[[#This Row],[S.No]] -> 2 | B181: =BOQ[[#This Row],[Item Description]] -> 300X4.8MM UV Cable Tie Black | C181: =BOQ[[#This Row],[Make / Vendor]] -> 0 | D181: =BOQ[[#This Row],[Unit]] -> Pkt | E181: =BOQ[[#This Row],[BOQ]] -> 10000 | F181: =SUMIF('Goods Receipt'!$J:$J,Over_all[[#This Row],[Item Description]],'Goods Receipt'!$M:$M) -> 10000 | G181: =IF(Over_all[[#This Row],[BOQ]]-Over_all[[#This Row],[Received]]>=0,Over_all[[#This Row],[BOQ]]-Over_all[[#This Row],[Received]],"") -> 0 | H181: =IF(Over_all[[#This Row],[BOQ]]-Over_all[[#This Row],[Received]]<0,Over_all[[#This Row],[BOQ]]-Over_all[[#This Row],[Received]],"") | J181: =Over_all[[#This Row],[Received]] -> 10000 | K181: =SUMIF(ISSUE!$F:$F,Over_all[[#This Row],[Item Description]],ISSUE!$I:$I) -> 0 | L181: =Over_all[[#This Row],[Received.]]-Over_all[[#This Row],[Issued]] -> 10000
A182: =BOQ[[#This Row],[S.No]] -> 3 | B182: =BOQ[[#This Row],[Item Description]] -> 300x4.6 SS Cable Tie | C182: =BOQ[[#This Row],[Make / Vendor]] -> 0 | D182: =BOQ[[#This Row],[Unit]] -> Pkt | E182: =BOQ[[#This Row],[BOQ]] -> 800 | F182: =SUMIF('Goods Receipt'!$J:$J,Over_all[[#This Row],[Item Description]],'Goods Receipt'!$M:$M) -> 800 | G182: =IF(Over_all[[#This Row],[BOQ]]-Over_all[[#This Row],[Received]]>=0,Over_all[[#This Row],[BOQ]]-Over_all[[#This Row],[Received]],"") -> 0 | H182: =IF(Over_all[[#This Row],[BOQ]]-Over_all[[#This Row],[Received]]<0,Over_all[[#This Row],[BOQ]]-Over_all[[#This Row],[Received]],"") | J182: =Over_all[[#This Row],[Received]] -> 800 | K182: =SUMIF(ISSUE!$F:$F,Over_all[[#This Row],[Item Description]],ISSUE!$I:$I) -> 0 | L182: =Over_all[[#This Row],[Received.]]-Over_all[[#This Row],[Issued]] -> 800
A183: =BOQ[[#This Row],[S.No]] -> 0 | B183: =BOQ[[#This Row],[Item Description]] -> 0 | C183: =BOQ[[#This Row],[Make / Vendor]] -> 0 | D183: =BOQ[[#This Row],[Unit]] -> 0 | E183: =BOQ[[#This Row],[BOQ]] -> 0 | F183: =SUMIF('Goods Receipt'!$J:$J,Over_all[[#This Row],[Item Description]],'Goods Receipt'!$M:$M) -> 0 | G183: =IF(Over_all[[#This Row],[BOQ]]-Over_all[[#This Row],[Received]]>=0,Over_all[[#This Row],[BOQ]]-Over_all[[#This Row],[Received]],"") -> 0 | H183: =IF(Over_all[[#This Row],[BOQ]]-Over_all[[#This Row],[Received]]<0,Over_all[[#This Row],[BOQ]]-Over_all[[#This Row],[Received]],"") | J183: =Over_all[[#This Row],[Received]] -> 0 | K183: =SUMIF(ISSUE!$F:$F,Over_all[[#This Row],[Item Description]],ISSUE!$I:$I) -> 0 | L183: =Over_all[[#This Row],[Received.]]-Over_all[[#This Row],[Issued]] -> 0
... A230: =BOQ[[#This Row],[S.No]] -> 35 | B230: =BOQ[[#This Row],[Item Description]] -> 33Kv Earthing Electrode | C230: =BOQ[[#This Row],[Make / Vendor]] -> 0 | D230: =BOQ[[#This Row],[Unit]] -> Nos | E230: =BOQ[[#This Row],[BOQ]] -> 0 | F230: =SUMIF('Goods Receipt'!$J:$J,Over_all[[#This Row],[Item Description]],'Goods Receipt'!$M:$M) -> 2 | G230: =IF(Over_all[[#This Row],[BOQ]]-Over_all[[#This Row],[Received]]>=0,Over_all[[#This Row],[BOQ]]-Over_all[[#This Row],[Received]],"") | H230: =IF(Over_all[[#This Row],[BOQ]]-Over_all[[#This Row],[Received]]<0,Over_all[[#This Row],[BOQ]]-Over_all[[#This Row],[Received]],"") -> -2 | J230: =Over_all[[#This Row],[Received]] -> 2 | K230: =SUMIF(ISSUE!$F:$F,Over_all[[#This Row],[Item Description]],ISSUE!$I:$I) -> 0 | L230: =Over_all[[#This Row],[Received.]]-Over_all[[#This Row],[Issued]] -> 2
B231: =BOQ[[#This Row],[Item Description]] -> 0 | C231: =BOQ[[#This Row],[Make / Vendor]] -> 0 | D231: =BOQ[[#This Row],[Unit]] -> 0 | E231: =BOQ[[#This Row],[BOQ]] -> 0 | F231: =SUMIF('Goods Receipt'!$J:$J,Over_all[[#This Row],[Item Description]],'Goods Receipt'!$M:$M) -> 0 | G231: =IF(Over_all[[#This Row],[BOQ]]-Over_all[[#This Row],[Received]]>=0,Over_all[[#This Row],[BOQ]]-Over_all[[#This Row],[Received]],"") -> 0 | H231: =IF(Over_all[[#This Row],[BOQ]]-Over_all[[#This Row],[Received]]<0,Over_all[[#This Row],[BOQ]]-Over_all[[#This Row],[Received]],"") | J231: =Over_all[[#This Row],[Received]] -> 0 | K231: =SUMIF(ISSUE!$F:$F,Over_all[[#This Row],[Item Description]],ISSUE!$I:$I) -> 0 | L231: =Over_all[[#This Row],[Received.]]-Over_all[[#This Row],[Issued]] -> 0
A232: =BOQ[[#This Row],[S.No]] -> Q | B232: =BOQ[[#This Row],[Item Description]] -> CCTV | C232: =BOQ[[#This Row],[Make / Vendor]] -> 0 | D232: =BOQ[[#This Row],[Unit]] -> 0 | E232: =BOQ[[#This Row],[BOQ]] -> 0 | F232: =SUMIF('Goods Receipt'!$J:$J,Over_all[[#This Row],[Item Description]],'Goods Receipt'!$M:$M) -> 0 | G232: =IF(Over_all[[#This Row],[BOQ]]-Over_all[[#This Row],[Received]]>=0,Over_all[[#This Row],[BOQ]]-Over_all[[#This Row],[Received]],"") -> 0 | H232: =IF(Over_all[[#This Row],[BOQ]]-Over_all[[#This Row],[Received]]<0,Over_all[[#This Row],[BOQ]]-Over_all[[#This Row],[Received]],"") | J232: =Over_all[[#This Row],[Received]] -> 0 | K232: =SUMIF(ISSUE!$F:$F,Over_all[[#This Row],[Item Description]],ISSUE!$I:$I) -> 0 | L232: =Over_all[[#This Row],[Received.]]-Over_all[[#This Row],[Issued]] -> 0
A233: =BOQ[[#This Row],[S.No]] -> 0 | B233: =BOQ[[#This Row],[Item Description]] -> 0 | C233: =BOQ[[#This Row],[Make / Vendor]] -> 0 | D233: =BOQ[[#This Row],[Unit]] -> 0 | E233: =BOQ[[#This Row],[BOQ]] -> 0 | F233: =SUMIF('Goods Receipt'!$J:$J,Over_all[[#This Row],[Item Description]],'Goods Receipt'!$M:$M) -> 0 | G233: =IF(Over_all[[#This Row],[BOQ]]-Over_all[[#This Row],[Received]]>=0,Over_all[[#This Row],[BOQ]]-Over_all[[#This Row],[Received]],"") -> 0 | H233: =IF(Over_all[[#This Row],[BOQ]]-Over_all[[#This Row],[Received]]<0,Over_all[[#This Row],[BOQ]]-Over_all[[#This Row],[Received]],"") | J233: =Over_all[[#This Row],[Received]] -> 0 | K233: =SUMIF(ISSUE!$F:$F,Over_all[[#This Row],[Item Description]],ISSUE!$I:$I) -> 0 | L233: =Over_all[[#This Row],[Received.]]-Over_all[[#This Row],[Issued]] -> 0
A234: =BOQ[[#This Row],[S.No]] -> R | B234: =BOQ[[#This Row],[Item Description]] -> NIFPS | C234: =BOQ[[#This Row],[Make / Vendor]] -> 0 | D234: =BOQ[[#This Row],[Unit]] -> 0 | E234: =BOQ[[#This Row],[BOQ]] -> 0 | F234: =SUMIF('Goods Receipt'!$J:$J,Over_all[[#This Row],[Item Description]],'Goods Receipt'!$M:$M) -> 0 | G234: =IF(Over_all[[#This Row],[BOQ]]-Over_all[[#This Row],[Received]]>=0,Over_all[[#This Row],[BOQ]]-Over_all[[#This Row],[Received]],"") -> 0 | H234: =IF(Over_all[[#This Row],[BOQ]]-Over_all[[#This Row],[Received]]<0,Over_all[[#This Row],[BOQ]]-Over_all[[#This Row],[Received]],"") | J234: =Over_all[[#This Row],[Received]] -> 0 | K234: =SUMIF(ISSUE!$F:$F,Over_all[[#This Row],[Item Description]],ISSUE!$I:$I) -> 0 | L234: =Over_all[[#This Row],[Received.]]-Over_all[[#This Row],[Issued]] -> 0
A235: =BOQ[[#This Row],[S.No]] -> 1 | B235: =BOQ[[#This Row],[Item Description]] -> N2 Fire Production System | C235: =BOQ[[#This Row],[Make / Vendor]] -> 0 | D235: =BOQ[[#This Row],[Unit]] -> Nos | E235: =BOQ[[#This Row],[BOQ]] -> 0 | F235: =SUMIF('Goods Receipt'!$J:$J,Over_all[[#This Row],[Item Description]],'Goods Receipt'!$M:$M) -> 1 | G235: =IF(Over_all[[#This Row],[BOQ]]-Over_all[[#This Row],[Received]]>=0,Over_all[[#This Row],[BOQ]]-Over_all[[#This Row],[Received]],"") | H235: =IF(Over_all[[#This Row],[BOQ]]-Over_all[[#This Row],[Received]]<0,Over_all[[#This Row],[BOQ]]-Over_all[[#This Row],[Received]],"") -> -1 | J235: =Over_all[[#This Row],[Received]] -> 1 | K235: =SUMIF(ISSUE!$F:$F,Over_all[[#This Row],[Item Description]],ISSUE!$I:$I) -> 0 | L235: =Over_all[[#This Row],[Received.]]-Over_all[[#This Row],[Issued]] -> 1
A236: =BOQ[[#This Row],[S.No]] -> 2 | B236: =BOQ[[#This Row],[Item Description]] -> Fire Extingushing Cubicle | C236: =BOQ[[#This Row],[Make / Vendor]] -> 0 | D236: =BOQ[[#This Row],[Unit]] -> Nos | E236: =BOQ[[#This Row],[BOQ]] -> 0 | F236: =SUMIF('Goods Receipt'!$J:$J,Over_all[[#This Row],[Item Description]],'Goods Receipt'!$M:$M) -> 1 | G236: =IF(Over_all[[#This Row],[BOQ]]-Over_all[[#This Row],[Received]]>=0,Over_all[[#This Row],[BOQ]]-Over_all[[#This Row],[Received]],"") | H236: =IF(Over_all[[#This Row],[BOQ]]-Over_all[[#This Row],[Received]]<0,Over_all[[#This Row],[BOQ]]-Over_all[[#This Row],[Received]],"") -> -1 | J236: =Over_all[[#This Row],[Received]] -> 1 | K236: =SUMIF(ISSUE!$F:$F,Over_all[[#This Row],[Item Description]],ISSUE!$I:$I) -> 0 | L236: =Over_all[[#This Row],[Received.]]-Over_all[[#This Row],[Issued]] -> 1
A237: =BOQ[[#This Row],[S.No]] -> 3 | B237: =BOQ[[#This Row],[Item Description]] -> Control Box | C237: =BOQ[[#This Row],[Make / Vendor]] -> 0 | D237: =BOQ[[#This Row],[Unit]] -> Nos | E237: =BOQ[[#This Row],[BOQ]] -> 0 | F237: =SUMIF('Goods Receipt'!$J:$J,Over_all[[#This Row],[Item Description]],'Goods Receipt'!$M:$M) -> 1 | G237: =IF(Over_all[[#This Row],[BOQ]]-Over_all[[#This Row],[Received]]>=0,Over_all[[#This Row],[BOQ]]-Over_all[[#This Row],[Received]],"") | H237: =IF(Over_all[[#This Row],[BOQ]]-Over_all[[#This Row],[Received]]<0,Over_all[[#This Row],[BOQ]]-Over_all[[#This Row],[Received]],"") -> -1 | J237: =Over_all[[#This Row],[Received]] -> 1 | K237: =SUMIF(ISSUE!$F:$F,Over_all[[#This Row],[Item Description]],ISSUE!$I:$I) -> 0 | L237: =Over_all[[#This Row],[Received.]]-Over_all[[#This Row],[Issued]] -> 1
A238: =BOQ[[#This Row],[S.No]] -> 4 | B238: =BOQ[[#This Row],[Item Description]] -> Fire Detectors | C238: =BOQ[[#This Row],[Make / Vendor]] -> 0 | D238: =BOQ[[#This Row],[Unit]] -> Nos | E238: =BOQ[[#This Row],[BOQ]] -> 0 | F238: =SUMIF('Goods Receipt'!$J:$J,Over_all[[#This Row],[Item Description]],'Goods Receipt'!$M:$M) -> 8 | G238: =IF(Over_all[[#This Row],[BOQ]]-Over_all[[#This Row],[Received]]>=0,Over_all[[#This Row],[BOQ]]-Over_all[[#This Row],[Received]],"") | H238: =IF(Over_all[[#This Row],[BOQ]]-Over_all[[#This Row],[Received]]<0,Over_all[[#This Row],[BOQ]]-Over_all[[#This Row],[Received]],"") -> -8 | J238: =Over_all[[#This Row],[Received]] -> 8 | K238: =SUMIF(ISSUE!$F:$F,Over_all[[#This Row],[Item Description]],ISSUE!$I:$I) -> 0 | L238: =Over_all[[#This Row],[Received.]]-Over_all[[#This Row],[Issued]] -> 8
A239: =BOQ[[#This Row],[S.No]] -> 5 | B239: =BOQ[[#This Row],[Item Description]] -> Signal Box | C239: =BOQ[[#This Row],[Make / Vendor]] -> 0 | D239: =BOQ[[#This Row],[Unit]] -> Nos | E239: =BOQ[[#This Row],[BOQ]] -> 0 | F239: =SUMIF('Goods Receipt'!$J:$J,Over_all[[#This Row],[Item Description]],'Goods Receipt'!$M:$M) -> 1 | G239: =IF(Over_all[[#This Row],[BOQ]]-Over_all[[#This Row],[Received]]>=0,Over_all[[#This Row],[BOQ]]-Over_all[[#This Row],[Received]],"") | H239: =IF(Over_all[[#This Row],[BOQ]]-Over_all[[#This Row],[Received]]<0,Over_all[[#This Row],[BOQ]]-Over_all[[#This Row],[Received]],"") -> -1 | J239: =Over_all[[#This Row],[Received]] -> 1 | K239: =SUMIF(ISSUE!$F:$F,Over_all[[#This Row],[Item Description]],ISSUE!$I:$I) -> 0 | L239: =Over_all[[#This Row],[Received.]]-Over_all[[#This Row],[Issued]] -> 1
A240: =BOQ[[#This Row],[S.No]] -> 6 | B240: =BOQ[[#This Row],[Item Description]] -> Transformer Conservator Isolation Valve | C240: =BOQ[[#This Row],[Make / Vendor]] -> 0 | D240: =BOQ[[#This Row],[Unit]] -> Nos | E240: =BOQ[[#This Row],[BOQ]] -> 0 | F240: =SUMIF('Goods Receipt'!$J:$J,Over_all[[#This Row],[Item Description]],'Goods Receipt'!$M:$M) -> 1 | G240: =IF(Over_all[[#This Row],[BOQ]]-Over_all[[#This Row],[Received]]>=0,Over_all[[#This Row],[BOQ]]-Over_all[[#This Row],[Received]],"") | H240: =IF(Over_all[[#This Row],[BOQ]]-Over_all[[#This Row],[Received]]<0,Over_all[[#This Row],[BOQ]]-Over_all[[#This Row],[Received]],"") -> -1 | J240: =Over_all[[#This Row],[Received]] -> 1 | K240: =SUMIF(ISSUE!$F:$F,Over_all[[#This Row],[Item Description]],ISSUE!$I:$I) -> 0 | L240: =Over_all[[#This Row],[Received.]]-Over_all[[#This Row],[Issued]] -> 1
A241: =BOQ[[#This Row],[S.No]] -> 7 | B241: =BOQ[[#This Row],[Item Description]] -> Keys | C241: =BOQ[[#This Row],[Make / Vendor]] -> 0 | D241: =BOQ[[#This Row],[Unit]] -> Nos | E241: =BOQ[[#This Row],[BOQ]] -> 0 | F241: =SUMIF('Goods Receipt'!$J:$J,Over_all[[#This Row],[Item Description]],'Goods Receipt'!$M:$M) -> 6 | G241: =IF(Over_all[[#This Row],[BOQ]]-Over_all[[#This Row],[Received]]>=0,Over_all[[#This Row],[BOQ]]-Over_all[[#This Row],[Received]],"") | H241: =IF(Over_all[[#This Row],[BOQ]]-Over_all[[#This Row],[Received]]<0,Over_all[[#This Row],[BOQ]]-Over_all[[#This Row],[Received]],"") -> -6 | J241: =Over_all[[#This Row],[Received]] -> 6 | K241: =SUMIF(ISSUE!$F:$F,Over_all[[#This Row],[Item Description]],ISSUE!$I:$I) -> 0 | L241: =Over_all[[#This Row],[Received.]]-Over_all[[#This Row],[Issued]] -> 6
A242: =BOQ[[#This Row],[S.No]] -> 8 | B242: =BOQ[[#This Row],[Item Description]] -> FS Cable | C242: =BOQ[[#This Row],[Make / Vendor]] -> 0 | D242: =BOQ[[#This Row],[Unit]] -> Mtr | E242: =BOQ[[#This Row],[BOQ]] -> 0 | F242: =SUMIF('Goods Receipt'!$J:$J,Over_all[[#This Row],[Item Description]],'Goods Receipt'!$M:$M) -> 40 | G242: =IF(Over_all[[#This Row],[BOQ]]-Over_all[[#This Row],[Received]]>=0,Over_all[[#This Row],[BOQ]]-Over_all[[#This Row],[Received]],"") | H242: =IF(Over_all[[#This Row],[BOQ]]-Over_all[[#This Row],[Received]]<0,Over_all[[#This Row],[BOQ]]-Over_all[[#This Row],[Received]],"") -> -40 | J242: =Over_all[[#This Row],[Received]] -> 40 | K242: =SUMIF(ISSUE!$F:$F,Over_all[[#This Row],[Item Description]],ISSUE!$I:$I) -> 0 | L242: =Over_all[[#This Row],[Received.]]-Over_all[[#This Row],[Issued]] -> 40
A243: =BOQ[[#This Row],[S.No]] -> 9 | B243: =BOQ[[#This Row],[Item Description]] -> Fire Detectors Cover | C243: =BOQ[[#This Row],[Make / Vendor]] -> 0 | D243: =BOQ[[#This Row],[Unit]] -> Nos | E243: =BOQ[[#This Row],[BOQ]] -> 0 | F243: =SUMIF('Goods Receipt'!$J:$J,Over_all[[#This Row],[Item Description]],'Goods Receipt'!$M:$M) -> 8 | G243: =IF(Over_all[[#This Row],[BOQ]]-Over_all[[#This Row],[Received]]>=0,Over_all[[#This Row],[BOQ]]-Over_all[[#This Row],[Received]],"") | H243: =IF(Over_all[[#This Row],[BOQ]]-Over_all[[#This Row],[Received]]<0,Over_all[[#This Row],[BOQ]]-Over_all[[#This Row],[Received]],"") -> -8 | J243: =Over_all[[#This Row],[Received]] -> 8 | K243: =SUMIF(ISSUE!$F:$F,Over_all[[#This Row],[Item Description]],ISSUE!$I:$I) -> 0 | L243: =Over_all[[#This Row],[Received.]]-Over_all[[#This Row],[Issued]] -> 8
... A294: =BOQ[[#This Row],[S.No]] -> 0 | B294: =BOQ[[#This Row],[Item Description]] -> 0 | C294: =BOQ[[#This Row],[Make / Vendor]] -> 0 | D294: =BOQ[[#This Row],[Unit]] -> 0 | E294: =BOQ[[#This Row],[BOQ]] -> 0 | F294: =SUMIF('Goods Receipt'!$J:$J,Over_all[[#This Row],[Item Description]],'Goods Receipt'!$M:$M) -> 0 | G294: =IF(Over_all[[#This Row],[BOQ]]-Over_all[[#This Row],[Received]]>=0,Over_all[[#This Row],[BOQ]]-Over_all[[#This Row],[Received]],"") -> 0 | H294: =IF(Over_all[[#This Row],[BOQ]]-Over_all[[#This Row],[Received]]<0,Over_all[[#This Row],[BOQ]]-Over_all[[#This Row],[Received]],"") | J294: =Over_all[[#This Row],[Received]] -> 0 | K294: =SUMIF(ISSUE!$F:$F,Over_all[[#This Row],[Item Description]],ISSUE!$I:$I) -> 0 | L294: =Over_all[[#This Row],[Received.]]-Over_all[[#This Row],[Issued]] -> 0
A295: =BOQ[[#This Row],[S.No]] -> X | B295: =BOQ[[#This Row],[Item Description]] -> Bus_Duct | C295: =BOQ[[#This Row],[Make / Vendor]] -> 0 | D295: =BOQ[[#This Row],[Unit]] -> 0 | F295: =SUMIF('Goods Receipt'!J:J,Over_all[[#This Row],[Item Description]],'Goods Receipt'!M:M) -> 0 | G295: =IF(Over_all[[#This Row],[BOQ]]-Over_all[[#This Row],[Received]]>=0,Over_all[[#This Row],[BOQ]]-Over_all[[#This Row],[Received]],"") -> 0 | H295: =IF(Over_all[[#This Row],[BOQ]]-Over_all[[#This Row],[Received]]<0,Over_all[[#This Row],[BOQ]]-Over_all[[#This Row],[Received]],"") | J295: =Over_all[[#This Row],[Received]] -> 0 | K295: =SUMIF(ISSUE!$F:$F,Over_all[[#This Row],[Item Description]],ISSUE!$I:$I) -> 0 | L295: =Over_all[[#This Row],[Received.]]-Over_all[[#This Row],[Issued]] -> 0
A296: =BOQ[[#This Row],[S.No]] -> 1 | B296: =BOQ[[#This Row],[Item Description]] -> 5000A TP Air Insulated Bus duct Stright Run | C296: =BOQ[[#This Row],[Make / Vendor]] -> 0 | D296: =BOQ[[#This Row],[Unit]] -> Mtr | F296: =SUMIF('Goods Receipt'!J:J,Over_all[[#This Row],[Item Description]],'Goods Receipt'!M:M) -> 37 | G296: =IF(Over_all[[#This Row],[BOQ]]-Over_all[[#This Row],[Received]]>=0,Over_all[[#This Row],[BOQ]]-Over_all[[#This Row],[Received]],"") | H296: =IF(Over_all[[#This Row],[BOQ]]-Over_all[[#This Row],[Received]]<0,Over_all[[#This Row],[BOQ]]-Over_all[[#This Row],[Received]],"") -> -37 | J296: =Over_all[[#This Row],[Received]] -> 37 | K296: =SUMIF(ISSUE!$F:$F,Over_all[[#This Row],[Item Description]],ISSUE!$I:$I) -> 0 | L296: =Over_all[[#This Row],[Received.]]-Over_all[[#This Row],[Issued]] -> 37
A297: =BOQ[[#This Row],[S.No]] -> 2 | B297: =BOQ[[#This Row],[Item Description]] -> 5000A Copper Flexible (Traafo.End ) | C297: =BOQ[[#This Row],[Make / Vendor]] -> 0 | D297: =BOQ[[#This Row],[Unit]] -> Set | E297: =BOQ[[#This Row],[BOQ]] -> 0 | F297: =SUMIF('Goods Receipt'!$J:$J,Over_all[[#This Row],[Item Description]],'Goods Receipt'!$M:$M) -> 4 | G297: =IF(Over_all[[#This Row],[BOQ]]-Over_all[[#This Row],[Received]]>=0,Over_all[[#This Row],[BOQ]]-Over_all[[#This Row],[Received]],"") | H297: =IF(Over_all[[#This Row],[BOQ]]-Over_all[[#This Row],[Received]]<0,Over_all[[#This Row],[BOQ]]-Over_all[[#This Row],[Received]],"") -> -4 | J297: =Over_all[[#This Row],[Received]] -> 4 | K297: =SUMIF(ISSUE!$F:$F,Over_all[[#This Row],[Item Description]],ISSUE!$I:$I) -> 0 | L297: =Over_all[[#This Row],[Received.]]-Over_all[[#This Row],[Issued]] -> 4
A298: =BOQ[[#This Row],[S.No]] -> 3 | B298: =BOQ[[#This Row],[Item Description]] -> 5000A Aluminium Flexible ( Panel End ) | C298: =BOQ[[#This Row],[Make / Vendor]] -> 0 | D298: =BOQ[[#This Row],[Unit]] -> Set | E298: =BOQ[[#This Row],[BOQ]] -> 0 | F298: =SUMIF('Goods Receipt'!$J:$J,Over_all[[#This Row],[Item Description]],'Goods Receipt'!$M:$M) -> 4 | G298: =IF(Over_all[[#This Row],[BOQ]]-Over_all[[#This Row],[Received]]>=0,Over_all[[#This Row],[BOQ]]-Over_all[[#This Row],[Received]],"") | H298: =IF(Over_all[[#This Row],[BOQ]]-Over_all[[#This Row],[Received]]<0,Over_all[[#This Row],[BOQ]]-Over_all[[#This Row],[Received]],"") -> -4 | J298: =Over_all[[#This Row],[Received]] -> 4 | K298: =SUMIF(ISSUE!$F:$F,Over_all[[#This Row],[Item Description]],ISSUE!$I:$I) -> 0 | L298: =Over_all[[#This Row],[Received.]]-Over_all[[#This Row],[Issued]] -> 4
A299: =BOQ[[#This Row],[S.No]] -> 4 | B299: =BOQ[[#This Row],[Item Description]] -> Bus Duct Accessories | C299: =BOQ[[#This Row],[Make / Vendor]] -> 0 | D299: =BOQ[[#This Row],[Unit]] -> Nos | E299: =BOQ[[#This Row],[BOQ]] -> 0 | F299: =SUMIF('Goods Receipt'!$J:$J,Over_all[[#This Row],[Item Description]],'Goods Receipt'!$M:$M) -> 4 | G299: =IF(Over_all[[#This Row],[BOQ]]-Over_all[[#This Row],[Received]]>=0,Over_all[[#This Row],[BOQ]]-Over_all[[#This Row],[Received]],"") | H299: =IF(Over_all[[#This Row],[BOQ]]-Over_all[[#This Row],[Received]]<0,Over_all[[#This Row],[BOQ]]-Over_all[[#This Row],[Received]],"") -> -4 | J299: =Over_all[[#This Row],[Received]] -> 4 | K299: =SUMIF(ISSUE!$F:$F,Over_all[[#This Row],[Item Description]],ISSUE!$I:$I) -> 0 | L299: =Over_all[[#This Row],[Received.]]-Over_all[[#This Row],[Issued]] -> 4
A300: =BOQ[[#This Row],[S.No]] -> 0 | B300: =BOQ[[#This Row],[Item Description]] -> 0 | C300: =BOQ[[#This Row],[Make / Vendor]] -> 0 | D300: =BOQ[[#This Row],[Unit]] -> 0 | E300: =BOQ[[#This Row],[BOQ]] -> 0 | F300: =SUMIF('Goods Receipt'!$J:$J,Over_all[[#This Row],[Item Description]],'Goods Receipt'!$M:$M) -> 0 | G300: =IF(Over_all[[#This Row],[BOQ]]-Over_all[[#This Row],[Received]]>=0,Over_all[[#This Row],[BOQ]]-Over_all[[#This Row],[Received]],"") -> 0 | H300: =IF(Over_all[[#This Row],[BOQ]]-Over_all[[#This Row],[Received]]<0,Over_all[[#This Row],[BOQ]]-Over_all[[#This Row],[Received]],"") | J300: =Over_all[[#This Row],[Received]] -> 0 | K300: =SUMIF(ISSUE!$F:$F,Over_all[[#This Row],[Item Description]],ISSUE!$I:$I) -> 0 | L300: =Over_all[[#This Row],[Received.]]-Over_all[[#This Row],[Issued]] -> 0
A301: =BOQ[[#This Row],[S.No]] -> Y | B301: =BOQ[[#This Row],[Item Description]] -> Cable_Route_Marker | C301: =BOQ[[#This Row],[Make / Vendor]] -> 0 | D301: =BOQ[[#This Row],[Unit]] -> 0 | E301: =BOQ[[#This Row],[BOQ]] -> 0 | F301: =SUMIF('Goods Receipt'!$J:$J,Over_all[[#This Row],[Item Description]],'Goods Receipt'!$M:$M) -> 0 | G301: =IF(Over_all[[#This Row],[BOQ]]-Over_all[[#This Row],[Received]]>=0,Over_all[[#This Row],[BOQ]]-Over_all[[#This Row],[Received]],"") -> 0 | H301: =IF(Over_all[[#This Row],[BOQ]]-Over_all[[#This Row],[Received]]<0,Over_all[[#This Row],[BOQ]]-Over_all[[#This Row],[Received]],"") | J301: =Over_all[[#This Row],[Received]] -> 0 | K301: =SUMIF(ISSUE!$F:$F,Over_all[[#This Row],[Item Description]],ISSUE!$I:$I) -> 0 | L301: =Over_all[[#This Row],[Received.]]-Over_all[[#This Row],[Issued]] -> 0
A302: =BOQ[[#This Row],[S.No]] -> 1 | B302: =BOQ[[#This Row],[Item Description]] -> LT Cable Route Marker | C302: =BOQ[[#This Row],[Make / Vendor]] -> 0 | D302: =BOQ[[#This Row],[Unit]] -> Nos | F302: =SUMIF('Goods Receipt'!J:J,Over_all[[#This Row],[Item Description]],'Goods Receipt'!M:M) -> 240 | G302: =IF(Over_all[[#This Row],[BOQ]]-Over_all[[#This Row],[Received]]>=0,Over_all[[#This Row],[BOQ]]-Over_all[[#This Row],[Received]],"") | H302: =IF(Over_all[[#This Row],[BOQ]]-Over_all[[#This Row],[Received]]<0,Over_all[[#This Row],[BOQ]]-Over_all[[#This Row],[Received]],"") -> -240 | J302: =Over_all[[#This Row],[Received]] -> 240 | K302: =SUMIF(ISSUE!$F:$F,Over_all[[#This Row],[Item Description]],ISSUE!$I:$I) -> 0 | L302: =Over_all[[#This Row],[Received.]]-Over_all[[#This Row],[Issued]] -> 240
A303: =BOQ[[#This Row],[S.No]] -> 2 | B303: =BOQ[[#This Row],[Item Description]] -> HT Cable Route Marker | C303: =BOQ[[#This Row],[Make / Vendor]] -> 0 | D303: =BOQ[[#This Row],[Unit]] -> Nos | F303: =SUMIF('Goods Receipt'!J:J,Over_all[[#This Row],[Item Description]],'Goods Receipt'!M:M) -> 20 | G303: =IF(Over_all[[#This Row],[BOQ]]-Over_all[[#This Row],[Received]]>=0,Over_all[[#This Row],[BOQ]]-Over_all[[#This Row],[Received]],"") | H303: =IF(Over_all[[#This Row],[BOQ]]-Over_all[[#This Row],[Received]]<0,Over_all[[#This Row],[BOQ]]-Over_all[[#This Row],[Received]],"") -> -20 | J303: =Over_all[[#This Row],[Received]] -> 20 | K303: =SUMIF(ISSUE!$F:$F,Over_all[[#This Row],[Item Description]],ISSUE!$I:$I) -> 0 | L303: =Over_all[[#This Row],[Received.]]-Over_all[[#This Row],[Issued]] -> 20
A304: =BOQ[[#This Row],[S.No]] -> 3 | B304: =BOQ[[#This Row],[Item Description]] -> DC Cable Route Marker | C304: =BOQ[[#This Row],[Make / Vendor]] -> 0 | D304: =BOQ[[#This Row],[Unit]] -> Nos | E304: =BOQ[[#This Row],[BOQ]] -> 0 | F304: =SUMIF('Goods Receipt'!$J:$J,Over_all[[#This Row],[Item Description]],'Goods Receipt'!$M:$M) -> 80 | G304: =IF(Over_all[[#This Row],[BOQ]]-Over_all[[#This Row],[Received]]>=0,Over_all[[#This Row],[BOQ]]-Over_all[[#This Row],[Received]],"") | H304: =IF(Over_all[[#This Row],[BOQ]]-Over_all[[#This Row],[Received]]<0,Over_all[[#This Row],[BOQ]]-Over_all[[#This Row],[Received]],"") -> -80 | J304: =Over_all[[#This Row],[Received]] -> 80 | K304: =SUMIF(ISSUE!$F:$F,Over_all[[#This Row],[Item Description]],ISSUE!$I:$I) -> 0 | L304: =Over_all[[#This Row],[Received.]]-Over_all[[#This Row],[Issued]] -> 80
A305: =BOQ[[#This Row],[S.No]] -> 0 | B305: =BOQ[[#This Row],[Item Description]] -> 0 | C305: =BOQ[[#This Row],[Make / Vendor]] -> 0 | D305: =BOQ[[#This Row],[Unit]] -> 0 | E305: =BOQ[[#This Row],[BOQ]] -> 0 | F305: =SUMIF('Goods Receipt'!$J:$J,Over_all[[#This Row],[Item Description]],'Goods Receipt'!$M:$M) -> 0 | G305: =IF(Over_all[[#This Row],[BOQ]]-Over_all[[#This Row],[Received]]>=0,Over_all[[#This Row],[BOQ]]-Over_all[[#This Row],[Received]],"") -> 0 | H305: =IF(Over_all[[#This Row],[BOQ]]-Over_all[[#This Row],[Received]]<0,Over_all[[#This Row],[BOQ]]-Over_all[[#This Row],[Received]],"") | J305: =Over_all[[#This Row],[Received]] -> 0 | K305: =SUMIF(ISSUE!$F:$F,Over_all[[#This Row],[Item Description]],ISSUE!$I:$I) -> 0 | L305: =Over_all[[#This Row],[Received.]]-Over_all[[#This Row],[Issued]] -> 0
A306: =BOQ[[#This Row],[S.No]] -> Z | B306: =BOQ[[#This Row],[Item Description]] -> Switch Yard_Equipments With Accessories | C306: =BOQ[[#This Row],[Make / Vendor]] -> 0 | D306: =BOQ[[#This Row],[Unit]] -> 0 | F306: =SUMIF('Goods Receipt'!J:J,Over_all[[#This Row],[Item Description]],'Goods Receipt'!M:M) -> 0 | G306: =IF(Over_all[[#This Row],[BOQ]]-Over_all[[#This Row],[Received]]>=0,Over_all[[#This Row],[BOQ]]-Over_all[[#This Row],[Received]],"") -> 0 | H306: =IF(Over_all[[#This Row],[BOQ]]-Over_all[[#This Row],[Received]]<0,Over_all[[#This Row],[BOQ]]-Over_all[[#This Row],[Received]],"") | J306: =Over_all[[#This Row],[Received]] -> 0 | K306: =SUMIF(ISSUE!$F:$F,Over_all[[#This Row],[Item Description]],ISSUE!$I:$I) -> 0 | L306: =Over_all[[#This Row],[Received.]]-Over_all[[#This Row],[Issued]] -> 0
A307: =BOQ[[#This Row],[S.No]] -> 1 | B307: =BOQ[[#This Row],[Item Description]] -> 66Kv CT For Metering | C307: =BOQ[[#This Row],[Make / Vendor]] -> 0 | D307: =BOQ[[#This Row],[Unit]] -> Nos | F307: =SUMIF('Goods Receipt'!J:J,Over_all[[#This Row],[Item Description]],'Goods Receipt'!M:M) -> 3 | G307: =IF(Over_all[[#This Row],[BOQ]]-Over_all[[#This Row],[Received]]>=0,Over_all[[#This Row],[BOQ]]-Over_all[[#This Row],[Received]],"") | H307: =IF(Over_all[[#This Row],[BOQ]]-Over_all[[#This Row],[Received]]<0,Over_all[[#This Row],[BOQ]]-Over_all[[#This Row],[Received]],"") -> -3 | J307: =Over_all[[#This Row],[Received]] -> 3 | K307: =SUMIF(ISSUE!$F:$F,Over_all[[#This Row],[Item Description]],ISSUE!$I:$I) -> 0 | L307: =Over_all[[#This Row],[Received.]]-Over_all[[#This Row],[Issued]] -> 3
A308: =BOQ[[#This Row],[S.No]] -> 2 | B308: =BOQ[[#This Row],[Item Description]] -> 66Kv CT For Protection -Ratio 100-150/1-1-1A | C308: =BOQ[[#This Row],[Make / Vendor]] -> 0 | D308: =BOQ[[#This Row],[Unit]] -> Nos | F308: =SUMIF('Goods Receipt'!J:J,Over_all[[#This Row],[Item Description]],'Goods Receipt'!M:M) -> 3 | G308: =IF(Over_all[[#This Row],[BOQ]]-Over_all[[#This Row],[Received]]>=0,Over_all[[#This Row],[BOQ]]-Over_all[[#This Row],[Received]],"") | H308: =IF(Over_all[[#This Row],[BOQ]]-Over_all[[#This Row],[Received]]<0,Over_all[[#This Row],[BOQ]]-Over_all[[#This Row],[Received]],"") -> -3 | J308: =Over_all[[#This Row],[Received]] -> 3 | K308: =SUMIF(ISSUE!$F:$F,Over_all[[#This Row],[Item Description]],ISSUE!$I:$I) -> 0 | L308: =Over_all[[#This Row],[Received.]]-Over_all[[#This Row],[Issued]] -> 3
A309: =BOQ[[#This Row],[S.No]] -> 3 | B309: =BOQ[[#This Row],[Item Description]] -> 66Kv CT For Protection -Ratio 300-600/1-1-1-A | C309: =BOQ[[#This Row],[Make / Vendor]] -> 0 | D309: =BOQ[[#This Row],[Unit]] -> Nos | F309: =SUMIF('Goods Receipt'!J:J,Over_all[[#This Row],[Item Description]],'Goods Receipt'!M:M) -> 3 | G309: =IF(Over_all[[#This Row],[BOQ]]-Over_all[[#This Row],[Received]]>=0,Over_all[[#This Row],[BOQ]]-Over_all[[#This Row],[Received]],"") | H309: =IF(Over_all[[#This Row],[BOQ]]-Over_all[[#This Row],[Received]]<0,Over_all[[#This Row],[BOQ]]-Over_all[[#This Row],[Received]],"") -> -3 | J309: =Over_all[[#This Row],[Received]] -> 3 | K309: =SUMIF(ISSUE!$F:$F,Over_all[[#This Row],[Item Description]],ISSUE!$I:$I) -> 0 | L309: =Over_all[[#This Row],[Received.]]-Over_all[[#This Row],[Issued]] -> 3
A310: =BOQ[[#This Row],[S.No]] -> 4 | B310: =BOQ[[#This Row],[Item Description]] -> 66Kv CT For Metering -Ratio of 100/1A | C310: =BOQ[[#This Row],[Make / Vendor]] -> 0 | D310: =BOQ[[#This Row],[Unit]] -> Nos | F310: 3 | G310: =IF(Over_all[[#This Row],[BOQ]]-Over_all[[#This Row],[Received]]>=0,Over_all[[#This Row],[BOQ]]-Over_all[[#This Row],[Received]],"") | H310: =IF(Over_all[[#This Row],[BOQ]]-Over_all[[#This Row],[Received]]<0,Over_all[[#This Row],[BOQ]]-Over_all[[#This Row],[Received]],"") -> -3 | J310: =Over_all[[#This Row],[Received]] -> 3 | K310: =SUMIF(ISSUE!$F:$F,Over_all[[#This Row],[Item Description]],ISSUE!$I:$I) -> 0 | L310: =Over_all[[#This Row],[Received.]]-Over_all[[#This Row],[Issued]] -> 3
A311: =BOQ[[#This Row],[S.No]] -> 5 | B311: =BOQ[[#This Row],[Item Description]] -> 66Kv PT For Metering 66kv/RT3/110V/RT3 | C311: =BOQ[[#This Row],[Make / Vendor]] -> 0 | D311: =BOQ[[#This Row],[Unit]] -> Nos | F311: 3 | G311: =IF(Over_all[[#This Row],[BOQ]]-Over_all[[#This Row],[Received]]>=0,Over_all[[#This Row],[BOQ]]-Over_all[[#This Row],[Received]],"") | H311: =IF(Over_all[[#This Row],[BOQ]]-Over_all[[#This Row],[Received]]<0,Over_all[[#This Row],[BOQ]]-Over_all[[#This Row],[Received]],"") -> -3 | J311: =Over_all[[#This Row],[Received]] -> 3 | K311: =SUMIF(ISSUE!$F:$F,Over_all[[#This Row],[Item Description]],ISSUE!$I:$I) -> 0 | L311: =Over_all[[#This Row],[Received.]]-Over_all[[#This Row],[Issued]] -> 3
A312: =BOQ[[#This Row],[S.No]] -> 6 | B312: =BOQ[[#This Row],[Item Description]] -> 66Kv CT For Metering -200/1A | C312: =BOQ[[#This Row],[Make / Vendor]] -> 0 | D312: =BOQ[[#This Row],[Unit]] -> Nos | F312: =SUMIF('Goods Receipt'!J:J,Over_all[[#This Row],[Item Description]],'Goods Receipt'!M:M) -> 3 | G312: =IF(Over_all[[#This Row],[BOQ]]-Over_all[[#This Row],[Received]]>=0,Over_all[[#This Row],[BOQ]]-Over_all[[#This Row],[Received]],"") | H312: =IF(Over_all[[#This Row],[BOQ]]-Over_all[[#This Row],[Received]]<0,Over_all[[#This Row],[BOQ]]-Over_all[[#This Row],[Received]],"") -> -3 | J312: =Over_all[[#This Row],[Received]] -> 3 | K312: =SUMIF(ISSUE!$F:$F,Over_all[[#This Row],[Item Description]],ISSUE!$I:$I) -> 0 | L312: =Over_all[[#This Row],[Received.]]-Over_all[[#This Row],[Issued]] -> 3
A313: =BOQ[[#This Row],[S.No]] -> 7 | B313: =BOQ[[#This Row],[Item Description]] -> 66Kv PT For Metering 66kv/RT3/110V/RT3 | C313: =BOQ[[#This Row],[Make / Vendor]] -> 0 | D313: =BOQ[[#This Row],[Unit]] -> Nos | F313: 3 | G313: =IF(Over_all[[#This Row],[BOQ]]-Over_all[[#This Row],[Received]]>=0,Over_all[[#This Row],[BOQ]]-Over_all[[#This Row],[Received]],"") | H313: =IF(Over_all[[#This Row],[BOQ]]-Over_all[[#This Row],[Received]]<0,Over_all[[#This Row],[BOQ]]-Over_all[[#This Row],[Received]],"") -> -3 | J313: =Over_all[[#This Row],[Received]] -> 3 | K313: =SUMIF(ISSUE!$F:$F,Over_all[[#This Row],[Item Description]],ISSUE!$I:$I) -> 0 | L313: =Over_all[[#This Row],[Received.]]-Over_all[[#This Row],[Issued]] -> 3
A314: =BOQ[[#This Row],[S.No]] -> 8 | B314: =BOQ[[#This Row],[Item Description]] -> 66Kv Control & Relay Panel | C314: =BOQ[[#This Row],[Make / Vendor]] -> 0 | D314: =BOQ[[#This Row],[Unit]] -> Nos | F314: =SUMIF('Goods Receipt'!J:J,Over_all[[#This Row],[Item Description]],'Goods Receipt'!M:M) -> 2 | G314: =IF(Over_all[[#This Row],[BOQ]]-Over_all[[#This Row],[Received]]>=0,Over_all[[#This Row],[BOQ]]-Over_all[[#This Row],[Received]],"") | H314: =IF(Over_all[[#This Row],[BOQ]]-Over_all[[#This Row],[Received]]<0,Over_all[[#This Row],[BOQ]]-Over_all[[#This Row],[Received]],"") -> -2 | J314: =Over_all[[#This Row],[Received]] -> 2 | K314: =SUMIF(ISSUE!$F:$F,Over_all[[#This Row],[Item Description]],ISSUE!$I:$I) -> 0 | L314: =Over_all[[#This Row],[Received.]]-Over_all[[#This Row],[Issued]] -> 2
A315: =BOQ[[#This Row],[S.No]] -> 9 | B315: =BOQ[[#This Row],[Item Description]] -> Switch Yard Materials & Structure & Structure Fasteners | C315: =BOQ[[#This Row],[Make / Vendor]] -> 0 | D315: =BOQ[[#This Row],[Unit]] -> lot | F315: =SUMIF('Goods Receipt'!J:J,Over_all[[#This Row],[Item Description]],'Goods Receipt'!M:M) -> 1 | G315: =IF(Over_all[[#This Row],[BOQ]]-Over_all[[#This Row],[Received]]>=0,Over_all[[#This Row],[BOQ]]-Over_all[[#This Row],[Received]],"") | H315: =IF(Over_all[[#This Row],[BOQ]]-Over_all[[#This Row],[Received]]<0,Over_all[[#This Row],[BOQ]]-Over_all[[#This Row],[Received]],"") -> -1 | J315: =Over_all[[#This Row],[Received]] -> 1 | K315: =SUMIF(ISSUE!$F:$F,Over_all[[#This Row],[Item Description]],ISSUE!$I:$I) -> 0 | L315: =Over_all[[#This Row],[Received.]]-Over_all[[#This Row],[Issued]] -> 1
A316: =BOQ[[#This Row],[S.No]] -> 0 | B316: =BOQ[[#This Row],[Item Description]] -> 0 | C316: =BOQ[[#This Row],[Make / Vendor]] -> 0 | D316: =BOQ[[#This Row],[Unit]] -> 0 | E316: =BOQ[[#This Row],[BOQ]] -> 0 | F316: =SUMIF('Goods Receipt'!$J:$J,Over_all[[#This Row],[Item Description]],'Goods Receipt'!$M:$M) -> 0 | G316: =IF(Over_all[[#This Row],[BOQ]]-Over_all[[#This Row],[Received]]>=0,Over_all[[#This Row],[BOQ]]-Over_all[[#This Row],[Received]],"") -> 0 | H316: =IF(Over_all[[#This Row],[BOQ]]-Over_all[[#This Row],[Received]]<0,Over_all[[#This Row],[BOQ]]-Over_all[[#This Row],[Received]],"") | J316: =Over_all[[#This Row],[Received]] -> 0 | K316: =SUMIF(ISSUE!$F:$F,Over_all[[#This Row],[Item Description]],ISSUE!$I:$I) -> 0 | L316: =Over_all[[#This Row],[Received.]]-Over_all[[#This Row],[Issued]] -> 0

Sheet Master Data
B2: Category | D2: Unit | F2: Assets | G2: Battery | H2: Bus_Duct | I2: Cable_Tray | J2: DC_Cables | K2: AC_Cables | L2: HT_Cables | M2: Earthing_cables | N2: Aux_Control_Cable | O2: Communication_Cable | P2: CCTV | Q2: UPS | R2: MCS | S2: Connectors | T2: Cable_Glands | U2: Cable_Termination_Kit | V2: Cable_Lugs | W2: Cable_Sleeve | X2: Cable_Route_Marker | Y2: Cable_Tie | Z2: Inverter | AA2: Transformers | AB2: HT_Panel | AC2: LT_Panel | AD2: Aux_UPS_Panel | AE2: Earthing | AF2: Pheriperal Boundary | AG2: Inverters_Structure | AH2: Lighting_arrestor | AI2: Street_Light | AJ2: Module_Mounting_Structure | AK2: MMS_Fasteners | AL2: NIFPS | AM2: Pipes | AN2: Solar_Modules | AO2: Safety_Equipments | AP2: Others | AQ2: Switch Yard_Equipments With Accessories | AR2: Scada
B3: Billable | D3: Nos | F3: Store Container | H3: 5000A TP Air Insulated Bus duct Stright Run | J3: DC Cable | K3: 3CX240Sqmm A2XFY UNSCR ATR UV AF 3.3 KV | L3: 3CX240Sqmm A2XFY 19/33KV HT Cable | M3: 1C X 50Sq.mm Copper Flexible Cable | N3: 3C X 35Sq.mm 1.1 Kv A2XFY Cable | O3: CAT-6 Cable | R3: UPVC Pipe 11/2'' | T3: 3C X 240 Sq.mm Double Compression Metal Gland | U3: 3C X 240 Sq.mm Indoor Typr Termination Kit | V3: 3C X 240 Sq.mm Bi Metallic Lug | W3: 3C X 240 Sq.mm Cable Heat Sleeve Red | X3: LT Cable Route Marker | Y3: 100X2.5MM UV Cable Tie Black | Z3: Solis 225K-EHV-5G Plus Grid Tie Solar PV Inverter | AA3: 6 MVA Transformer | AB3: 33KV HT VCB Panel | AC3: 800V LT Panel | AD3: AUX ACDB Panel | AE3: 25x3 MM GI Earth Strip | AF3: Precast Panel | AG3: Inverter Column Post (ISMC - 100x50x5mm - 3000mmL | AH3: ESE Train | AI3: NES-SL-30 | AJ3: Column Post - 120x50x20x2.0 MM | AK3: HEX BOLT+NUT+2PLN WSR+1SP WSR M-16x40 | AL3: N2 Fire Production System | AM3: 38x50 OD DWC Pipe (500MTR) UV & Anti Rodent) | AO3: Sand Bucket With Stend canopy | AP3: Yellow Warning Tape (LT 2500 Mtr,DC 1000 Mtr,HT 500 Mtr) | AQ3: 66Kv CT For Metering | AR3: MCR Panel
B4: Non-Billable | D4: Mtr | F4: Secucity Cabin | H4: 5000A Copper Flexible (Traafo.End ) | J4: 1CX6Sqmm DC Cable Black | N4: 4C X 6Sq.mm 1.1 Kv A2XWY Cable | O4: RS 485 ARM Cable | R4: UPVC Pipe 1'' | T4: 3C X 240 Sq.mm Double Bracing Metal Gland | V4: 3C X 240Sq.mm Aluminium Lug | W4: 3C X 240 Sq.mm Cable Heat Sleeve Yellow | X4: HT Cable Route Marker | Y4: 300X4.8MM UV Cable Tie Black | AA4: Radiators | AB4: 33KV HT VCB Panel (21C-1OG) Board Panel | AD4: UPS Panel | AE4: 50x6 MM GI Earth Strip | AF4: Precast Post | AG4: Inverter Support Pipe (SHS-40x40x2.5mm-1550mmL | AH4: 6MM Guy Rope | AI4: 6.5 Mtr HDGI Street Light Pole | AJ4: Column Ext - 50x50x2.0 MM | AK4: HEX BOLT+NUT+2PLN WSR+1SP WSR M-10x30 | AL4: Fire Extingushing Cubicle | AM4: 50 MM Coupler | AO4: CO2 Type Fire Extinguisher - 4.5 Kg | AP4: 300mm AL Rail | AQ4: 66Kv CT For Protection -Ratio 100-150/1-1-1A | AR4: ICR Panel
B5: Consumables | D5: Kg | H5: 5000A Aluminium Flexible ( Panel End ) | J5: 1CX6Sqmm DC Cable Red | N5: 2C X 6Sq.mm Flexible HRFR Cable | O5: 12F FO Cable | R5: Gardan Pipe | T5: 3C X 35 Sq.mm Double Bracing Metal Gland | V5: 1C X 50Sq.mm Copper Lug | W5: 3C X 240 Sq,mm Cable Heat Sleeve Bule | X5: DC Cable Route Marker | Y5: 300x4.6 SS Cable Tie | AA5: Marshalling Box | AE5: 40x6 MM Copper Earth Strip | AG5: Roof Support -1 (ISA 40x40x5mm - 600mm L | AH5: 6MM U Clamp | AI5: NES-SL-70 | AJ5: Module Mounting Strucyure - Purlin (P1) | AK5: HEX BOLT+NUT+2PLN WSR+1SP WSR M-12x30 | AL5: Control Box | AM5: 50 MM Elbow | AO5: CO2 Type Fire Extinguisher - 9 Kg | AP5: Portr.High | AQ5: 66Kv CT For Protection -Ratio 300-600/1-1-1-A | AR5: Operating Work Station With Pre Installation Software and keyboard &Mouse
B6: Safety | D6: Set | H6: Bus Duct Accessories | N6: 2C X 4Sq.mm Copper Flexible Cable | R6: UPVC Vall 1 1/2 | T6: 2C X 6 Sq.mm Double Bracing Metal Gland | V6: 4.0 Sq.mm Cu Ring Type Lug | W6: 50 Sq.mm Cable Heat Sleeve | AA6: Conservator Tank With Accessories | AG6: Roof Support -2 (ISA 40x40x5mm - 700mm L | AH6: Grount Hook for fixing guy cable | AI6: ARM Bracket | AJ6: Module Mounting Strucyure - Rafter | AK6: HEX BOLT+NUT+REC.WSR+ 1SP WSR M-10x30 | AL6: Fire Detectors | AM6: 50 MM Tee | AO6: ABC Type Fire Extinguisher - 6 Kg | AP6: PU Form | AQ6: 66Kv CT For Metering -Ratio of 100/1A | AR6: 32 Inch Display
B7: Tools and Tackles | D7: Lot | N7: 2C X 2.5 Sq.mm Copper Flexible Cable | R7: UPVC Vall 1 | T7: 4C X 6 Sq.mm Double Bracing Metal Gland | V7: 1C X 4.0 Sq.mm Cu Copper Lug | W7: 2C X 6 Sq.mm Cable Heat Sleeve | AA7: HV Cable Box & HV Cable Box Canopy Fitted | AG7: Roof Support -3 (ISA 40x40x5mm - 644mm L | AH7: J bolt (dia 18x500mm) for fixing mast base plate hole | AI7: Conduict | AJ7: Module Mounting Strucyure - Rafter Bracing Back | AK7: Rectangle Washer (40*20*11*3) Mechanical Plating | AL7: Signal Box | AM7: 50 MM O Ring | AO7: Safety Shoes (Allen copper-1156) | AP7: Cable Tag | AQ7: 66Kv PT For Metering 66kv/RT3/110V/RT3 | AR7: A4 Printer
B8: Assets | D8: Ltr | N8: 12C X 2.5 Sq.mm 1.1 Kv 2XFY Cable | R8: UPVC Elbow 1 1/2 | T8: 2C X 4.0 Sq.mm PVC Gland | V8: 35 Sq.mm Al Ring Type Lug | W8: 2C X 4 Sq.mm Cable Heat Sleeve | AA8: 33Kv Insulators | AG8: Purlin (SHA-30x30x2.5mm - 2200mm L | AH8: Down Conductor insulator BC 525 with nut bolt | AI8: Rod | AJ8: Module Mounting Strucyure - Bracing Connector | AK8: Hex Bolt,M8x20 | AL8: Transformer Conservator Isolation Valve | AM8: Np3 600 MM S&S Pipe | AO8: Safety Shoes (Labour) | AP8: Scada MCR | AQ8: 66Kv CT For Metering -200/1A | AR8: Wooden Table
B9: Others | D9: Coil | N9: 3C X 4 Sq.mm Copper Flexible Cable | R9: UPVC Elbow 1 | T9: 2C X 2.5 Sq.mm PVC Gland | V9: 2.5 Sq.mm Cu Ring Type Lug | W9: 4C X 6 Sq.mm Cable Heat Sleeve | AA9: Aluminium Gland Plate | AG9: Conduit Support Pipe (SHS-40x40x2.5mm - 1550mm L | AH9: OTC 25x3 | AI9: Junction Box | AJ9: Module Mounting Strucyure - Purlin (P2) | AK9: Hex Nut,M8 | AL9: Keys | AO9: Safety Gumboot | AP9: Scada ICR 1 | AQ9: 66Kv PT For Metering 66kv/RT3/110V/RT3 | AR9: Chair
D10: Pair | R10: UPVC Tee 1 1/2 | T10: 12C X 2.5 Sq.mm PVC Gland | V10: 2.5 Sq.mm Cu Pin Type Lug | W10: 2C X 2.5 Sq.mm Cable Heat Sleeve | AA10: Inspection Cover | AG10: Roof Sheet (1200x2400x0.5mm) | AH10: L shape | AI10: 3C X 1.5 Sq mm Copper Flexible Cable | AJ10: Module Mounting Strucyure - Col, to Rafter Bracing front | AK10: Plain WSR,M8 | AL10: FS Cable | AO10: Safety Relflectice Jacket Staff | AP10: Scada ICR 2 | AQ10: 66Kv Control & Relay Panel | AR10: SC-LC Patch Cord Single Mode
R11: UPVC Tee 1 | V11: 2.5 Sq.mm Cu Fork Type Lug | W11: 12 X 2.5 Sq.mm Cable Heat Sleeve | AA11: 50 X 06 mm Copper Flat | AG11: SS-304 (M12x80(SS-304-80mm L | AH11: Lightning flash counter | AI11: LED Arm | AJ11: Module Mounting Strucyure - Stay Bracing | AK11: Spring WSRM8 | AL11: Fire Detectors Cover | AO11: Safety Relflectice Jacket Orange | AP11: Radium Stickers 200 X 60 | AQ11: Switch Yard Materials & Structure & Structure Fasteners
R12: UPVC Redusar | V12: 6 Sq.mm Fork Type Copper Lug | AA12: Danger Plate | AG12: SS-304 (M10x80(SS-304-80mm L | AH12: GI supporting mast of 7 mtrs in 3 parts with base plate | AK12: M8 Serrated Washer | AL12: FRLS 12 Core Cable | AO12: Safety Helmet | AP12: Radium Stickers 300 X 60
R13: UPVC Redusar Tee | V13: 6 Sq.mm AL Ring Type Lug | AA13: Breather | AG13: SDS with EPDM washer | AH13: 17mm dia, 3mtr long copper bonded rod with clamp with nut and bolt,plain & spring | AL13: FRLS 4 Core Cable | AO13: Safety Helmet Green
B14: Sub-contractor Name | D14: Price | R14: UPVC Coplin 1 1/2 | V14: 6 Sq.mm Cu Pin Type Lug | AA14: Buchholz Relay & Buchholz Canopy | AH14: Earthcon | AL14: Supply of Pipe Fittings | AO14: Safety Helmet labour
B15: Inqilab | D15: Show | R15: UPVC Coplin 1 | V15: 16 Sq.mm Ring Type Lug | AA15: 450mm / 132w / 900 rpm With Wire Guard For Fan | AL15: Pipes For connection Between | AO15: Safety Hand Gloves (White Grey)
B16: Udaratva | D16: Hide | R16: UPVC Handcap 1 1/2 | AA16: Transformer Oil | AL16: 6'' GI Pipe -6Mtr Iength | AO16: Safety Hand Gloves Lether For Welding
R17: UPVC Handcap 1 | AO17: Safety Goggles
R18: Taki | AO18: Safety (Barrication Tap Roll)
R19: Motor | AO19: Full Body Harness With Soak Absorber
R20: Soket Set | AO20: Stretcher Foldable
R21: Preser Vall | AO21: First And Box
R22: NRV Vall 1 1/2 | AO22: Snack Cather Stick
R23: UPVC Union 1 1/2 | AO23: Safety Welding Helmat
AO24: CO2 Fire Extinguisher - 4.5Kg
AO25: Abc Type Fire Extinguisher - 4 Kg
AO26: Safety Fire Stand With 4 Buckets
AO27: Digital vernier caliper
AO28: Coating Thickness Tester
AO29: Earth Testing Kit
AO30: LOTO Kit
B31: Location | AO31: 5Kv Meco Make Megger
B32: Block-1 | AO32: 2000V AC/DC Clamp Meter -Meco
B33: PSS | AO33: Measuring Tap-5 MTR
AO34: Jacket &Bib pant,Hood,Class E Helmet With Face Shield ,Fabric Leathergloves and storage Bag
AO35: Screw Driver (Taparia)
AO36: Sprit Level
AO37: 33Kv Earthing Electrode

Sheet ISSUE
A2: S. No. | B2: Req Slip No. | C2: Date | D2: Item Category | E2: Item Types | F2: Item Description | G2: Unit | H2: Quantity Demanded | I2: Quantity Issued | J2: Sub-contractor Name | K2: Contractor Person (Received by) | L2: Location | M2: Recommanded Engineer (Name) | N2: Issued By | O2: Remarks
A3: 1 | B3: 5251 | C3: 45569 | D3: Billable | E3: MMS_Fasteners | F3: HEX BOLT+NUT+2PLN WSR+1SP WSR M-10x30 | G3: Set | H3: 0 | I3: 0 | J3: New Aditya | K3: Jay-Patel | L3: Phase 02 | M3: Sadham | N3: Sundar | O3: 1050 Return
A4: =+A3+1 -> 2 | B4: 5253 | C4: 45585 | D4: Billable | E4: Module_Mounting_Structure | F4: Column Post - 120x50x20x2.0 MM | G4: Nos | H4: 519 | I4: 519 | J4: Inqilab | K4: Piyush | L4: Phase 02 | M4: Sadham | N4: Sundar
A5: =+A4+1 -> 3 | B5: 5253 | C5: 45585 | D5: Billable | E5: Module_Mounting_Structure | F5: Column Ext - 50x50x2.0 MM | G5: Nos | H5: 498 | I5: 498 | J5: Inqilab | K5: Piyush | L5: Phase 02 | M5: Sadham | N5: Sundar
A6: 4 | B6: 5253 | C6: 45585 | D6: Billable | E6: MMS_Fasteners | F6: HEX BOLT+NUT+2PLN WSR+1SP WSR M-10x30 | G6: Set | H6: 2370 | I6: 2370 | J6: Inqilab | K6: Piyush | L6: Phase 02 | M6: Sadham | N6: Sundar
A7: =+A6+1 -> 5 | B7: 5254 | C7: 45589 | D7: Billable | E7: MMS_Fasteners | F7: HEX BOLT+NUT+2PLN WSR+1SP WSR M-10x30 | G7: Set | H7: 1600 | I7: 1600 | J7: Inqilab | K7: Piyush | L7: Phase 02 | M7: Sadham | N7: Sundar
A8: 6 | B8: 5255 | C8: 45590 | D8: Billable | E8: MMS_Fasteners | F8: HEX BOLT+NUT+2PLN WSR+1SP WSR M-10x30 | G8: Set | H8: 1050 | I8: 1050 | J8: Udaratva | K8: Venugopal | L8: Phase 02 | M8: Sadham | N8: Sundar
A9: 7 | B9: 5256 | C9: 45590 | D9: Billable | E9: Safety_Equipments | F9: Safety Shoes (Labour) | G9: Set | H9: 4 | I9: 4 | J9: Udaratva | K9: Venugopal | L9: Phase 02 | M9: Sadham | N9: Sundar
A10: 8 | B10: 5257 | C10: 45590 | D10: Billable | E10: Inverters_Structure | F10: Inverter Column Post (ISMC - 100x50x5mm - 3000mmL | G10: Nos | H10: 22 | I10: 22 | J10: Inqilab | K10: Piyush | L10: Phase 02 | M10: Sadham | N10: Sundar
A11: 9 | B11: 5257 | C11: 45590 | D11: Billable | E11: Inverters_Structure | F11: SS-304 (M12x80(SS-304-80mm L | G11: Set | H11: 88 | I11: 88 | J11: Inqilab | K11: Piyush | L11: Phase 02 | M11: Sadham | N11: Sundar
A12: 10 | B12: 5258 | C12: 45605 | D12: Billable | E12: Module_Mounting_Structure | F12: Column Post - 120x50x20x2.0 MM | G12: Nos | H12: 1000 | I12: 1000 | J12: Udaratva | K12: Venugopal | L12: Phase 02 | M12: Sadham | N12: Sundar
A13: 11 | B13: 5258 | C13: 45605 | D13: Billable | E13: Module_Mounting_Structure | F13: Column Ext - 50x50x2.0 MM | G13: Nos | H13: 1000 | I13: 1000 | J13: Udaratva | K13: Venugopal | L13: Phase 02 | M13: Sadham | N13: Sundar
A14: 12 | B14: 5259 | C14: 45605 | D14: Billable | E14: Module_Mounting_Structure | F14: Column Post - 120x50x20x2.0 MM | G14: Nos | H14: 1030 | I14: 1030 | J14: Inqilab | K14: Piyush | L14: Phase 02 | M14: Sadham | N14: Sundar
A15: 13 | B15: 5259 | C15: 45605 | D15: Billable | E15: Module_Mounting_Structure | F15: Column Ext - 50x50x2.0 MM | G15: Nos | H15: 1030 | I15: 1030 | J15: Inqilab | K15: Piyush | L15: Phase 02 | M15: Sadham | N15: Sundar
A16: 14 | B16: 5259 | C16: 45605 | D16: Billable | E16: MMS_Fasteners | F16: HEX BOLT+NUT+2PLN WSR+1SP WSR M-10x30 | G16: Set | H16: 2150 | I16: 2150 | J16: Inqilab | K16: Piyush | L16: Phase 02 | M16: Sadham | N16: Sundar
A17: 15 | B17: 5260 | C17: 45605 | D17: Billable | E17: Safety_Equipments | F17: Safety Shoes (Allen copper-1156) | G17: Set | H17: 1 | I17: 1 | K17: Birjesh Panchal | L17: Phase 02 | M17: Sadham | N17: Sundar | O17: Cilent
A18: 16 | B18: 5261 | C18: 45605 | D18: Billable | E18: Safety_Equipments | F18: Safety Shoes (Allen copper-1156) | G18: Set | H18: 1 | I18: 1 | K18: Prince | L18: Phase 02 | M18: Sadham | N18: Sundar | O18: Prozeal/O/M
A19: 17 | B19: 5262 | C19: 45605 | D19: Billable | E19: Safety_Equipments | F19: Safety Shoes (Allen copper-1156) | G19: Set | H19: 1 | I19: 1 | K19: Sunil Kumar | L19: Phase 02 | M19: Sadham | N19: Sundar | O19: Prozeal Q/C
A20: 18 | B20: 5262 | C20: 45605 | D20: Billable | E20: Safety_Equipments | F20: Safety Relflectice Jacket Staff | G20: Nos | H20: 1 | I20: 1 | K20: Sunil Kumar | L20: Phase 02 | M20: Sadham | N20: Sundar | O20: Prozeal Q/C
A21: 19 | B21: 5262 | C21: 45605 | D21: Billable | E21: Safety_Equipments | F21: Safety Helmet | G21: Nos | H21: 1 | I21: 1 | K21: Sunil Kumar | L21: Phase 02 | M21: Sadham | N21: Sundar | O21: Prozeal Q/C
A22: 20 | B22: 5263 | C22: 45609 | D22: Billable | E22: MMS_Fasteners | F22: HEX BOLT+NUT+2PLN WSR+1SP WSR M-10x30 | G22: Set | H22: 2100 | I22: 2100 | J22: Udaratva | K22: Venugopal | L22: Phase 02 | M22: Sadham | N22: Sundar
A23: 21 | B23: 5264 | C23: 45609 | D23: Billable | E23: Module_Mounting_Structure | F23: Module Mounting Strucyure - Rafter | G23: Nos | H23: 1090 | I23: 1090 | J23: Inqilab | K23: Piyush | L23: Phase 02 | M23: Sadham | N23: Sundar
A24: =+A23+1 -> 22 | B24: 5264 | C24: 45609 | D24: Billable | E24: Module_Mounting_Structure | F24: Module Mounting Strucyure - Col, to Rafter Bracing front | G24: Nos | H24: 1090 | I24: 1090 | J24: Inqilab | K24: Piyush | L24: Phase 02 | M24: Sadham | N24: Sundar
A25: =+A24+1 -> 23 | B25: 5264 | C25: 45609 | D25: Billable | E25: Module_Mounting_Structure | F25: Module Mounting Strucyure - Rafter Bracing Back | G25: Nos | H25: 1090 | I25: 1090 | J25: Inqilab | K25: Piyush | L25: Phase 02 | M25: Sadham | N25: Sundar
A26: =+A25+1 -> 24 | B26: 5264 | C26: 45609 | D26: Billable | E26: MMS_Fasteners | F26: Hex Bolt,M8x20 | G26: Nos | H26: 1510 | I26: 1510 | J26: Inqilab | K26: Piyush | L26: Phase 02 | M26: Sadham | N26: Sundar
A27: =+A26+1 -> 25 | B27: 5264 | C27: 45609 | D27: Billable | E27: MMS_Fasteners | F27: Hex Nut,M8 | G27: Nos | H27: 1510 | I27: 1510 | J27: Inqilab | K27: Piyush | L27: Phase 02 | M27: Sadham | N27: Sundar
A28: =+A27+1 -> 26 | B28: 5264 | C28: 45609 | D28: Billable | E28: MMS_Fasteners | F28: Plain WSR,M8 | G28: Nos | H28: 16302 | I28: 16302 | J28: Inqilab | K28: Piyush | L28: Phase 02 | M28: Sadham | N28: Sundar
A29: =+A28+1 -> 27 | B29: 5264 | C29: 45609 | D29: Billable | E29: MMS_Fasteners | F29: Spring WSRM8 | G29: Nos | H29: 21510 | I29: 21510 | J29: Inqilab | K29: Piyush | L29: Phase 02 | M29: Sadham | N29: Sundar
A30: =+A29+1 -> 28 | B30: 5265 | C30: 45611 | D30: Billable | E30: MMS_Fasteners | F30: HEX BOLT+NUT+2PLN WSR+1SP WSR M-10x30 | G30: Set | H30: 3500 | I30: 3500 | J30: Udaratva | K30: Venugopal | L30: Phase 02 | M30: Sadham | N30: Sundar
A31: =+A30+1 -> 29 | B31: 5265 | C31: 45611 | D31: Billable | E31: MMS_Fasteners | F31: HEX BOLT+NUT+2PLN WSR+1SP WSR M-12x30 | G31: Set | H31: 3750 | I31: 3750 | J31: Udaratva | K31: Venugopal | L31: Phase 02 | M31: Sadham | N31: Sundar
A32: =+A31+1 -> 30 | B32: 5265 | C32: 45611 | D32: Billable | E32: MMS_Fasteners | F32: HEX BOLT+NUT+2PLN WSR+1SP WSR M-16x40 | G32: Set | H32: 1000 | I32: 1000 | J32: Udaratva | K32: Venugopal | L32: Phase 02 | M32: Sadham | N32: Sundar
A33: =+A32+1 -> 31 | B33: 5265 | C33: 45611 | D33: Billable | E33: MMS_Fasteners | F33: HEX BOLT+NUT+REC.WSR+ 1SP WSR M-10x30 | G33: Set | H33: 5000 | I33: 5000 | J33: Udaratva | K33: Venugopal | L33: Phase 02 | M33: Sadham | N33: Sundar
A34: =+A33+1 -> 32 | B34: 5265 | C34: 45611 | D34: Billable | E34: Inverters_Structure | F34: Inverter Column Post (ISMC - 100x50x5mm - 3000mmL | G34: Nos | H34: 44 | I34: 44 | J34: Udaratva | K34: Venugopal | L34: Phase 02 | M34: Sadham | N34: Sundar
A35: =+A34+1 -> 33 | B35: 5265 | C35: 45611 | D35: Billable | E35: Inverters_Structure | F35: Inverter Support Pipe (SHS-40x40x2.5mm-1550mmL | G35: Nos | H35: 44 | I35: 44 | J35: Udaratva | K35: Venugopal | L35: Phase 02 | M35: Sadham | N35: Sundar
... A65: =+A64+1 -> 63 | B65: 5272 | C65: 45624 | D65: Billable | E65: Pipes | F65: 38x50 OD DWC Pipe (500MTR) UV & Anti Rodent) | G65: Mtr | H65: 1000 | I65: 1000 | J65: Inqilab | K65: Piyush | L65: Phase 02 | M65: Sadham | N65: Sundar
A66: =+A65+1 -> 64 | B66: 5272 | C66: 45624 | D66: Billable | E66: AC_Cables | F66: 3CX240Sqmm A2XFY UNSCR ATR UV AF 3.3 KV | G66: Mtr | H66: 1008 | I66: 1008 | J66: Inqilab | K66: Piyush | L66: Phase 02 | M66: Sadham | N66: Sundar | O66: Drum No:HT246599E24
A67: =+A66+1 -> 65 | B67: 5272 | C67: 45624 | D67: Billable | E67: AC_Cables | F67: 3CX240Sqmm A2XFY UNSCR ATR UV AF 3.3 KV | G67: Mtr | H67: 987 | I67: 987 | J67: Inqilab | K67: Piyush | L67: Phase 02 | M67: Sadham | N67: Sundar | O67: Drum No:HT46596E24
A68: =+A67+1 -> 66 | B68: 5272 | C68: 45624 | D68: Billable | E68: AC_Cables | F68: 3CX240Sqmm A2XFY UNSCR ATR UV AF 3.3 KV | G68: Mtr | H68: 1010 | I68: 1010 | J68: Inqilab | K68: Piyush | L68: Phase 02 | M68: Sadham | N68: Sundar | O68: Drum No: HT46597E24
A69: =+A68+1 -> 67 | B69: 5273 | C69: 45624 | D69: Billable | E69: Safety_Equipments | F69: Safety Gumboot | G69: Set | H69: 3 | I69: 3 | J69: Udaratva | K69: Venugopal | L69: Phase 02 | M69: Sadham | N69: Sundar | O69: Debit
A70: =+A69+1 -> 68 | B70: 5274 | C70: 45625 | D70: Billable | E70: MMS_Fasteners | F70: HEX BOLT+NUT+REC.WSR+ 1SP WSR M-10x30 | G70: Set | H70: 23960 | I70: 23960 | J70: Inqilab | K70: Piyush | L70: Phase 02 | M70: Sadham | N70: Sundar
A71: =+A70+1 -> 69 | B71: 5275 | C71: 45627 | D71: Billable | E71: DC_Cables | F71: 1CX6Sqmm DC Cable Black | G71: Mtr | H71: 1993 | I71: 1993 | J71: Udaratva | K71: Venugopal | L71: Phase 02 | M71: Sadham | N71: Sundar | O71: Drum No:4520101001/39
A72: =+A71+1 -> 70 | B72: 5275 | C72: 45627 | D72: Billable | E72: DC_Cables | F72: 1CX6Sqmm DC Cable Red | G72: Mtr | H72: 2014 | I72: 2014 | J72: Udaratva | K72: Venugopal | L72: Phase 02 | M72: Sadham | N72: Sundar | O72: Drum No: 4526402000/39
A73: =+A72+1 -> 71 | B73: 5276 | C73: 45627 | D73: Billable | E73: DC_Cables | F73: 1CX6Sqmm DC Cable Black | G73: Mtr | H73: 2020 | I73: 2020 | J73: Inqilab | K73: Piyush | L73: Phase 02 | M73: Sadham | N73: Sundar | O73: Drum No:4526401001/38
A74: =+A73+1 -> 72 | B74: 5276 | C74: 45627 | D74: Billable | E74: DC_Cables | F74: 1CX6Sqmm DC Cable Black | G74: Mtr | H74: 2011 | I74: 2011 | J74: Inqilab | K74: Piyush | L74: Phase 02 | M74: Sadham | N74: Sundar | O74: Drum No:4526401001/39
A75: =+A74+1 -> 73 | B75: 5276 | C75: 45627 | D75: Billable | E75: DC_Cables | F75: 1CX6Sqmm DC Cable Red | G75: Mtr | H75: 2010 | I75: 2010 | J75: Inqilab | K75: Piyush | L75: Phase 02 | M75: Sadham | N75: Sundar | O75: Drum No:4526402001/37
A76: =+A75+1 -> 74 | B76: 5276 | C76: 45627 | D76: Billable | E76: DC_Cables | F76: 1CX6Sqmm DC Cable Red | G76: Mtr | H76: 2043 | I76: 2043 | J76: Inqilab | K76: Piyush | L76: Phase 02 | M76: Sadham | N76: Sundar | O76: Drum No:4526402001/42
A77: =+A76+1 -> 75 | B77: 5276 | C77: 45627 | D77: Billable | E77: DC_Cables | F77: 1CX6Sqmm DC Cable Red | G77: Mtr | H77: 2000 | I77: 2000 | J77: Inqilab | K77: Piyush | L77: Phase 02 | M77: Sadham | N77: Sundar | O77: Drum No:4526402001/41
A78: =+A77+1 -> 76 | B78: 5276 | C78: 45627 | D78: Billable | E78: DC_Cables | F78: 1CX6Sqmm DC Cable Red | G78: Mtr | H78: 2000 | I78: 2000 | J78: Inqilab | K78: Piyush | L78: Phase 02 | M78: Sadham | N78: Sundar | O78: Drum No:4526402001/40
A79: =+A78+1 -> 77 | B79: 5277 | C79: 45629 | D79: Billable | E79: AC_Cables | F79: 3CX240Sqmm A2XFY UNSCR ATR UV AF 3.3 KV | G79: Mtr | H79: 1009 | I79: 1009 | J79: Udaratva | K79: Venugopal | L79: Phase 02 | M79: Sadham | N79: Sundar | O79: Drum No:HT46578E24
A80: =+A79+1 -> 78 | B80: 5277 | C80: 45629 | D80: Billable | E80: AC_Cables | F80: 3CX240Sqmm A2XFY UNSCR ATR UV AF 3.3 KV | G80: Mtr | H80: 1002 | I80: 1002 | J80: Udaratva | K80: Venugopal | L80: Phase 02 | M80: Sadham | N80: Sundar | O80: Drum No:HT46521E24
A81: =+A80+1 -> 79 | B81: 5277 | C81: 45629 | D81: Billable | E81: AC_Cables | F81: 3CX240Sqmm A2XFY UNSCR ATR UV AF 3.3 KV | G81: Mtr | H81: 1007 | I81: 1007 | J81: Udaratva | K81: Venugopal | L81: Phase 02 | M81: Sadham | N81: Sundar | O81: Drum No:HT46581E24
A82: =+A81+1 -> 80 | B82: 5277 | C82: 45629 | D82: Billable | E82: AC_Cables | F82: 3CX240Sqmm A2XFY UNSCR ATR UV AF 3.3 KV | G82: Mtr | H82: 1004 | I82: 1004 | J82: Udaratva | K82: Venugopal | L82: Phase 02 | M82: Sadham | N82: Sundar | O82: Drum No:HT46577E24
A83: =+A82+1 -> 81 | B83: 5278 | C83: 45630 | D83: Billable | E83: Others | F83: Yellow Warning Tape (LT 2500 Mtr,DC 1000 Mtr,HT 500 Mtr) | G83: Mtr | H83: 500 | I83: 500 | J83: Inqilab | K83: Piyush | L83: Phase 02 | M83: Sadham | N83: Sundar
A84: =+A83+1 -> 82 | B84: 5278 | C84: 45630 | D84: Billable | E84: Pipes | F84: 50 MM Coupler | G84: Nos | H84: 25 | I84: 25 | J84: Inqilab | K84: Piyush | L84: Phase 02 | M84: Sadham | N84: Sundar
A85: =+A84+1 -> 83 | B85: 5280 | C85: 45631 | D85: Billable | E85: AC_Cables | F85: 3CX240Sqmm A2XFY UNSCR ATR UV AF 3.3 KV | G85: Mtr | H85: 1018 | I85: 1018 | J85: Udaratva | K85: Venugopal | L85: Phase 02 | M85: Sadham | N85: Sundar | O85: Drum No:HT46564E24
A86: =+A85+1 -> 84 | B86: 5281 | C86: 45631 | D86: Billable | E86: DC_Cables | F86: 1CX6Sqmm DC Cable Black | G86: Mtr | H86: 2010 | I86: 2010 | J86: Inqilab | K86: Piyush | L86: Phase 02 | M86: Sadham | N86: Sundar | O86: Drum No:4968201001/07
A87: =+A86+1 -> 85 | B87: 5281 | C87: 45631 | D87: Billable | E87: DC_Cables | F87: 1CX6Sqmm DC Cable Black | G87: Mtr | H87: 2010 | I87: 2010 | J87: Inqilab | K87: Piyush | L87: Phase 02 | M87: Sadham | N87: Sundar | O87: Drum No:4968201001/10
A88: =+A87+1 -> 86 | B88: 5282 | C88: 45632 | D88: Billable | E88: Pipes | F88: 38x50 OD DWC Pipe (500MTR) UV & Anti Rodent) | G88: Mtr | H88: 500 | I88: 500 | J88: Inqilab | K88: Piyush | L88: Phase 02 | M88: Sadham | N88: Sundar
A89: =+A88+1 -> 87 | B89: 5282 | C89: 45632 | D89: Billable | E89: Pipes | F89: 50 MM Tee | G89: Nos | H89: 50 | I89: 50 | J89: Inqilab | K89: Piyush | L89: Phase 02 | M89: Sadham | N89: Sundar
A90: =+A89+1 -> 88
A91: =+A90+1 -> 89
A92: =+A91+1 -> 90
A93: =+A92+1 -> 91
A94: =+A93+1 -> 92
A95: =+A94+1 -> 93
A96: =+A95+1 -> 94
A97: =+A96+1 -> 95
A98: =+A97+1 -> 96
A99: =+A98+1 -> 97
A100: =+A99+1 -> 98
A101: =+A100+1 -> 99
... A4941: =+A4940+1 -> 4939
A4942: 1
A4943: =+A4942+1 -> 2
A4944: =+A4943+1 -> 3
A4945: =+A4944+1 -> 4
A4946: =+A4945+1 -> 5
A4947: =+A4946+1 -> 6
A4948: =+A4947+1 -> 7
A4949: =+A4948+1 -> 8
A4950: =+A4949+1 -> 9
A4951: =+A4950+1 -> 10
A4952: =+A4951+1 -> 11
A4953: =+A4952+1 -> 12
A4954: =+A4953+1 -> 13
... A5012: =+A5011+1 -> 71

Sheet Goods Receipt
A3: S. No. | B3: Recd. Date | C3: Vendor Invoice No | D3: Vendor Invoice Date | E3: GRN | F3: GRN Date | G3: Supplier Name | H3: Item Category | I3: Item Type | J3: Item Description | K3: Unit | L3: Invoice. / Received Qty | M3: Accepted Qty | N3: Rejected/ Shortage Qty. | O3: LR No. | P3: LR. Date | Q3: Transporter Name | R3: Vechicle No | S3: P O No. | T3: P O Date. | U3: Received Qty | V3: Purchase unit | W3: Purchase Rate | X3: Purchase Amount | Y3: WAY BILL No. | Z3: Remarks | AB3: Price | AC3: Show
A4: 1 | B4: 45499 | C4: NSM01169/2024-25 | D4: 45498 | E4: 2 | F4: 45519 | H4: Billable | I4: Module_Mounting_Structure | J4: Column Post - 120x50x20x2.0 MM | K4: Nos | L4: 2160 | M4: 2160 | N4: =Goods_Receipt[[#This Row],[ Invoice. / Received Qty ]]-Goods_Receipt[[#This Row],[ Accepted Qty ]] -> 0 | O4: 42 | P4: 45498 | R4: GJ06AX9564 | S4: PGEL/24-25/1219 | T4: 45468 | Y4: 671757801051
A5: 2 | B5: 45499 | C5: NSM01169/2024-25 | D5: 45498 | E5: 2 | F5: 45519 | H5: Billable | I5: Module_Mounting_Structure | J5: Column Ext - 50x50x2.0 MM | K5: Nos | L5: 2160 | M5: 2160 | N5: =Goods_Receipt[[#This Row],[ Invoice. / Received Qty ]]-Goods_Receipt[[#This Row],[ Accepted Qty ]] -> 0 | O5: 42 | P5: 45498 | R5: GJ06AX9564 | S5: PGEL/24-25/1219 | T5: 45468 | Y5: 671757801051
A6: 3 | B6: 45503 | C6: NGF/0468/24-25 | D6: 45497 | E6: 3 | F6: 45519 | H6: Billable | I6: MMS_Fasteners | J6: HEX BOLT+NUT+2PLN WSR+1SP WSR M-16x40 | K6: Nos | L6: 4290 | M6: 4290 | N6: =Goods_Receipt[[#This Row],[ Invoice. / Received Qty ]]-Goods_Receipt[[#This Row],[ Accepted Qty ]] -> 0 | O6: 3631 | P6: 45497 | R6: HR69D3182 | S6: PGEL/24-25/1406 | T6: 45476 | Y6: 241799438896
A7: 4 | B7: 45503 | C7: NGF/0468/24-25 | D7: 45497 | E7: 3 | F7: 45519 | H7: Billable | I7: MMS_Fasteners | J7: HEX BOLT+NUT+2PLN WSR+1SP WSR M-10x30 | K7: Nos | L7: 12870 | M7: 12870 | N7: =Goods_Receipt[[#This Row],[ Invoice. / Received Qty ]]-Goods_Receipt[[#This Row],[ Accepted Qty ]] -> 0 | O7: 3631 | P7: 45497 | R7: HR69D3182 | S7: PGEL/24-25/1406 | T7: 45476 | Y7: 241799438896
A8: 5 | B8: 45503 | C8: NGF/0468/24-25 | D8: 45497 | E8: 3 | F8: 45519 | H8: Billable | I8: MMS_Fasteners | J8: HEX BOLT+NUT+2PLN WSR+1SP WSR M-12x30 | K8: Nos | L8: 54340 | M8: 54340 | N8: =Goods_Receipt[[#This Row],[ Invoice. / Received Qty ]]-Goods_Receipt[[#This Row],[ Accepted Qty ]] -> 0 | O8: 3631 | P8: 45497 | R8: HR69D3182 | S8: PGEL/24-25/1406 | T8: 45476 | Y8: 241799438896
A9: 6 | B9: 45503 | C9: NGF/0468/24-25 | D9: 45497 | E9: 3 | F9: 45519 | H9: Billable | I9: MMS_Fasteners | J9: HEX BOLT+NUT+REC.WSR+ 1SP WSR M-10x30 | K9: Nos | L9: 57200 | M9: 57200 | N9: =Goods_Receipt[[#This Row],[ Invoice. / Received Qty ]]-Goods_Receipt[[#This Row],[ Accepted Qty ]] -> 0 | O9: 3631 | P9: 45497 | R9: HR69D3182 | S9: PGEL/24-25/1406 | T9: 45476 | Y9: 241799438896
A10: 7 | B10: 45504 | C10: 24-25/231 | D10: 45500 | E10: 4 | F10: 45519 | H10: Billable | I10: MMS_Fasteners | J10: Rectangle Washer (40*20*11*3) Mechanical Plating | K10: Nos | L10: 114400 | M10: 114400 | N10: =Goods_Receipt[[#This Row],[ Invoice. / Received Qty ]]-Goods_Receipt[[#This Row],[ Accepted Qty ]] -> 0 | O10: 231 | P10: 45500 | R10: GJ06BX3206 | Y10: 381818012077
A11: 8 | B11: 45512 | C11: NGF/0517/24-25 | D11: 45509 | E11: 5 | F11: 45519 | H11: Billable | I11: MMS_Fasteners | J11: Hex Bolt,M8x20 | K11: Nos | L11: 80000 | M11: 80000 | N11: =Goods_Receipt[[#This Row],[ Invoice. / Received Qty ]]-Goods_Receipt[[#This Row],[ Accepted Qty ]] -> 0 | O11: 948094 | P11: 45509 | R11: GJ06AZ8868 | S11: PGEL/24-25/1406 | T11: 45476 | Y11: 251805544671
A12: 9 | B12: 45512 | C12: NGF/0517/24-25 | D12: 45509 | E12: 5 | F12: 45519 | H12: Billable | I12: MMS_Fasteners | J12: Hex Bolt,M8x20 | K12: Nos | L12: 1510 | M12: 1510 | N12: =Goods_Receipt[[#This Row],[ Invoice. / Received Qty ]]-Goods_Receipt[[#This Row],[ Accepted Qty ]] -> 0 | O12: 948094 | P12: 45509 | R12: GJ06AZ8868 | S12: PGEL/24-25/1406 | T12: 45476 | Y12: 251805544671
A13: 10 | B13: 45512 | C13: NGF/0517/24-25 | D13: 45509 | E13: 5 | F13: 45519 | H13: Billable | I13: MMS_Fasteners | J13: Hex Nut,M8 | K13: Nos | L13: 1510 | M13: 1510 | N13: =Goods_Receipt[[#This Row],[ Invoice. / Received Qty ]]-Goods_Receipt[[#This Row],[ Accepted Qty ]] -> 0 | O13: 948094 | P13: 45509 | R13: GJ06AZ8868 | S13: PGEL/24-25/1406 | T13: 45476 | Y13: 251805544671
A14: 11 | B14: 45512 | C14: NGF/0517/24-25 | D14: 45509 | E14: 5 | F14: 45519 | H14: Billable | I14: MMS_Fasteners | J14: Hex Nut,M8 | K14: Nos | L14: 80000 | M14: 80000 | N14: =Goods_Receipt[[#This Row],[ Invoice. / Received Qty ]]-Goods_Receipt[[#This Row],[ Accepted Qty ]] -> 0 | O14: 948094 | P14: 45509 | R14: GJ06AZ8868 | S14: PGEL/24-25/1406 | T14: 45476 | Y14: 251805544671
A15: 12 | B15: 45512 | C15: NGF/0517/24-25 | D15: 45509 | E15: 5 | F15: 45519 | H15: Billable | I15: MMS_Fasteners | J15: Plain WSR,M8 | K15: Nos | L15: 163020 | M15: 163020 | N15: =Goods_Receipt[[#This Row],[ Invoice. / Received Qty ]]-Goods_Receipt[[#This Row],[ Accepted Qty ]] -> 0 | O15: 948094 | P15: 45509 | R15: GJ06AZ8868 | S15: PGEL/24-25/1406 | T15: 45476 | Y15: 251805544671
A16: 13 | B16: 45512 | C16: NGF/0517/24-25 | D16: 45509 | E16: 5 | F16: 45519 | H16: Billable | I16: MMS_Fasteners | J16: Spring WSRM8 | K16: Nos | L16: 40000 | M16: 40000 | N16: =Goods_Receipt[[#This Row],[ Invoice. / Received Qty ]]-Goods_Receipt[[#This Row],[ Accepted Qty ]] -> 0 | O16: 948094 | P16: 45509 | R16: GJ06AZ8868 | S16: PGEL/24-25/1406 | T16: 45476 | Y16: 251805544671
A17: 14 | B17: 45512 | C17: NGF/0517/24-25 | D17: 45509 | E17: 5 | F17: 45519 | H17: Billable | I17: MMS_Fasteners | J17: Spring WSRM8 | K17: Nos | L17: 41510 | M17: 41510 | N17: =Goods_Receipt[[#This Row],[ Invoice. / Received Qty ]]-Goods_Receipt[[#This Row],[ Accepted Qty ]] -> 0 | O17: 948094 | P17: 45509 | R17: GJ06AZ8868 | S17: PGEL/24-25/1406 | T17: 45476 | Y17: 251805544671
A18: 15 | B18: 45514 | D18: 45514 | E18: 31 | F18: 45519 | H18: Billable | I18: Inverter | J18: Solis 225K-EHV-5G Plus Grid Tie Solar PV Inverter | K18: Nos | L18: 3 | M18: 3 | N18: =Goods_Receipt[[#This Row],[ Invoice. / Received Qty ]]-Goods_Receipt[[#This Row],[ Accepted Qty ]] -> 0 | O18: 52422 | P18: 45514 | R18: GJ13AW0110 | S18: 4200052777 | T18: 45514 | Y18: 661765509003
A19: 16 | B19: 45514 | D19: 45514 | E19: 32 | F19: 45519 | H19: Billable | I19: Inverter | J19: Solis 225K-EHV-5G Plus Grid Tie Solar PV Inverter | K19: Nos | L19: 3 | M19: 3 | N19: =Goods_Receipt[[#This Row],[ Invoice. / Received Qty ]]-Goods_Receipt[[#This Row],[ Accepted Qty ]] -> 0 | O19: 52422 | P19: 45514 | R19: GJ13AW0110 | S19: 4200054306 | T19: 45514 | Y19: 661765509003
A20: 17 | B20: 45516 | C20: NSM01308/2024-25 | D20: 45514 | E20: 7 | F20: 45519 | H20: Billable | I20: Module_Mounting_Structure | J20: Module Mounting Strucyure - Purlin (P1) | K20: Nos | L20: 1799 | M20: 1799 | N20: =Goods_Receipt[[#This Row],[ Invoice. / Received Qty ]]-Goods_Receipt[[#This Row],[ Accepted Qty ]] -> 0 | O20: 46 | P20: 45514 | R20: GJ06BV5038 | S20: PGEL/24-25/1219 | T20: 45468 | Y20: 681765877331
A21: 18 | B21: 45516 | C21: NSM01308/2024-25 | D21: 45514 | E21: 7 | F21: 45519 | H21: Billable | I21: Module_Mounting_Structure | J21: Module Mounting Strucyure - Rafter | K21: Nos | L21: 1440 | M21: 1440 | N21: =Goods_Receipt[[#This Row],[ Invoice. / Received Qty ]]-Goods_Receipt[[#This Row],[ Accepted Qty ]] -> 0 | O21: 46 | P21: 45514 | R21: GJ06BV5038 | S21: PGEL/24-25/1219 | T21: 45468 | Y21: 681765877331
A22: 19 | B22: 45516 | C22: NSM01308/2024-25 | D22: 45514 | E22: 7 | F22: 45519 | H22: Billable | I22: Module_Mounting_Structure | J22: Module Mounting Strucyure - Rafter Bracing Back | K22: Nos | L22: 1600 | M22: 1600 | N22: =Goods_Receipt[[#This Row],[ Invoice. / Received Qty ]]-Goods_Receipt[[#This Row],[ Accepted Qty ]] -> 0 | O22: 46 | P22: 45514 | R22: GJ06BV5038 | S22: PGEL/24-25/1219 | T22: 45468 | Y22: 681765877331
A23: 20 | B23: 45516 | C23: NSM01313/2024-25 | D23: 45514 | E23: 8 | F23: 45519 | H23: Billable | I23: Module_Mounting_Structure | J23: Column Ext - 50x50x2.0 MM | K23: Nos | L23: 2051 | M23: 2051 | N23: =Goods_Receipt[[#This Row],[ Invoice. / Received Qty ]]-Goods_Receipt[[#This Row],[ Accepted Qty ]] -> 0 | O23: 48 | P23: 45514 | R23: GJ06AX6011 | S23: PGEL/24-25/1219 | T23: 45468 | Y23: 621765965485
A24: 21 | B24: 45516 | C24: NSM01312/2024-25 | D24: 45514 | E24: 9 | F24: 45519 | H24: Billable | I24: Module_Mounting_Structure | J24: Module Mounting Strucyure - Purlin (P1) | K24: Nos | L24: 1500 | M24: 1500 | N24: =Goods_Receipt[[#This Row],[ Invoice. / Received Qty ]]-Goods_Receipt[[#This Row],[ Accepted Qty ]] -> 0 | O24: 47 | P24: 45514 | R24: GJ06BV8011 | S24: PGEL/24-25/1219 | T24: 45468 | Y24: 631765939805
A25: 22 | B25: 45516 | C25: NSM01309/2024-25 | D25: 45514 | E25: 10 | F25: 45519 | H25: Billable | I25: Module_Mounting_Structure | J25: Column Post - 120x50x20x2.0 MM | K25: Nos | L25: 1957 | M25: 1957 | N25: =Goods_Receipt[[#This Row],[ Invoice. / Received Qty ]]-Goods_Receipt[[#This Row],[ Accepted Qty ]] -> 0 | O25: 17 | P25: 45514 | R25: GJ06BV6551 | S25: PGEL/24-25/1219 | T25: 45468 | Y25: 671765920731
A26: 23 | B26: 45516 | C26: NSM01309/2024-25 | D26: 45514 | E26: 10 | F26: 45519 | H26: Billable | I26: Module_Mounting_Structure | J26: Module Mounting Strucyure - Rafter Bracing Back | K26: Nos | L26: 800 | M26: 800 | N26: =Goods_Receipt[[#This Row],[ Invoice. / Received Qty ]]-Goods_Receipt[[#This Row],[ Accepted Qty ]] -> 0 | O26: 17 | P26: 45514 | R26: GJ06BV6551 | S26: PGEL/24-25/1219 | T26: 45468 | Y26: 671765920731
A27: 24 | B27: 45520 | C27: NSM01346/2024-25 | D27: 45518 | E27: 11 | F27: 45521 | H27: Billable | I27: Module_Mounting_Structure | J27: Module Mounting Strucyure - Purlin (P1) | K27: Nos | L27: 901 | M27: 901 | N27: =Goods_Receipt[[#This Row],[ Invoice. / Received Qty ]]-Goods_Receipt[[#This Row],[ Accepted Qty ]] -> 0 | O27: 50 | P27: 45518 | R27: GJ06BV8011 | S27: PGEL/24-25/1219 | T27: 45468 | Y27: 621767715961
A28: 25 | B28: 45520 | C28: NSM01346/2024-25 | D28: 45518 | E28: 11 | F28: 45521 | H28: Billable | I28: Module_Mounting_Structure | J28: Module Mounting Strucyure - Bracing Connector | K28: Nos | L28: 4335 | M28: 4335 | N28: =Goods_Receipt[[#This Row],[ Invoice. / Received Qty ]]-Goods_Receipt[[#This Row],[ Accepted Qty ]] -> 0 | O28: 50 | P28: 45518 | R28: GJ06BV8011 | S28: PGEL/24-25/1219 | T28: 45468 | Y28: 621767715961
A29: 26 | B29: 45520 | C29: NSM01347/2024-25 | D29: 45519 | E29: 12 | F29: 45521 | H29: Billable | I29: Module_Mounting_Structure | J29: Module Mounting Strucyure - Rafter | K29: Nos | L29: 1018 | M29: 1018 | N29: =Goods_Receipt[[#This Row],[ Invoice. / Received Qty ]]-Goods_Receipt[[#This Row],[ Accepted Qty ]] -> 0 | O29: 51 | P29: 45519 | R29: GJ06AX6011 | S29: PGEL/24-25/1219 | T29: 45468 | Y29: 611768017339
A30: 27 | B30: 45520 | C30: NSM01347/2024-25 | D30: 45519 | E30: 12 | F30: 45521 | H30: Billable | I30: Module_Mounting_Structure | J30: Module Mounting Strucyure - Rafter Bracing Back | K30: Nos | L30: 1200 | M30: 1200 | N30: =Goods_Receipt[[#This Row],[ Invoice. / Received Qty ]]-Goods_Receipt[[#This Row],[ Accepted Qty ]] -> 0 | O30: 51 | P30: 45519 | R30: GJ06AX6011 | S30: PGEL/24-25/1219 | T30: 45468 | Y30: 611768017339
A31: 28 | B31: 45520 | C31: NSM01341/2024-25 | D31: 45518 | E31: 13 | F31: 45521 | H31: Billable | I31: Module_Mounting_Structure | J31: Module Mounting Strucyure - Purlin (P2) | K31: Nos | L31: 1800 | M31: 1800 | N31: =Goods_Receipt[[#This Row],[ Invoice. / Received Qty ]]-Goods_Receipt[[#This Row],[ Accepted Qty ]] -> 0 | O31: 49 | P31: 45518 | R31: GJ06BV5038 | S31: PGEL/24-25/1219 | T31: 45468 | Y31: 641767596953
... A39: 36 | B39: 45520 | C39: NSM01348/2024-25 | D39: 45519 | E39: 14 | F39: 45521 | H39: Billable | I39: Module_Mounting_Structure | J39: Module Mounting Strucyure - Stay Bracing | K39: Nos | L39: 1431 | M39: 1431 | N39: =Goods_Receipt[[#This Row],[ Invoice. / Received Qty ]]-Goods_Receipt[[#This Row],[ Accepted Qty ]] -> 0 | O39: 49 | P39: 45519 | R39: GJ06AZ9564 | S39: PGEL/24-25/1219 | T39: 45468 | Y39: 641768018667
A40: 37 | B40: 45525 | C40: JE00071/24-25 | D40: 45524 | E40: 15 | F40: 45525 | H40: Billable | I40: Pipes | J40: 38x50 OD DWC Pipe (500MTR) UV & Anti Rodent) | K40: MTR | L40: 10000 | M40: 10000 | N40: =Goods_Receipt[[#This Row],[ Invoice. / Received Qty ]]-Goods_Receipt[[#This Row],[ Accepted Qty ]] -> 0 | O40: 63 | P40: 45524 | R40: GJ01FT7521 | S40: 2040/24-25 | Y40: 691769723228
A41: 38 | B41: 45525 | C41: JE00071/24-25 | D41: 45524 | E41: 15 | F41: 45525 | H41: Billable | I41: Pipes | J41: 50 MM Coupler | K41: Nos | L41: 300 | M41: 300 | N41: =Goods_Receipt[[#This Row],[ Invoice. / Received Qty ]]-Goods_Receipt[[#This Row],[ Accepted Qty ]] -> 0 | O41: 63 | P41: 45524 | R41: GJ01FT7521 | S41: 2040/24-25 | Y41: 691769723228
A42: 39 | B42: 45525 | C42: JE00071/24-25 | D42: 45524 | E42: 15 | F42: 45525 | H42: Billable | I42: Pipes | J42: 50 MM Elbow | K42: Nos | L42: 300 | M42: 300 | N42: =Goods_Receipt[[#This Row],[ Invoice. / Received Qty ]]-Goods_Receipt[[#This Row],[ Accepted Qty ]] -> 0 | O42: 63 | P42: 45524 | R42: GJ01FT7521 | S42: 2040/24-25 | Y42: 691769723228
A43: 40 | B43: 45525 | C43: JE00071/24-25 | D43: 45524 | E43: 15 | F43: 45525 | H43: Billable | I43: Pipes | J43: 50 MM Tee | K43: Nos | L43: 300 | M43: 300 | N43: =Goods_Receipt[[#This Row],[ Invoice. / Received Qty ]]-Goods_Receipt[[#This Row],[ Accepted Qty ]] -> 0 | O43: 63 | P43: 45524 | R43: GJ01FT7521 | S43: 2040/24-25 | Y43: 691769723228
A44: 41 | B44: 45525 | C44: JE00071/24-25 | D44: 45524 | E44: 15 | F44: 45525 | H44: Billable | I44: Pipes | J44: 50 MM O Ring | K44: Nos | L44: 300 | M44: 300 | N44: =Goods_Receipt[[#This Row],[ Invoice. / Received Qty ]]-Goods_Receipt[[#This Row],[ Accepted Qty ]] -> 0 | O44: 63 | P44: 45524 | R44: GJ01FT7521 | S44: 2040/24-25 | Y44: 691769723228
A45: 42 | B45: 45492 | C45: PGEPL/00157/24-25 | D45: 45490 | E45: 16 | F45: 45525 | H45: Billable | I45: Inverter | J45: Solis 225K-EHV-5G Plus Grid Tie Solar PV Inverter | K45: Nos | L45: 5 | M45: 5 | N45: =Goods_Receipt[[#This Row],[ Invoice. / Received Qty ]]-Goods_Receipt[[#This Row],[ Accepted Qty ]] -> 0 | O45: P/2776 | P45: 45490 | R45: GJ18BV0905 | T45: 45490 | Y45: 64175441616
A46: 43 | B46: 45533 | C46: DC/328/24-25 | D46: 45527 | E46: 17 | F46: 45534 | H46: Others | I46: Others | J46: Yellow Warning Tape (LT 2500 Mtr,DC 1000 Mtr,HT 500 Mtr) | K46: MTR | L46: 4000 | M46: 4000 | N46: =Goods_Receipt[[#This Row],[ Invoice. / Received Qty ]]-Goods_Receipt[[#This Row],[ Accepted Qty ]] -> 0 | O46: R100/1664180 | P46: 45527 | R46: GJ06AY0725 | S46: PGEL/24-25/2102 | T46: 45524 | Y46: 661771343891
A47: 44 | B47: 45533 | C47: DC/328/24-25 | D47: 45527 | E47: 17 | F47: 45534 | H47: Others | I47: Cable_Route_Marker | J47: LT Cable Route Marker | K47: Nos | L47: 240 | M47: 240 | N47: =Goods_Receipt[[#This Row],[ Invoice. / Received Qty ]]-Goods_Receipt[[#This Row],[ Accepted Qty ]] -> 0 | O47: R100/1664180 | P47: 45527 | R47: GJ06AY0725 | S47: PGEL/24-25/2102 | T47: 45524 | Y47: 661771343891
A48: 45 | B48: 45533 | C48: DC/328/24-25 | D48: 45527 | E48: 17 | F48: 45534 | H48: Others | I48: Cable_Route_Marker | J48: HT Cable Route Marker | K48: Nos | L48: 20 | M48: 20 | N48: =Goods_Receipt[[#This Row],[ Invoice. / Received Qty ]]-Goods_Receipt[[#This Row],[ Accepted Qty ]] -> 0 | O48: R100/1664180 | P48: 45527 | R48: GJ06AY0725 | S48: PGEL/24-25/2102 | T48: 45524 | Y48: 661771343891
A49: 46 | B49: 45533 | C49: DC/328/24-25 | D49: 45527 | E49: 17 | F49: 45534 | H49: Others | I49: Cable_Route_Marker | J49: DC Cable Route Marker | K49: Nos | L49: 80 | M49: 80 | N49: =Goods_Receipt[[#This Row],[ Invoice. / Received Qty ]]-Goods_Receipt[[#This Row],[ Accepted Qty ]] -> 0 | O49: R100/1664180 | P49: 45527 | R49: GJ06AY0725 | S49: PGEL/24-25/2102 | T49: 45524 | Y49: 661771343891
A50: 47 | B50: 45536 | C50: VSI/24-25/1121 | D50: 45530 | E50: 19 | F50: 45536 | H50: Billable | I50: Inverters_Structure | J50: Inverter Column Post (ISMC - 100x50x5mm - 3000mmL | K50: Nos | L50: 88 | M50: 88 | N50: =Goods_Receipt[[#This Row],[ Invoice. / Received Qty ]]-Goods_Receipt[[#This Row],[ Accepted Qty ]] -> 0 | O50: 477 | P50: 45530 | R50: UP15ET1476 | S50: PGEL/24-25/1730 | T50: 45497 | Y50: 421472569853
A51: 48 | B51: 45536 | C51: VSI/24-25/1121 | D51: 45530 | E51: 19 | F51: 45536 | H51: Billable | I51: Inverters_Structure | J51: Inverter Support Pipe (SHS-40x40x2.5mm-1550mmL | K51: Nos | L51: 88 | M51: 88 | N51: =Goods_Receipt[[#This Row],[ Invoice. / Received Qty ]]-Goods_Receipt[[#This Row],[ Accepted Qty ]] -> 0 | O51: 477 | P51: 45530 | R51: UP15ET1476 | S51: PGEL/24-25/1730 | T51: 45497 | Y51: 421472569853
A52: 49 | B52: 45536 | C52: VSI/24-25/1121 | D52: 45530 | E52: 19 | F52: 45536 | H52: Billable | I52: Inverters_Structure | J52: Roof Support -1 (ISA 40x40x5mm - 600mm L | K52: Nos | L52: 88 | M52: 88 | N52: =Goods_Receipt[[#This Row],[ Invoice. / Received Qty ]]-Goods_Receipt[[#This Row],[ Accepted Qty ]] -> 0 | O52: 477 | P52: 45530 | R52: UP15ET1476 | S52: PGEL/24-25/1730 | T52: 45497 | Y52: 421472569853
A53: 50 | B53: 45536 | C53: VSI/24-25/1121 | D53: 45530 | E53: 19 | F53: 45536 | H53: Billable | I53: Inverters_Structure | J53: Roof Support -2 (ISA 40x40x5mm - 700mm L | K53: Nos | L53: 88 | M53: 88 | N53: =Goods_Receipt[[#This Row],[ Invoice. / Received Qty ]]-Goods_Receipt[[#This Row],[ Accepted Qty ]] -> 0 | O53: 477 | P53: 45530 | R53: UP15ET1476 | S53: PGEL/24-25/1730 | T53: 45497 | Y53: 421472569853
A54: 51 | B54: 45536 | C54: VSI/24-25/1121 | D54: 45530 | E54: 19 | F54: 45536 | H54: Billable | I54: Inverters_Structure | J54: Roof Support -3 (ISA 40x40x5mm - 644mm L | K54: Nos | L54: 88 | M54: 88 | N54: =Goods_Receipt[[#This Row],[ Invoice. / Received Qty ]]-Goods_Receipt[[#This Row],[ Accepted Qty ]] -> 0 | O54: 477 | P54: 45530 | R54: UP15ET1476 | S54: PGEL/24-25/1730 | T54: 45497 | Y54: 421472569853
A55: 52 | B55: 45536 | C55: VSI/24-25/1121 | D55: 45530 | E55: 19 | F55: 45536 | H55: Billable | I55: Inverters_Structure | J55: Purlin (SHA-30x30x2.5mm - 2200mm L | K55: Nos | L55: 88 | M55: 88 | N55: =Goods_Receipt[[#This Row],[ Invoice. / Received Qty ]]-Goods_Receipt[[#This Row],[ Accepted Qty ]] -> 0 | O55: 477 | P55: 45530 | R55: UP15ET1476 | S55: PGEL/24-25/1730 | T55: 45497 | Y55: 421472569853
A56: 53 | B56: 45536 | C56: VSI/24-25/1121 | D56: 45530 | E56: 19 | F56: 45536 | H56: Billable | I56: Inverters_Structure | J56: Conduit Support Pipe (SHS-40x40x2.5mm - 1550mm L | K56: Nos | L56: 44 | M56: 44 | N56: =Goods_Receipt[[#This Row],[ Invoice. / Received Qty ]]-Goods_Receipt[[#This Row],[ Accepted Qty ]] -> 0 | O56: 477 | P56: 45530 | R56: UP15ET1476 | S56: PGEL/24-25/1730 | T56: 45497 | Y56: 421472569853
A57: 54 | B57: 45536 | C57: VSI/24-25/1121 | D57: 45530 | E57: 19 | F57: 45536 | H57: Billable | I57: Inverters_Structure | J57: Roof Sheet (1200x2400x0.5mm) | K57: Nos | L57: 44 | M57: 44 | N57: =Goods_Receipt[[#This Row],[ Invoice. / Received Qty ]]-Goods_Receipt[[#This Row],[ Accepted Qty ]] -> 0 | O57: 477 | P57: 45530 | R57: UP15ET1476 | S57: PGEL/24-25/1730 | T57: 45497 | Y57: 421472569853
A58: 55 | B58: 45536 | C58: VSI/24-25/1121 | D58: 45530 | E58: 19 | F58: 45536 | H58: Billable | I58: Inverters_Structure | J58: SS-304 (M12x80(SS-304-80mm L | K58: Nos | L58: 440 | M58: 440 | N58: =Goods_Receipt[[#This Row],[ Invoice. / Received Qty ]]-Goods_Receipt[[#This Row],[ Accepted Qty ]] -> 0 | O58: 477 | P58: 45530 | R58: UP15ET1476 | S58: PGEL/24-25/1730 | T58: 45497 | Y58: 421472569853
A59: 56 | B59: 45536 | C59: VSI/24-25/1121 | D59: 45530 | E59: 19 | F59: 45536 | H59: Billable | I59: Inverters_Structure | J59: SS-304 (M10x80(SS-304-80mm L | K59: Nos | L59: 352 | M59: 352 | N59: =Goods_Receipt[[#This Row],[ Invoice. / Received Qty ]]-Goods_Receipt[[#This Row],[ Accepted Qty ]] -> 0 | O59: 477 | P59: 45530 | R59: UP15ET1476 | S59: PGEL/24-25/1730 | T59: 45497 | Y59: 421472569853
A60: 57 | B60: 45536 | C60: VSI/24-25/1121 | D60: 45530 | E60: 19 | F60: 45536 | H60: Billable | I60: Inverters_Structure | J60: SDS with EPDM washer | K60: Set | L60: 440 | M60: 440 | N60: =Goods_Receipt[[#This Row],[ Invoice. / Received Qty ]]-Goods_Receipt[[#This Row],[ Accepted Qty ]] -> 0 | O60: 477 | P60: 45530 | R60: UP15ET1476 | S60: PGEL/24-25/1730 | T60: 45497 | Y60: 421472569853
A61: 58 | B61: 45545 | C61: SGI/M/24-25/240 | D61: 45544 | E61: 20/21 | F61: 45545 | H61: Billable | I61: Lighting_arrestor | J61: ESE Train | K61: Nos | L61: 6 | M61: 6 | N61: =Goods_Receipt[[#This Row],[ Invoice. / Received Qty ]]-Goods_Receipt[[#This Row],[ Accepted Qty ]] -> 0 | O61: 55378275 | P61: 45544 | R61: GJ34T3549 | S61: PGEL/24-25/1998 | T61: 45538 | Y61: 281823086576
A62: 59 | B62: 45545 | C62: SGI/M/24-25/240 | D62: 45544 | E62: 20/21 | F62: 45545 | H62: Billable | I62: Lighting_arrestor | J62: 6MM Guy Rope | K62: MTR | L62: 126 | M62: 126 | N62: =Goods_Receipt[[#This Row],[ Invoice. / Received Qty ]]-Goods_Receipt[[#This Row],[ Accepted Qty ]] -> 0 | O62: 55378275 | P62: 45544 | R62: GJ34T3549 | S62: PGEL/24-25/1998 | T62: 45538 | Y62: 281823086576
A63: 60 | B63: 45545 | C63: SGI/M/24-25/240 | D63: 45544 | E63: 20/21 | F63: 45545 | H63: Billable | I63: Lighting_arrestor | J63: 6MM U Clamp | K63: Nos | L63: 72 | M63: 72 | N63: =Goods_Receipt[[#This Row],[ Invoice. / Received Qty ]]-Goods_Receipt[[#This Row],[ Accepted Qty ]] -> 0 | O63: 55378275 | P63: 45544 | R63: GJ34T3549 | S63: PGEL/24-25/1998 | T63: 45538 | Y63: 281823086576
A64: 61 | B64: 45545 | C64: SGI/M/24-25/240 | D64: 45544 | E64: 20/21 | F64: 45545 | H64: Billable | I64: Lighting_arrestor | J64: Grount Hook for fixing guy cable | K64: Nos | L64: 18 | M64: 18 | N64: =Goods_Receipt[[#This Row],[ Invoice. / Received Qty ]]-Goods_Receipt[[#This Row],[ Accepted Qty ]] -> 0 | O64: 55378275 | P64: 45544 | R64: GJ34T3549 | S64: PGEL/24-25/1998 | T64: 45538 | Y64: 281823086576
A65: 62 | B65: 45545 | C65: SGI/M/24-25/240 | D65: 45544 | E65: 20/21 | F65: 45545 | H65: Billable | I65: Lighting_arrestor | J65: J bolt (dia 18x500mm) for fixing mast base plate hole | K65: Nos | L65: 24 | M65: 24 | N65: =Goods_Receipt[[#This Row],[ Invoice. / Received Qty ]]-Goods_Receipt[[#This Row],[ Accepted Qty ]] -> 0 | O65: 55378275 | P65: 45544 | R65: GJ34T3549 | S65: PGEL/24-25/1998 | T65: 45538 | Y65: 281823086576
A66: 63 | B66: 45545 | C66: SGI/M/24-25/240 | D66: 45544 | E66: 20/21 | F66: 45545 | H66: Billable | I66: Lighting_arrestor | J66: Down Conductor insulator BC 525 with nut bolt | K66: Nos | L66: 42 | M66: 42 | N66: =Goods_Receipt[[#This Row],[ Invoice. / Received Qty ]]-Goods_Receipt[[#This Row],[ Accepted Qty ]] -> 0 | O66: 55378275 | P66: 45544 | R66: GJ34T3549 | S66: PGEL/24-25/1998 | T66: 45538 | Y66: 281823086576
A67: 64 | B67: 45545 | C67: SGI/M/24-25/240 | D67: 45544 | E67: 20/21 | F67: 45545 | H67: Billable | I67: Lighting_arrestor | J67: OTC 25x3 | K67: Nos | L67: 6 | M67: 6 | N67: =Goods_Receipt[[#This Row],[ Invoice. / Received Qty ]]-Goods_Receipt[[#This Row],[ Accepted Qty ]] -> 0 | O67: 55378275 | P67: 45544 | R67: GJ34T3549 | S67: PGEL/24-25/1998 | T67: 45538 | Y67: 281823086576
A68: 65 | B68: 45545 | C68: SGI/M/24-25/240 | D68: 45544 | E68: 20/21 | F68: 45545 | H68: Billable | I68: Lighting_arrestor | J68: L shape | K68: Nos | L68: 6 | M68: 6 | N68: =Goods_Receipt[[#This Row],[ Invoice. / Received Qty ]]-Goods_Receipt[[#This Row],[ Accepted Qty ]] -> 0 | O68: 55378275 | P68: 45544 | R68: GJ34T3549 | S68: PGEL/24-25/1998 | T68: 45538 | Y68: 281823086576
A69: 66 | B69: 45545 | C69: SGI/M/24-25/240 | D69: 45544 | E69: 20/21 | F69: 45545 | H69: Billable | I69: Lighting_arrestor | J69: Lightning flash counter | K69: Nos | L69: 6 | M69: 6 | N69: =Goods_Receipt[[#This Row],[ Invoice. / Received Qty ]]-Goods_Receipt[[#This Row],[ Accepted Qty ]] -> 0 | O69: 55378275 | P69: 45544 | R69: GJ34T3549 | S69: PGEL/24-25/1998 | T69: 45538 | Y69: 281823086576
A70: 67 | B70: 45545 | C70: SGI/M/24-25/240 | D70: 45544 | E70: 20/21 | F70: 45545 | H70: Billable | I70: Lighting_arrestor | J70: GI supporting mast of 7 mtrs in 3 parts with base plate | K70: Nos | L70: 6 | M70: 6 | N70: =Goods_Receipt[[#This Row],[ Invoice. / Received Qty ]]-Goods_Receipt[[#This Row],[ Accepted Qty ]] -> 0 | O70: 55378275 | P70: 45544 | R70: GJ34T3549 | S70: PGEL/24-25/1998 | T70: 45538 | Y70: 281823086576
A71: 68 | B71: 45545 | C71: SGI/M/24-25/240 | D71: 45544 | E71: 20/21 | F71: 45545 | H71: Billable | I71: Lighting_arrestor | J71: 17mm dia, 3mtr long copper bonded rod with clamp with nut and bolt,plain & spring | K71: Nos | L71: 92 | M71: 92 | N71: =Goods_Receipt[[#This Row],[ Invoice. / Received Qty ]]-Goods_Receipt[[#This Row],[ Accepted Qty ]] -> 0 | O71: 55378275 | P71: 45544 | R71: GJ34T3549 | S71: PGEL/24-25/1998 | T71: 45538 | Y71: 281823086576
A72: 69 | B72: 45545 | C72: SGI/M/24-25/240 | D72: 45544 | E72: 20/21 | F72: 45545 | H72: Billable | I72: Lighting_arrestor | J72: Earthcon | K72: Bag | L72: 184 | M72: 184 | O72: 55378275 | P72: 45544 | R72: GJ34T3549 | S72: PGEL/24-25/1998 | T72: 45538 | Y72: 281823086576
A73: 70 | B73: 45547 | C73: PGEPL/0195/24-25 | D73: 45546 | E73: 22 | F73: 45548 | H73: Billable | I73: Earthing | J73: 25x3 MM GI Earth Strip | K73: KGS | L73: 2500 | M73: 2500 | N73: =Goods_Receipt[[#This Row],[ Invoice. / Received Qty ]]-Goods_Receipt[[#This Row],[ Accepted Qty ]] -> 0 | O73: 156 | P73: 45546 | R73: GJ17XX0436 | Y73: 671780188963
A74: 71 | B74: 45547 | C74: PGEPL/0195/24-25 | D74: 45546 | E74: 22 | F74: 45548 | H74: Billable | I74: DC_Cables | J74: 1CX6Sqmm DC Cable Black | K74: MTR | L74: 1000 | M74: 1000 | N74: =Goods_Receipt[[#This Row],[ Invoice. / Received Qty ]]-Goods_Receipt[[#This Row],[ Accepted Qty ]] -> 0 | O74: 156 | P74: 45546 | R74: GJ17XX0436 | Y74: 671780188963 | Z74: O/M
A75: 72 | B75: 45547 | C75: PGEPL/0195/24-25 | D75: 45546 | E75: 22 | F75: 45548 | H75: Billable | I75: DC_Cables | J75: 1CX6Sqmm DC Cable Red | K75: MTR | L75: 1000 | M75: 1000 | O75: 156 | P75: 45546 | R75: GJ17XX0436 | Y75: 671780188963 | Z75: O/M
A76: 73 | B76: 45547 | C76: PGEPL/0195/24-25 | D76: 45546 | E76: 22 | F76: 45548 | H76: Billable | I76: Others | J76: 300mm AL Rail | K76: Nos | L76: 600 | M76: 600 | N76: =Goods_Receipt[[#This Row],[ Invoice. / Received Qty ]]-Goods_Receipt[[#This Row],[ Accepted Qty ]] -> 0 | O76: 156 | P76: 45546 | R76: GJ17XX0436 | Y76: 671780188963
A77: 74 | B77: 45547 | C77: PGEPL/0195/24-25 | D77: 45546 | E77: 22 | F77: 45548 | H77: Billable | I77: Others | J77: Portr.High | K77: Nos | L77: 2000 | M77: 2000 | N77: =Goods_Receipt[[#This Row],[ Invoice. / Received Qty ]]-Goods_Receipt[[#This Row],[ Accepted Qty ]] -> 0 | O77: 156 | P77: 45546 | R77: GJ17XX0436 | Y77: 671780188963
A78: 75 | B78: 45551 | C78: SPC100/24-25 | D78: 45549 | E78: 23 | F78: 45551 | H78: Assets | I78: Assets | J78: Store Container | K78: Nos | L78: 1 | M78: 1 | N78: =Goods_Receipt[[#This Row],[ Invoice. / Received Qty ]]-Goods_Receipt[[#This Row],[ Accepted Qty ]] -> 0 | O78: 52476 | P78: 45549 | R78: MH48CQ8282 | S78: PGEL/24-25/2301 | T78: 45538 | Y78: 6317 8183 5079
A79: 76 | B79: 45559 | C79: 961838576 | D79: 45558 | E79: 24 | F79: 45559 | H79: Billable | I79: DC_Cables | J79: 1CX6Sqmm DC Cable Black | K79: MTR | L79: 18090 | M79: 12062 | N79: =Goods_Receipt[[#This Row],[ Invoice. / Received Qty ]]-Goods_Receipt[[#This Row],[ Accepted Qty ]] -> 6028 | O79: 1523688 | P79: 45558 | R79: GJ23AW3736 | S79: PGEL/24-25/1623 | T79: 45491 | Y79: 6417 8614 5413 | Z79: 3 Drums 6028 Mtr Transfer to Ujjval alloys dunavada site
A80: 77 | B80: 45559 | C80: 961838576 | D80: 45558 | E80: 24 | F80: 45559 | H80: Billable | I80: DC_Cables | J80: 1CX6Sqmm DC Cable Red | K80: MTR | L80: 18107 | M80: 16107 | N80: =Goods_Receipt[[#This Row],[ Invoice. / Received Qty ]]-Goods_Receipt[[#This Row],[ Accepted Qty ]] -> 2000 | O80: 1523688 | P80: 45558 | R80: GJ23AW3736 | S80: PGEL/24-25/1623 | T80: 45491 | Y80: 6417 8614 5413 | Z80: 1 Drum 2000 Mtr Transfer to Ujjval alloys dunavada site
A81: 78 | B81: 45559 | C81: GT/1140 | D81: 45558 | E81: 25 | F81: 45559 | H81: Billable | I81: Cable_Tie | J81: 100X2.5MM UV Cable Tie Black | K81: Nos | L81: 25000 | M81: 25000 | N81: =Goods_Receipt[[#This Row],[ Invoice. / Received Qty ]]-Goods_Receipt[[#This Row],[ Accepted Qty ]] -> 0 | S81: PGEL/24-25/2542
A82: 79 | B82: 45559 | C82: GT/1140 | D82: 45558 | E82: 25 | F82: 45559 | H82: Billable | I82: Cable_Tie | J82: 300X4.8MM UV Cable Tie Black | K82: Nos | L82: 10000 | M82: 10000 | N82: =Goods_Receipt[[#This Row],[ Invoice. / Received Qty ]]-Goods_Receipt[[#This Row],[ Accepted Qty ]] -> 0 | S82: PGEL/24-25/2542
A83: 80 | B83: 45559 | C83: GT/1140 | D83: 45558 | E83: 25 | F83: 45559 | H83: Billable | I83: Cable_Tie | J83: 300x4.6 SS Cable Tie | K83: Nos | L83: 800 | M83: 800 | N83: =Goods_Receipt[[#This Row],[ Invoice. / Received Qty ]]-Goods_Receipt[[#This Row],[ Accepted Qty ]] -> 0 | S83: PGEL/24-25/2542
A84: 81 | B84: 45562 | C84: PGEL/24-25/467 | D84: 45560 | E84: 26 | F84: 45563 | H84: Billable | I84: Inverter | J84: Solis 225K-EHV-5G Plus Grid Tie Solar PV Inverter | K84: Nos | L84: 41 | M84: 41 | N84: =Goods_Receipt[[#This Row],[ Invoice. / Received Qty ]]-Goods_Receipt[[#This Row],[ Accepted Qty ]] -> 0 | R84: MH48CB5913 NL01AB6673 | S84: 4200052777 | T84: 45560 | Y84: 6617 8723 2046
A85: 82 | B85: 45565 | C85: DD/118/2024-25 | D85: 45563 | E85: 28 | F85: 45565 | H85: Billable | I85: HT_Cables | J85: 3CX240Sqmm A2XFY 19/33KV HT Cable | K85: MTR | L85: 1512 | M85: 1512 | N85: =Goods_Receipt[[#This Row],[ Invoice. / Received Qty ]]-Goods_Receipt[[#This Row],[ Accepted Qty ]] -> 0 | O85: 23105 | P85: 45562 | R85: RJ01GC1981 | S85: PGEL/24-25/1720 | T85: 45496 | Y85: 7214 6267 6834
A86: 83 | B86: 45565 | C86: DD/117/2024-25 | D86: 45500 | E86: 29 | F86: 45565 | H86: Billable | I86: AC_Cables | J86: 3CX240Sqmm A2XFY UNSCR ATR UV AF 3.3 KV | K86: MTR | L86: 6042 | M86: 6042 | N86: =Goods_Receipt[[#This Row],[ Invoice. / Received Qty ]]-Goods_Receipt[[#This Row],[ Accepted Qty ]] -> 0 | O86: 8670998 | P86: 45561 | R86: HR69C5896 | S86: PGEL/24-25/1720 | T86: 45496 | Y86: 7314 6169 3387
A87: 84 | B87: 45565 | C87: DD/116/2024-25 | D87: 45562 | E87: 30 | F87: 45565 | H87: Billable | I87: AC_Cables | J87: 3CX240Sqmm A2XFY UNSCR ATR UV AF 3.3 KV | K87: MTR | L87: 6024 | M87: 6024 | N87: =Goods_Receipt[[#This Row],[ Invoice. / Received Qty ]]-Goods_Receipt[[#This Row],[ Accepted Qty ]] -> 0 | O87: 8670997 | P87: 45561 | R87: MH46BM9430 | S87: PGEL/24-25/1720 | T87: 45496 | Y87: 7514 6169 3383
A88: 85 | B88: 45576 | C88: 252401597 | D88: 45570 | E88: 33 | F88: 45576 | H88: Billable | I88: Safety_Equipments | J88: Sand Bucket With Stend canopy | K88: Nos | L88: 4 | M88: 4 | O88: 80039935 | P88: 45570 | R88: GJ06BT6816 | S88: PGEL/24-25/2686 | T88: 45561 | Y88: 6717 9317 6335
A89: 86 | B89: 45576 | C89: 252401597 | D89: 45570 | E89: 33 | F89: 45576 | H89: Billable | I89: Safety_Equipments | J89: CO2 Type Fire Extinguisher - 4.5 Kg | K89: Nos | L89: 44 | M89: 44 | N89: =Goods_Receipt[[#This Row],[ Invoice. / Received Qty ]]-Goods_Receipt[[#This Row],[ Accepted Qty ]] -> 0 | O89: 80039935 | P89: 45570 | R89: GJ06BT6816 | S89: PGEL/24-25/2686 | T89: 45561 | Y89: 6717 9317 6335
A90: 87 | B90: 45576 | C90: 252401597 | D90: 45570 | E90: 33 | F90: 45576 | H90: Billable | I90: Safety_Equipments | J90: CO2 Type Fire Extinguisher - 9 Kg | K90: Nos | L90: 4 | M90: 4 | N90: =Goods_Receipt[[#This Row],[ Invoice. / Received Qty ]]-Goods_Receipt[[#This Row],[ Accepted Qty ]] -> 0 | O90: 80039935 | P90: 45570 | R90: GJ06BT6816 | S90: PGEL/24-25/2686 | T90: 45561 | Y90: 6717 9317 6335
A91: 88 | B91: 45576 | C91: 252401597 | D91: 45570 | E91: 33 | F91: 45576 | H91: Billable | I91: Safety_Equipments | J91: ABC Type Fire Extinguisher - 6 Kg | K91: Nos | L91: 2 | M91: 2 | N91: =Goods_Receipt[[#This Row],[ Invoice. / Received Qty ]]-Goods_Receipt[[#This Row],[ Accepted Qty ]] -> 0 | O91: 80039935 | P91: 45570 | R91: GJ06BT6816 | S91: PGEL/24-25/2686 | T91: 45561 | Y91: 6717 9317 6335
A92: 89 | B92: 45582 | C92: G/0327 | D92: 45575 | E92: 34 | F92: 45583 | H92: Billable | I92: Earthing | J92: 25x3 MM GI Earth Strip | K92: Kg | L92: 2100 | M92: 2100 | N92: =Goods_Receipt[[#This Row],[ Invoice. / Received Qty ]]-Goods_Receipt[[#This Row],[ Accepted Qty ]] -> 0 | R92: GJ02AT5581 | S92: PGEL/24-25/2649 | T92: 45560 | Y92: 6017 9878 5094
A93: 90 | B93: 45582 | C93: G/0327 | D93: 45575 | E93: 34 | F93: 45583 | H93: Billable | I93: Earthing | J93: 50x6 MM GI Earth Strip | K93: Kg | L93: 6070 | M93: 6070 | N93: =Goods_Receipt[[#This Row],[ Invoice. / Received Qty ]]-Goods_Receipt[[#This Row],[ Accepted Qty ]] -> 0 | R93: GJ02AT5581 | S93: PGEL/24-25/2649 | T93: 45560 | Y93: 6017 9878 5094
A94: 91 | B94: 45582 | C94: G/0327 | D94: 45575 | E94: 34 | F94: 45583 | H94: Billable | I94: Earthing | J94: 40x6 MM Copper Earth Strip | K94: MTR | L94: 110 | M94: 110 | N94: =Goods_Receipt[[#This Row],[ Invoice. / Received Qty ]]-Goods_Receipt[[#This Row],[ Accepted Qty ]] -> 0 | R94: GJ02AT5581 | S94: PGEL/24-25/2649 | T94: 45560 | Y94: 6017 9878 5094
A95: 92 | B95: 45586 | C95: 20240312 | D95: 45586 | E95: 35 | F95: 45586 | H95: Billable | I95: Aux_UPS_Panel | J95: AUX ACDB Panel | K95: Nos | L95: 2 | M95: 2 | N95: =Goods_Receipt[[#This Row],[ Invoice. / Received Qty ]]-Goods_Receipt[[#This Row],[ Accepted Qty ]] -> 0 | R95: GJ2TTT9145 | S95: PGEL/24-25/1661 | T95: 45495 | Y95: 6218 0139 2084
A96: 93 | B96: 45586 | C96: 20240312 | D96: 45586 | E96: 35 | F96: 45586 | H96: Billable | I96: Aux_UPS_Panel | J96: UPS Panel | K96: Nos | L96: 2 | M96: 2 | N96: =Goods_Receipt[[#This Row],[ Invoice. / Received Qty ]]-Goods_Receipt[[#This Row],[ Accepted Qty ]] -> 0 | R96: GJ2TTT9145 | S96: PGEL/24-25/1661 | T96: 45495 | Y96: 6218 0139 2084
A97: 94 | B97: 45587 | C97: EPPL/M/395/2425 | D97: 45586 | E97: 36 | F97: 45587 | H97: Billable | I97: LT_Panel | J97: 800V LT Panel | K97: Nos | L97: 4 | M97: 4 | N97: =Goods_Receipt[[#This Row],[ Invoice. / Received Qty ]]-Goods_Receipt[[#This Row],[ Accepted Qty ]] -> 0 | O97: BRD/24-25/761 | P97: 45586 | R97: GJ06AX4535 | S97: PGEL/24-25/1390 | T97: 45586 | Y97: 6918 0162 4467
A98: 95 | B98: 45588 | C98: 24FP1P1455 | D98: 45586 | E98: 37 | F98: 45588 | H98: Billable | I98: NIFPS | J98: N2 Fire Production System | K98: Nos | L98: 1 | M98: 1 | N98: =Goods_Receipt[[#This Row],[ Invoice. / Received Qty ]]-Goods_Receipt[[#This Row],[ Accepted Qty ]] -> 0 | O98: 1687 | P98: 45586 | R98: GJ16AV6709 | S98: PGEL/24-25/2006 | T98: 45512 | Y98: 2918 4676 8609
A99: 96 | B99: 45588 | C99: 24FP1P1455 | D99: 45586 | E99: 37 | F99: 45588 | H99: Billable | I99: NIFPS | J99: Fire Extingushing Cubicle | K99: Nos | L99: 1 | M99: 1 | N99: =Goods_Receipt[[#This Row],[ Invoice. / Received Qty ]]-Goods_Receipt[[#This Row],[ Accepted Qty ]] -> 0 | O99: 1687 | P99: 45586 | R99: GJ16AV6709 | S99: PGEL/24-25/2006 | T99: 45512 | Y99: 2918 4676 8609
A100: 97 | B100: 45588 | C100: 24FP1P1455 | D100: 45586 | E100: 37 | F100: 45588 | H100: Billable | I100: NIFPS | J100: Control Box | K100: Nos | L100: 1 | M100: 1 | N100: =Goods_Receipt[[#This Row],[ Invoice. / Received Qty ]]-Goods_Receipt[[#This Row],[ Accepted Qty ]] -> 0 | O100: 1687 | P100: 45586 | R100: GJ16AV6709 | S100: PGEL/24-25/2006 | T100: 45512 | Y100: 2918 4676 8609
A101: 98 | B101: 45588 | C101: 24FP1P1455 | D101: 45586 | E101: 37 | F101: 45588 | H101: Billable | I101: NIFPS | J101: Fire Detectors | K101: Nos | L101: 8 | M101: 8 | N101: =Goods_Receipt[[#This Row],[ Invoice. / Received Qty ]]-Goods_Receipt[[#This Row],[ Accepted Qty ]] -> 0 | O101: 1687 | P101: 45586 | R101: GJ16AV6709 | S101: PGEL/24-25/2006 | T101: 45512 | Y101: 2918 4676 8609
A102: 99 | B102: 45588 | C102: 24FP1P1455 | D102: 45586 | E102: 37 | F102: 45588 | H102: Billable | I102: NIFPS | J102: Signal Box | K102: Nos | L102: 1 | M102: 1 | O102: 1687 | P102: 45586 | R102: GJ16AV6709 | S102: PGEL/24-25/2006 | T102: 45512 | Y102: 2918 4676 8609
A103: 100 | B103: 45588 | C103: 24FP1P1455 | D103: 45586 | E103: 37 | F103: 45588 | H103: Billable | I103: NIFPS | J103: Transformer Conservator Isolation Valve | K103: Nos | L103: 1 | M103: 1 | N103: =Goods_Receipt[[#This Row],[ Invoice. / Received Qty ]]-Goods_Receipt[[#This Row],[ Accepted Qty ]] -> 0 | O103: 1687 | P103: 45586 | R103: GJ16AV6709 | S103: PGEL/24-25/2006 | T103: 45512 | Y103: 2918 4676 8609
A104: 101 | B104: 45588 | C104: 24FP1P1455 | D104: 45586 | E104: 37 | F104: 45588 | H104: Billable | I104: NIFPS | J104: Keys | K104: Nos | L104: 6 | M104: 6 | N104: =Goods_Receipt[[#This Row],[ Invoice. / Received Qty ]]-Goods_Receipt[[#This Row],[ Accepted Qty ]] -> 0 | O104: 1687 | P104: 45586 | R104: GJ16AV6709 | S104: PGEL/24-25/2006 | T104: 45512 | Y104: 2918 4676 8609
A105: 102 | B105: 45588 | C105: 24FP1P1455 | D105: 45586 | E105: 37 | F105: 45588 | H105: Billable | I105: NIFPS | J105: FS Cable | K105: MTR | L105: 40 | M105: 40 | N105: =Goods_Receipt[[#This Row],[ Invoice. / Received Qty ]]-Goods_Receipt[[#This Row],[ Accepted Qty ]] -> 0 | O105: 1687 | P105: 45586 | R105: GJ16AV6709 | S105: PGEL/24-25/2006 | T105: 45512 | Y105: 2918 4676 8609
A106: 103 | B106: 45588 | C106: 24FP1P1455 | D106: 45586 | E106: 37 | F106: 45588 | H106: Billable | I106: NIFPS | J106: Fire Detectors Cover | K106: Nos | L106: 8 | M106: 8 | N106: =Goods_Receipt[[#This Row],[ Invoice. / Received Qty ]]-Goods_Receipt[[#This Row],[ Accepted Qty ]] -> 0 | O106: 1687 | P106: 45586 | R106: GJ16AV6709 | S106: PGEL/24-25/2006 | T106: 45512 | Y106: 2918 4676 8609
A107: 104 | B107: 45588 | C107: 24FP1P1455 | D107: 45586 | E107: 37 | F107: 45588 | H107: Billable | I107: NIFPS | J107: FRLS 12 Core Cable | K107: MTR | L107: 50 | M107: 50 | N107: =Goods_Receipt[[#This Row],[ Invoice. / Received Qty ]]-Goods_Receipt[[#This Row],[ Accepted Qty ]] -> 0 | O107: 1687 | P107: 45586 | R107: GJ16AV6709 | S107: PGEL/24-25/2006 | T107: 45512 | Y107: 2918 4676 8609
A108: 105 | B108: 45588 | C108: 24FP1P1455 | D108: 45586 | E108: 37 | F108: 45588 | H108: Billable | I108: NIFPS | J108: FRLS 4 Core Cable | K108: MTR | L108: 50 | M108: 50 | N108: =Goods_Receipt[[#This Row],[ Invoice. / Received Qty ]]-Goods_Receipt[[#This Row],[ Accepted Qty ]] -> 0 | O108: 1687 | P108: 45586 | R108: GJ16AV6709 | S108: PGEL/24-25/2006 | T108: 45512 | Y108: 2918 4676 8609
A109: 106 | B109: 45588 | C109: 24FP1P1455 | D109: 45586 | E109: 37 | F109: 45588 | H109: Billable | I109: NIFPS | J109: Supply of Pipe Fittings | K109: Nos | L109: 1 | M109: 1 | N109: =Goods_Receipt[[#This Row],[ Invoice. / Received Qty ]]-Goods_Receipt[[#This Row],[ Accepted Qty ]] -> 0 | O109: 1687 | P109: 45586 | R109: GJ16AV6709 | S109: PGEL/24-25/2006 | T109: 45512 | Y109: 2918 4676 8609
...

Sheet BOQ
B1: PROJECT NAME : Alembic PH 2 _12MWp
B2: LOCATION : Vadodara Gujarat
A3: S.No | B3: Item Description | C3: Make / Vendor | D3: Unit | E3: BOQ | F3: Remarks
A4: A | B4: ='Master Data'!$AJ$2 -> Module_Mounting_Structure
A5: 1 | B5: ='Master Data'!$AJ3 -> Column Post - 120x50x20x2.0 MM | D5: Nos | E5: 4434
A6: 2 | B6: ='Master Data'!$AJ4 -> Column Ext - 50x50x2.0 MM | D6: Nos | E6: 4434
A7: 3 | B7: ='Master Data'!$AJ5 -> Module Mounting Strucyure - Purlin (P1) | D7: Nos | E7: 5912
A8: 4 | B8: ='Master Data'!$AJ6 -> Module Mounting Strucyure - Rafter | D8: Nos | E8: 4434
A9: 5 | B9: ='Master Data'!$AJ7 -> Module Mounting Strucyure - Rafter Bracing Back | D9: Nos | E9: 4434
A10: 6 | B10: ='Master Data'!$AJ8 -> Module Mounting Strucyure - Bracing Connector | D10: Nos | E10: 4434
A11: 7 | B11: ='Master Data'!$AJ9 -> Module Mounting Strucyure - Purlin (P2) | D11: Nos | E11: 2956
A12: 8 | B12: ='Master Data'!$AJ10 -> Module Mounting Strucyure - Col, to Rafter Bracing front | D12: Nos | E12: 4434
A13: 9 | B13: ='Master Data'!$AJ11 -> Module Mounting Strucyure - Stay Bracing | D13: Nos | E13: 1478
B14: ='Master Data'!$AJ14 -> 0
A15: B | B15: ='Master Data'!$AK$2 -> MMS_Fasteners
A16: 1 | B16: ='Master Data'!$AK3 -> HEX BOLT+NUT+2PLN WSR+1SP WSR M-16x40 | D16: Set | E16: 4434
A17: 2 | B17: ='Master Data'!$AK4 -> HEX BOLT+NUT+2PLN WSR+1SP WSR M-10x30 | D17: Set | E17: 13302
A18: 3 | B18: ='Master Data'!$AK5 -> HEX BOLT+NUT+2PLN WSR+1SP WSR M-12x30 | D18: Set | E18: 56164
A19: 4 | B19: ='Master Data'!$AK6 -> HEX BOLT+NUT+REC.WSR+ 1SP WSR M-10x30 | D19: Set | E19: 59120
A20: 5 | B20: ='Master Data'!$AK7 -> Rectangle Washer (40*20*11*3) Mechanical Plating | D20: Nos | E20: 118240
A21: 6 | B21: ='Master Data'!$AK8 -> Hex Bolt,M8x20 | D21: Nos | E21: 84246
A22: 7 | B22: ='Master Data'!$AK9 -> Hex Nut,M8 | D22: Nos | E22: 84246
A23: 8 | B23: ='Master Data'!$AK10 -> Plain WSR,M8 | D23: Nos | E23: 168492
A24: 9 | B24: ='Master Data'!$AK11 -> Spring WSRM8 | D24: Nos | E24: 84246
A25: 10 | B25: ='Master Data'!$AK12 -> M8 Serrated Washer | D25: Nos | E25: 42000
B26: 0
A27: C | B27: ='Master Data'!$AN$2 -> Solar_Modules
B28: ='Master Data'!$AN3 -> 0 | D28: Nos | E28: 20692
A29: D | B29: Cables
A30: D.1 | B30: ='Master Data'!$J$2 -> DC_Cables
A31: 1 | B31: ='Master Data'!$J4 -> 1CX6Sqmm DC Cable Black | D31: Mtr | E31: 17000
A32: 2 | B32: ='Master Data'!$J5 -> 1CX6Sqmm DC Cable Red | D32: Mtr | E32: 17000
B33: ='Master Data'!$J6 -> 0
A34: D.2 | B34: ='Master Data'!$K$2 -> AC_Cables
A35: 1 | B35: ='Master Data'!$K3 -> 3CX240Sqmm A2XFY UNSCR ATR UV AF 3.3 KV | D35: Mtr | E35: 9500
B36: ='Master Data'!$K4 -> 0
A37: D.3 | B37: ='Master Data'!$L$2 -> HT_Cables
A38: 1 | B38: ='Master Data'!$L3 -> 3CX240Sqmm A2XFY 19/33KV HT Cable | D38: Mtr | E38: 1400
B39: ='Master Data'!$L4 -> 0
A40: D.4 | B40: ='Master Data'!$M$2 -> Earthing_cables
A41: 1 | B41: ='Master Data'!$M3 -> 1C X 50Sq.mm Copper Flexible Cable | D41: Mtr | E41: 150
B42: 0
A43: D.5 | B43: ='Master Data'!$N$2 -> Aux_Control_Cable
A44: 1 | B44: 3C X 35Sq.mm 1.1 Kv A2XFY Cable | D44: Mtr | E44: 30
A45: 2 | B45: 4C X 6Sq.mm 1.1 Kv A2XWY Cable | D45: Mtr | E45: 3100
A46: 3 | B46: 2C X 6Sq.mm Flexible HRFR Cable | D46: Mtr | E46: 30
A47: 4 | B47: 2C X 4Sq.mm Copper Flexible Cable | D47: Mtr | E47: 2200
A48: 5 | B48: 2C X 2.5 Sq.mm Copper Flexible Cable | D48: Mtr | E48: 400
A49: 6 | B49: 12C X 2.5 Sq.mm 1.1 Kv 2XFY Cable | D49: Mtr | E49: 250
A50: 7 | B50: 3C X 4 Sq.mm Copper Flexible Cable | D50: Mtr | E50: 100
B51: 0
A52: D.6 | B52: ='Master Data'!$O$2 -> Communication_Cable
A53: 1 | B53: CAT-6 Cable | D53: Mtr | E53: 100
A54: 2 | B54: RS 485 ARM Cable | D54: Mtr | E54: 300
A55: 3 | B55: 12F FO Cable | D55: Mtr | E55: 1300
B56: 0
A57: E | B57: Equipment
A58: E-1 | B58: ='Master Data'!$Z$2 -> Inverter
A59: 1 | B59: ='Master Data'!$Z3 -> Solis 225K-EHV-5G Plus Grid Tie Solar PV Inverter | D59: Nos | E59: 44
B60: ='Master Data'!$Z4 -> 0
A61: E-2 | B61: ='Master Data'!$AC$2 -> LT_Panel
A62: 1 | B62: ='Master Data'!$AC3 -> 800V LT Panel | D62: Nos | E62: 4
B63: 0
A64: E-3 | B64: ='Master Data'!$AA$2 -> Transformers
A65: 1 | B65: 6 MVA Transformer | D65: Nos | E65: 2
A66: 2 | B66: Radiators | D66: Nos | E66: 16
A67: 3 | B67: Marshalling Box | D67: Nos | E67: 2
A68: 4 | B68: Conservator Tank With Accessories | D68: Nos | E68: 2
A69: 5 | B69: HV Cable Box & HV Cable Box Canopy Fitted | D69: Nos | E69: 2
A70: 6 | B70: 33Kv Insulators | D70: Nos | E70: 6
A71: 7 | B71: Aluminium Gland Plate | D71: Nos | E71: 2
A72: 8 | B72: Inspection Cover | D72: Nos | E72: 2
A73: 9 | B73: 50 X 06 mm Copper Flat | D73: Mtr | E73: 6
A74: 10 | B74: Danger Plate | D74: Nos | E74: 2
A75: 11 | B75: Breather | D75: Nos | E75: 2
A76: 12 | B76: Buchholz Relay & Buchholz Canopy | D76: Nos | E76: 2
... A78: 14 | B78: Transformer Oil | D78: Nos | E78: 14
B79: 0
A80: E-4 | B80: ='Master Data'!$AB$2 -> HT_Panel
A81: 1 | B81: ='Master Data'!$AB3 -> 33KV HT VCB Panel | D81: Nos | E81: 3
A82: 2 | B82: 33KV HT VCB Panel (21C-1OG) Board Panel | D82: Nos | E82: 1
B83: 0
A84: E-5 | B84: ='Master Data'!$AD$2 -> Aux_UPS_Panel
A85: 1 | B85: ='Master Data'!$AD3 -> AUX ACDB Panel | D85: Nos | E85: 2
A86: 2 | B86: UPS Panel | D86: Nos | E86: 2
B87: 0
A88: E-6 | B88: ='Master Data'!$AR$2 -> Scada
A89: 1 | B89: MCR Panel | D89: Nos | E89: 1
A90: 2 | B90: ICR Panel | D90: Nos | E90: 2
A91: 3 | B91: Operating Work Station With Pre Installation Software and keyboard &Mouse | D91: Nos | E91: 1
A92: 4 | B92: 32 Inch Display | D92: Nos | E92: 1
A93: 5 | B93: A4 Printer | D93: Nos | E93: 1
A94: 6 | B94: Wooden Table | D94: Nos | E94: 1
A95: 7 | B95: Chair | D95: Nos | E95: 1
A96: 8 | B96: SC-LC Patch Cord Single Mode | D96: Nos | E96: 6
B97: 0
A98: E-7 | B98: ='Master Data'!$AH$2 -> Lighting_arrestor
A99: 1 | B99: ='Master Data'!$AH3 -> ESE Train | D99: Nos | E99: 6
A100: 2 | B100: ='Master Data'!$AH4 -> 6MM Guy Rope | D100: Nos | E100: 126
A101: 3 | B101: ='Master Data'!$AH5 -> 6MM U Clamp | D101: Nos | E101: 72
...
